Source File: /data/islam/DBT-workbench/resources/subjects/fixed/jsoup/39/src/test/java/org/jsoup/helper/RegressionTest0.java
Bytecode File: /data/islam/DBT-workbench/resources/subjects/fixed/jsoup/39/target/test-classes/org/jsoup/helper/RegressionTest0.class
Class name: RegressionTest0
Method name: test01
Start line: 12
End line: 24
Method source code: 
    public void test01() throws Throwable {
        if (debug)
            System.out.format("%n%s%n", "RegressionTest0.test01");
        java.io.InputStream inputStream0 = null;
        org.jsoup.parser.Parser parser3 = null;
        // The following exception was thrown during execution in test generation
        try {
            org.jsoup.nodes.Document document4 = org.jsoup.helper.DataUtil.load(inputStream0, "", "", parser3);
            org.junit.Assert.fail("Expected exception of type java.lang.NullPointerException; message: null");
        } catch (java.lang.NullPointerException e) {
        // Expected exception.
        }
    }
Method byte code: 
0: getstatic     #2
3: ifeq          24
6: getstatic     #3
9: ldc           #4
11: iconst_1
12: anewarray     #5
15: dup
16: iconst_0
17: ldc           #6
19: aastore
20: invokevirtual #7
23: pop
24: aconst_null
25: astore_1
26: aconst_null
27: astore_2
28: aload_1
29: ldc           #8
31: ldc           #8
33: aload_2
34: invokestatic  #9
37: astore_3
38: ldc           #10
40: invokestatic  #11
43: goto          47
46: astore_3
47: return
Exception table:
from    to  target type
28    43    46   Class java/lang/NullPointerException
Source File: /data/islam/DBT-workbench/resources/subjects/fixed/jsoup/39/src/test/java/org/jsoup/helper/RegressionTest0.java
Bytecode File: /data/islam/DBT-workbench/resources/subjects/fixed/jsoup/39/target/test-classes/org/jsoup/helper/RegressionTest0.class
Class name: RegressionTest0
Method name: test02
Start line: 27
End line: 32
Method source code: 
    public void test02() throws Throwable {
        if (debug)
            System.out.format("%n%s%n", "RegressionTest0.test02");
        java.lang.String str1 = org.jsoup.helper.DataUtil.getCharsetFromContentType("hi!");
        org.junit.Assert.assertNull(str1);
    }
Method byte code: 
0: getstatic     #2
3: ifeq          24
6: getstatic     #3
9: ldc           #4
11: iconst_1
12: anewarray     #5
15: dup
16: iconst_0
17: ldc           #13
19: aastore
20: invokevirtual #7
23: pop
24: ldc           #14
26: invokestatic  #15
29: astore_1
30: aload_1
31: invokestatic  #16
34: return
Source File: /data/islam/DBT-workbench/resources/subjects/fixed/jsoup/39/src/test/java/org/jsoup/helper/RegressionTest0.java
Bytecode File: /data/islam/DBT-workbench/resources/subjects/fixed/jsoup/39/target/test-classes/org/jsoup/helper/RegressionTest0.class
Class name: RegressionTest0
Method name: test03
Start line: 35
End line: 47
Method source code: 
    public void test03() throws Throwable {
        if (debug)
            System.out.format("%n%s%n", "RegressionTest0.test03");
        java.io.InputStream inputStream0 = null;
        org.jsoup.parser.Parser parser3 = null;
        // The following exception was thrown during execution in test generation
        try {
            org.jsoup.nodes.Document document4 = org.jsoup.helper.DataUtil.load(inputStream0, ":gt(0)", "", parser3);
            org.junit.Assert.fail("Expected exception of type java.lang.NullPointerException; message: null");
        } catch (java.lang.NullPointerException e) {
        // Expected exception.
        }
    }
Method byte code: 
0: getstatic     #2
3: ifeq          24
6: getstatic     #3
9: ldc           #4
11: iconst_1
12: anewarray     #5
15: dup
16: iconst_0
17: ldc           #17
19: aastore
20: invokevirtual #7
23: pop
24: aconst_null
25: astore_1
26: aconst_null
27: astore_2
28: aload_1
29: ldc           #18
31: ldc           #8
33: aload_2
34: invokestatic  #9
37: astore_3
38: ldc           #10
40: invokestatic  #11
43: goto          47
46: astore_3
47: return
Exception table:
from    to  target type
28    43    46   Class java/lang/NullPointerException
Source File: /data/islam/DBT-workbench/resources/subjects/fixed/jsoup/39/src/test/java/org/jsoup/helper/RegressionTest0.java
Bytecode File: /data/islam/DBT-workbench/resources/subjects/fixed/jsoup/39/target/test-classes/org/jsoup/helper/RegressionTest0.class
Class name: RegressionTest0
Method name: test04
Start line: 50
End line: 61
Method source code: 
    public void test04() throws Throwable {
        if (debug)
            System.out.format("%n%s%n", "RegressionTest0.test04");
        java.io.InputStream inputStream0 = null;
        // The following exception was thrown during execution in test generation
        try {
            java.nio.ByteBuffer byteBuffer2 = org.jsoup.helper.DataUtil.readToByteBuffer(inputStream0, (int) 'a');
            org.junit.Assert.fail("Expected exception of type java.lang.NullPointerException; message: null");
        } catch (java.lang.NullPointerException e) {
        // Expected exception.
        }
    }
Method byte code: 
0: getstatic     #2
3: ifeq          24
6: getstatic     #3
9: ldc           #4
11: iconst_1
12: anewarray     #5
15: dup
16: iconst_0
17: ldc           #19
19: aastore
20: invokevirtual #7
23: pop
24: aconst_null
25: astore_1
26: aload_1
27: bipush        97
29: invokestatic  #20
32: astore_2
33: ldc           #10
35: invokestatic  #11
38: goto          42
41: astore_2
42: return
Exception table:
from    to  target type
26    38    41   Class java/lang/NullPointerException
Source File: /data/islam/DBT-workbench/resources/subjects/fixed/jsoup/39/src/test/java/org/jsoup/helper/RegressionTest0.java
Bytecode File: /data/islam/DBT-workbench/resources/subjects/fixed/jsoup/39/target/test-classes/org/jsoup/helper/RegressionTest0.class
Class name: RegressionTest0
Method name: test05
Start line: 64
End line: 75
Method source code: 
    public void test05() throws Throwable {
        if (debug)
            System.out.format("%n%s%n", "RegressionTest0.test05");
        java.io.InputStream inputStream0 = null;
        // The following exception was thrown during execution in test generation
        try {
            org.jsoup.nodes.Document document3 = org.jsoup.helper.DataUtil.load(inputStream0, "", ".");
            org.junit.Assert.fail("Expected exception of type java.lang.NullPointerException; message: null");
        } catch (java.lang.NullPointerException e) {
        // Expected exception.
        }
    }
Method byte code: 
0: getstatic     #2
3: ifeq          24
6: getstatic     #3
9: ldc           #4
11: iconst_1
12: anewarray     #5
15: dup
16: iconst_0
17: ldc           #21
19: aastore
20: invokevirtual #7
23: pop
24: aconst_null
25: astore_1
26: aload_1
27: ldc           #8
29: ldc           #22
31: invokestatic  #23
34: astore_2
35: ldc           #10
37: invokestatic  #11
40: goto          44
43: astore_2
44: return
Exception table:
from    to  target type
26    40    43   Class java/lang/NullPointerException
Source File: /data/islam/DBT-workbench/resources/subjects/fixed/jsoup/39/src/test/java/org/jsoup/helper/RegressionTest0.java
Bytecode File: /data/islam/DBT-workbench/resources/subjects/fixed/jsoup/39/target/test-classes/org/jsoup/helper/RegressionTest0.class
Class name: RegressionTest0
Method name: test06
Start line: 78
End line: 90
Method source code: 
    public void test06() throws Throwable {
        if (debug)
            System.out.format("%n%s%n", "RegressionTest0.test06");
        java.nio.ByteBuffer byteBuffer0 = null;
        org.jsoup.parser.Parser parser3 = null;
        // The following exception was thrown during execution in test generation
        try {
            org.jsoup.nodes.Document document4 = org.jsoup.helper.DataUtil.parseByteData(byteBuffer0, "[<html>\n <head></head>\n <body></body>\n</html>, <html>\n <head></head>\n <body></body>\n</html>, <html>\n <head></head>\n <body></body>\n</html>]", "#document", parser3);
            org.junit.Assert.fail("Expected exception of type java.nio.charset.IllegalCharsetNameException; message: [<html>? <head></head>? <body></body>?</html>, <html>? <head></head>? <body></body>?</html>, <html>? <head></head>? <body></body>?</html>]");
        } catch (java.nio.charset.IllegalCharsetNameException e) {
        // Expected exception.
        }
    }
Method byte code: 
0: getstatic     #2
3: ifeq          24
6: getstatic     #3
9: ldc           #4
11: iconst_1
12: anewarray     #5
15: dup
16: iconst_0
17: ldc           #24
19: aastore
20: invokevirtual #7
23: pop
24: aconst_null
25: astore_1
26: aconst_null
27: astore_2
28: aload_1
29: ldc           #25
31: ldc           #26
33: aload_2
34: invokestatic  #27
37: astore_3
38: ldc           #28
40: invokestatic  #11
43: goto          47
46: astore_3
47: return
Exception table:
from    to  target type
28    43    46   Class java/nio/charset/IllegalCharsetNameException
Source File: /data/islam/DBT-workbench/resources/subjects/fixed/jsoup/39/src/test/java/org/jsoup/helper/RegressionTest0.java
Bytecode File: /data/islam/DBT-workbench/resources/subjects/fixed/jsoup/39/target/test-classes/org/jsoup/helper/RegressionTest0.class
Class name: RegressionTest0
Method name: test07
Start line: 93
End line: 98
Method source code: 
    public void test07() throws Throwable {
        if (debug)
            System.out.format("%n%s%n", "RegressionTest0.test07");
        java.lang.String str1 = org.jsoup.helper.DataUtil.getCharsetFromContentType(".");
        org.junit.Assert.assertNull(str1);
    }
Method byte code: 
0: getstatic     #2
3: ifeq          24
6: getstatic     #3
9: ldc           #4
11: iconst_1
12: anewarray     #5
15: dup
16: iconst_0
17: ldc           #30
19: aastore
20: invokevirtual #7
23: pop
24: ldc           #22
26: invokestatic  #15
29: astore_1
30: aload_1
31: invokestatic  #16
34: return
Source File: /data/islam/DBT-workbench/resources/subjects/fixed/jsoup/39/src/test/java/org/jsoup/helper/RegressionTest0.java
Bytecode File: /data/islam/DBT-workbench/resources/subjects/fixed/jsoup/39/target/test-classes/org/jsoup/helper/RegressionTest0.class
Class name: RegressionTest0
Method name: test08
Start line: 101
End line: 113
Method source code: 
    public void test08() throws Throwable {
        if (debug)
            System.out.format("%n%s%n", "RegressionTest0.test08");
        java.nio.ByteBuffer byteBuffer0 = null;
        org.jsoup.parser.Parser parser3 = null;
        // The following exception was thrown during execution in test generation
        try {
            org.jsoup.nodes.Document document4 = org.jsoup.helper.DataUtil.parseByteData(byteBuffer0, "hi!", "[<html>\n <head></head>\n <body></body>\n</html>, <html>\n <head></head>\n <body></body>\n</html>, <html>\n <head></head>\n <body></body>\n</html>]", parser3);
            org.junit.Assert.fail("Expected exception of type java.nio.charset.IllegalCharsetNameException; message: hi!");
        } catch (java.nio.charset.IllegalCharsetNameException e) {
        // Expected exception.
        }
    }
Method byte code: 
0: getstatic     #2
3: ifeq          24
6: getstatic     #3
9: ldc           #4
11: iconst_1
12: anewarray     #5
15: dup
16: iconst_0
17: ldc           #31
19: aastore
20: invokevirtual #7
23: pop
24: aconst_null
25: astore_1
26: aconst_null
27: astore_2
28: aload_1
29: ldc           #14
31: ldc           #25
33: aload_2
34: invokestatic  #27
37: astore_3
38: ldc           #32
40: invokestatic  #11
43: goto          47
46: astore_3
47: return
Exception table:
from    to  target type
28    43    46   Class java/nio/charset/IllegalCharsetNameException
Source File: /data/islam/DBT-workbench/resources/subjects/fixed/jsoup/39/src/test/java/org/jsoup/helper/RegressionTest0.java
Bytecode File: /data/islam/DBT-workbench/resources/subjects/fixed/jsoup/39/target/test-classes/org/jsoup/helper/RegressionTest0.class
Class name: RegressionTest0
Method name: test09
Start line: 116
End line: 127
Method source code: 
    public void test09() throws Throwable {
        if (debug)
            System.out.format("%n%s%n", "RegressionTest0.test09");
        java.io.File file0 = null;
        // The following exception was thrown during execution in test generation
        try {
            org.jsoup.nodes.Document document3 = org.jsoup.helper.DataUtil.load(file0, "UTF-8", "[<html>\n <head></head>\n <body></body>\n</html>, <html>\n <head></head>\n <body></body>\n</html>, <html>\n <head></head>\n <body></body>\n</html>]");
            org.junit.Assert.fail("Expected exception of type java.lang.NullPointerException; message: null");
        } catch (java.lang.NullPointerException e) {
        // Expected exception.
        }
    }
Method byte code: 
0: getstatic     #2
3: ifeq          24
6: getstatic     #3
9: ldc           #4
11: iconst_1
12: anewarray     #5
15: dup
16: iconst_0
17: ldc           #33
19: aastore
20: invokevirtual #7
23: pop
24: aconst_null
25: astore_1
26: aload_1
27: ldc           #34
29: ldc           #25
31: invokestatic  #35
34: astore_2
35: ldc           #10
37: invokestatic  #11
40: goto          44
43: astore_2
44: return
Exception table:
from    to  target type
26    40    43   Class java/lang/NullPointerException
Source File: /data/islam/DBT-workbench/resources/subjects/fixed/jsoup/39/src/test/java/org/jsoup/helper/RegressionTest0.java
Bytecode File: /data/islam/DBT-workbench/resources/subjects/fixed/jsoup/39/target/test-classes/org/jsoup/helper/RegressionTest0.class
Class name: RegressionTest0
Method name: test10
Start line: 130
End line: 141
Method source code: 
    public void test10() throws Throwable {
        if (debug)
            System.out.format("%n%s%n", "RegressionTest0.test10");
        java.io.InputStream inputStream0 = null;
        // The following exception was thrown during execution in test generation
        try {
            java.nio.ByteBuffer byteBuffer1 = org.jsoup.helper.DataUtil.readToByteBuffer(inputStream0);
            org.junit.Assert.fail("Expected exception of type java.lang.NullPointerException; message: null");
        } catch (java.lang.NullPointerException e) {
        // Expected exception.
        }
    }
Method byte code: 
0: getstatic     #2
3: ifeq          24
6: getstatic     #3
9: ldc           #4
11: iconst_1
12: anewarray     #5
15: dup
16: iconst_0
17: ldc           #36
19: aastore
20: invokevirtual #7
23: pop
24: aconst_null
25: astore_1
26: aload_1
27: invokestatic  #37
30: astore_2
31: ldc           #10
33: invokestatic  #11
36: goto          40
39: astore_2
40: return
Exception table:
from    to  target type
26    36    39   Class java/lang/NullPointerException
Source File: /data/islam/DBT-workbench/resources/subjects/fixed/jsoup/39/src/test/java/org/jsoup/helper/RegressionTest0.java
Bytecode File: /data/islam/DBT-workbench/resources/subjects/fixed/jsoup/39/target/test-classes/org/jsoup/helper/RegressionTest0.class
Class name: RegressionTest0
Method name: test11
Start line: 144
End line: 155
Method source code: 
    public void test11() throws Throwable {
        if (debug)
            System.out.format("%n%s%n", "RegressionTest0.test11");
        java.io.InputStream inputStream0 = null;
        // The following exception was thrown during execution in test generation
        try {
            org.jsoup.nodes.Document document3 = org.jsoup.helper.DataUtil.load(inputStream0, "[:nth-last-child(32n+100)^=*]", ":gt(0)");
            org.junit.Assert.fail("Expected exception of type java.lang.NullPointerException; message: null");
        } catch (java.lang.NullPointerException e) {
        // Expected exception.
        }
    }
Method byte code: 
0: getstatic     #2
3: ifeq          24
6: getstatic     #3
9: ldc           #4
11: iconst_1
12: anewarray     #5
15: dup
16: iconst_0
17: ldc           #38
19: aastore
20: invokevirtual #7
23: pop
24: aconst_null
25: astore_1
26: aload_1
27: ldc           #39
29: ldc           #18
31: invokestatic  #23
34: astore_2
35: ldc           #10
37: invokestatic  #11
40: goto          44
43: astore_2
44: return
Exception table:
from    to  target type
26    40    43   Class java/lang/NullPointerException
Source File: /data/islam/DBT-workbench/resources/subjects/fixed/jsoup/39/src/test/java/org/jsoup/helper/RegressionTest0.java
Bytecode File: /data/islam/DBT-workbench/resources/subjects/fixed/jsoup/39/target/test-classes/org/jsoup/helper/RegressionTest0.class
Class name: RegressionTest0
Method name: test12
Start line: 158
End line: 173
Method source code: 
    public void test12() throws Throwable {
        if (debug)
            System.out.format("%n%s%n", "RegressionTest0.test12");
        java.nio.ByteBuffer byteBuffer0 = null;
        org.jsoup.parser.Parser parser3 = org.jsoup.parser.Parser.xmlParser();
        org.jsoup.parser.Parser parser5 = parser3.setTrackErrors((int) (short) 100);
        // The following exception was thrown during execution in test generation
        try {
            org.jsoup.nodes.Document document6 = org.jsoup.helper.DataUtil.parseByteData(byteBuffer0, "<html>\n <head></head>\n <body></body>\n</html>\n<html>\n <head></head>\n <body></body>\n</html>\n<html>\n <head></head>\n <body></body>\n</html>\n<html>\n <head></head>\n <body></body>\n</html>", ":only-child", parser5);
            org.junit.Assert.fail("Expected exception of type java.nio.charset.IllegalCharsetNameException; message: <html>? <head></head>? <body></body>?</html>?<html>? <head></head>? <body></body>?</html>?<html>? <head></head>? <body></body>?</html>?<html>? <head></head>? <body></body>?</html>");
        } catch (java.nio.charset.IllegalCharsetNameException e) {
        // Expected exception.
        }
        org.junit.Assert.assertNotNull(parser3);
        org.junit.Assert.assertNotNull(parser5);
    }
Method byte code: 
0: getstatic     #2
3: ifeq          24
6: getstatic     #3
9: ldc           #4
11: iconst_1
12: anewarray     #5
15: dup
16: iconst_0
17: ldc           #40
19: aastore
20: invokevirtual #7
23: pop
24: aconst_null
25: astore_1
26: invokestatic  #41
29: astore_2
30: aload_2
31: bipush        100
33: invokevirtual #42
36: astore_3
37: aload_1
38: ldc           #43
40: ldc           #44
42: aload_3
43: invokestatic  #27
46: astore        4
48: ldc           #45
50: invokestatic  #11
53: goto          58
56: astore        4
58: aload_2
59: invokestatic  #46
62: aload_3
63: invokestatic  #46
66: return
Exception table:
from    to  target type
37    53    56   Class java/nio/charset/IllegalCharsetNameException
Source File: /data/islam/DBT-workbench/resources/subjects/fixed/jsoup/39/src/test/java/org/jsoup/helper/RegressionTest0.java
Bytecode File: /data/islam/DBT-workbench/resources/subjects/fixed/jsoup/39/target/test-classes/org/jsoup/helper/RegressionTest0.class
Class name: RegressionTest0
Method name: test13
Start line: 176
End line: 181
Method source code: 
    public void test13() throws Throwable {
        if (debug)
            System.out.format("%n%s%n", "RegressionTest0.test13");
        java.lang.String str1 = org.jsoup.helper.DataUtil.getCharsetFromContentType("<html>\n <head></head>\n <body></body>\n</html>\n<#root>\n <html>\n  <head></head>\n  <body></body>\n </html>\n</#root>");
        org.junit.Assert.assertNull(str1);
    }
Method byte code: 
0: getstatic     #2
3: ifeq          24
6: getstatic     #3
9: ldc           #4
11: iconst_1
12: anewarray     #5
15: dup
16: iconst_0
17: ldc           #47
19: aastore
20: invokevirtual #7
23: pop
24: ldc           #48
26: invokestatic  #15
29: astore_1
30: aload_1
31: invokestatic  #16
34: return
Source File: /data/islam/DBT-workbench/resources/subjects/fixed/jsoup/39/src/test/java/org/jsoup/helper/RegressionTest0.java
Bytecode File: /data/islam/DBT-workbench/resources/subjects/fixed/jsoup/39/target/test-classes/org/jsoup/helper/RegressionTest0.class
Class name: RegressionTest0
Method name: test14
Start line: 184
End line: 195
Method source code: 
    public void test14() throws Throwable {
        if (debug)
            System.out.format("%n%s%n", "RegressionTest0.test14");
        java.io.File file0 = null;
        // The following exception was thrown during execution in test generation
        try {
            org.jsoup.nodes.Document document3 = org.jsoup.helper.DataUtil.load(file0, "<html>\n <head></head>\n <body></body>\n</html>", ":only-of-type");
            org.junit.Assert.fail("Expected exception of type java.lang.NullPointerException; message: null");
        } catch (java.lang.NullPointerException e) {
        // Expected exception.
        }
    }
Method byte code: 
0: getstatic     #2
3: ifeq          24
6: getstatic     #3
9: ldc           #4
11: iconst_1
12: anewarray     #5
15: dup
16: iconst_0
17: ldc           #49
19: aastore
20: invokevirtual #7
23: pop
24: aconst_null
25: astore_1
26: aload_1
27: ldc           #50
29: ldc           #51
31: invokestatic  #35
34: astore_2
35: ldc           #10
37: invokestatic  #11
40: goto          44
43: astore_2
44: return
Exception table:
from    to  target type
26    40    43   Class java/lang/NullPointerException
Source File: /data/islam/DBT-workbench/resources/subjects/fixed/jsoup/39/src/test/java/org/jsoup/helper/RegressionTest0.java
Bytecode File: /data/islam/DBT-workbench/resources/subjects/fixed/jsoup/39/target/test-classes/org/jsoup/helper/RegressionTest0.class
Class name: RegressionTest0
Method name: test15
Start line: 198
End line: 209
Method source code: 
    public void test15() throws Throwable {
        if (debug)
            System.out.format("%n%s%n", "RegressionTest0.test15");
        java.io.File file0 = null;
        // The following exception was thrown during execution in test generation
        try {
            org.jsoup.nodes.Document document3 = org.jsoup.helper.DataUtil.load(file0, "", "");
            org.junit.Assert.fail("Expected exception of type java.lang.NullPointerException; message: null");
        } catch (java.lang.NullPointerException e) {
        // Expected exception.
        }
    }
Method byte code: 
0: getstatic     #2
3: ifeq          24
6: getstatic     #3
9: ldc           #4
11: iconst_1
12: anewarray     #5
15: dup
16: iconst_0
17: ldc           #52
19: aastore
20: invokevirtual #7
23: pop
24: aconst_null
25: astore_1
26: aload_1
27: ldc           #8
29: ldc           #8
31: invokestatic  #35
34: astore_2
35: ldc           #10
37: invokestatic  #11
40: goto          44
43: astore_2
44: return
Exception table:
from    to  target type
26    40    43   Class java/lang/NullPointerException
Source File: /data/islam/DBT-workbench/resources/subjects/fixed/jsoup/39/src/test/java/org/jsoup/helper/RegressionTest0.java
Bytecode File: /data/islam/DBT-workbench/resources/subjects/fixed/jsoup/39/target/test-classes/org/jsoup/helper/RegressionTest0.class
Class name: RegressionTest0
Method name: test16
Start line: 212
End line: 223
Method source code: 
    public void test16() throws Throwable {
        if (debug)
            System.out.format("%n%s%n", "RegressionTest0.test16");
        java.io.File file0 = null;
        // The following exception was thrown during execution in test generation
        try {
            org.jsoup.nodes.Document document3 = org.jsoup.helper.DataUtil.load(file0, "*", ":matches(null");
            org.junit.Assert.fail("Expected exception of type java.lang.NullPointerException; message: null");
        } catch (java.lang.NullPointerException e) {
        // Expected exception.
        }
    }
Method byte code: 
0: getstatic     #2
3: ifeq          24
6: getstatic     #3
9: ldc           #4
11: iconst_1
12: anewarray     #5
15: dup
16: iconst_0
17: ldc           #53
19: aastore
20: invokevirtual #7
23: pop
24: aconst_null
25: astore_1
26: aload_1
27: ldc           #54
29: ldc           #55
31: invokestatic  #35
34: astore_2
35: ldc           #10
37: invokestatic  #11
40: goto          44
43: astore_2
44: return
Exception table:
from    to  target type
26    40    43   Class java/lang/NullPointerException
Source File: /data/islam/DBT-workbench/resources/subjects/fixed/jsoup/39/src/test/java/org/jsoup/helper/RegressionTest0.java
Bytecode File: /data/islam/DBT-workbench/resources/subjects/fixed/jsoup/39/target/test-classes/org/jsoup/helper/RegressionTest0.class
Class name: RegressionTest0
Method name: test17
Start line: 226
End line: 243
Method source code: 
    public void test17() throws Throwable {
        if (debug)
            System.out.format("%n%s%n", "RegressionTest0.test17");
        java.nio.ByteBuffer byteBuffer0 = null;
        org.jsoup.parser.Parser parser3 = org.jsoup.parser.Parser.xmlParser();
        org.jsoup.parser.Parser parser5 = parser3.setTrackErrors((int) (short) 100);
        org.jsoup.nodes.Document document8 = parser5.parseInput(":gt(0)", "#.");
        // The following exception was thrown during execution in test generation
        try {
            org.jsoup.nodes.Document document9 = org.jsoup.helper.DataUtil.parseByteData(byteBuffer0, "#text", "org.jsoup.select.Selector$SelectorParseException: hi!", parser5);
            org.junit.Assert.fail("Expected exception of type java.nio.charset.IllegalCharsetNameException; message: #text");
        } catch (java.nio.charset.IllegalCharsetNameException e) {
        // Expected exception.
        }
        org.junit.Assert.assertNotNull(parser3);
        org.junit.Assert.assertNotNull(parser5);
        org.junit.Assert.assertNotNull(document8);
    }
Method byte code: 
0: getstatic     #2
3: ifeq          24
6: getstatic     #3
9: ldc           #4
11: iconst_1
12: anewarray     #5
15: dup
16: iconst_0
17: ldc           #56
19: aastore
20: invokevirtual #7
23: pop
24: aconst_null
25: astore_1
26: invokestatic  #41
29: astore_2
30: aload_2
31: bipush        100
33: invokevirtual #42
36: astore_3
37: aload_3
38: ldc           #18
40: ldc           #57
42: invokevirtual #58
45: astore        4
47: aload_1
48: ldc           #59
50: ldc           #60
52: aload_3
53: invokestatic  #27
56: astore        5
58: ldc           #61
60: invokestatic  #11
63: goto          68
66: astore        5
68: aload_2
69: invokestatic  #46
72: aload_3
73: invokestatic  #46
76: aload         4
78: invokestatic  #46
81: return
Exception table:
from    to  target type
47    63    66   Class java/nio/charset/IllegalCharsetNameException
Source File: /data/islam/DBT-workbench/resources/subjects/fixed/jsoup/39/src/test/java/org/jsoup/helper/RegressionTest0.java
Bytecode File: /data/islam/DBT-workbench/resources/subjects/fixed/jsoup/39/target/test-classes/org/jsoup/helper/RegressionTest0.class
Class name: RegressionTest0
Method name: test18
Start line: 246
End line: 257
Method source code: 
    public void test18() throws Throwable {
        if (debug)
            System.out.format("%n%s%n", "RegressionTest0.test18");
        java.io.InputStream inputStream0 = null;
        // The following exception was thrown during execution in test generation
        try {
            org.jsoup.nodes.Document document3 = org.jsoup.helper.DataUtil.load(inputStream0, "", ":only-child");
            org.junit.Assert.fail("Expected exception of type java.lang.NullPointerException; message: null");
        } catch (java.lang.NullPointerException e) {
        // Expected exception.
        }
    }
Method byte code: 
0: getstatic     #2
3: ifeq          24
6: getstatic     #3
9: ldc           #4
11: iconst_1
12: anewarray     #5
15: dup
16: iconst_0
17: ldc           #62
19: aastore
20: invokevirtual #7
23: pop
24: aconst_null
25: astore_1
26: aload_1
27: ldc           #8
29: ldc           #44
31: invokestatic  #23
34: astore_2
35: ldc           #10
37: invokestatic  #11
40: goto          44
43: astore_2
44: return
Exception table:
from    to  target type
26    40    43   Class java/lang/NullPointerException
Source File: /data/islam/DBT-workbench/resources/subjects/fixed/jsoup/39/src/test/java/org/jsoup/helper/RegressionTest0.java
Bytecode File: /data/islam/DBT-workbench/resources/subjects/fixed/jsoup/39/target/test-classes/org/jsoup/helper/RegressionTest0.class
Class name: RegressionTest0
Method name: test19
Start line: 260
End line: 279
Method source code: 
    public void test19() throws Throwable {
        if (debug)
            System.out.format("%n%s%n", "RegressionTest0.test19");
        java.io.InputStream inputStream0 = null;
        org.jsoup.parser.Parser parser3 = org.jsoup.parser.Parser.xmlParser();
        org.jsoup.parser.Parser parser5 = parser3.setTrackErrors((int) (short) 100);
        org.jsoup.nodes.Document document8 = parser3.parseInput("UTF-8", "<html> <head></head> <body></body> </html> <html> <head></head> <body></body> </html> <html> <head></head> <body></body> </html> <html> <head></head> <body></body> </html>");
        org.jsoup.nodes.Document document11 = parser3.parseInput(":empty", ":matches(null");
        // The following exception was thrown during execution in test generation
        try {
            org.jsoup.nodes.Document document12 = org.jsoup.helper.DataUtil.load(inputStream0, "hi!", "", parser3);
            org.junit.Assert.fail("Expected exception of type java.lang.NullPointerException; message: null");
        } catch (java.lang.NullPointerException e) {
        // Expected exception.
        }
        org.junit.Assert.assertNotNull(parser3);
        org.junit.Assert.assertNotNull(parser5);
        org.junit.Assert.assertNotNull(document8);
        org.junit.Assert.assertNotNull(document11);
    }
Method byte code: 
0: getstatic     #2
3: ifeq          24
6: getstatic     #3
9: ldc           #4
11: iconst_1
12: anewarray     #5
15: dup
16: iconst_0
17: ldc           #63
19: aastore
20: invokevirtual #7
23: pop
24: aconst_null
25: astore_1
26: invokestatic  #41
29: astore_2
30: aload_2
31: bipush        100
33: invokevirtual #42
36: astore_3
37: aload_2
38: ldc           #34
40: ldc           #64
42: invokevirtual #58
45: astore        4
47: aload_2
48: ldc           #65
50: ldc           #55
52: invokevirtual #58
55: astore        5
57: aload_1
58: ldc           #14
60: ldc           #8
62: aload_2
63: invokestatic  #9
66: astore        6
68: ldc           #10
70: invokestatic  #11
73: goto          78
76: astore        6
78: aload_2
79: invokestatic  #46
82: aload_3
83: invokestatic  #46
86: aload         4
88: invokestatic  #46
91: aload         5
93: invokestatic  #46
96: return
Exception table:
from    to  target type
57    73    76   Class java/lang/NullPointerException
Source File: /data/islam/DBT-workbench/resources/subjects/fixed/jsoup/39/src/test/java/org/jsoup/helper/RegressionTest0.java
Bytecode File: /data/islam/DBT-workbench/resources/subjects/fixed/jsoup/39/target/test-classes/org/jsoup/helper/RegressionTest0.class
Class name: RegressionTest0
Method name: test20
Start line: 282
End line: 293
Method source code: 
    public void test20() throws Throwable {
        if (debug)
            System.out.format("%n%s%n", "RegressionTest0.test20");
        java.io.InputStream inputStream0 = null;
        // The following exception was thrown during execution in test generation
        try {
            java.nio.ByteBuffer byteBuffer2 = org.jsoup.helper.DataUtil.readToByteBuffer(inputStream0, (int) (short) 10);
            org.junit.Assert.fail("Expected exception of type java.lang.NullPointerException; message: null");
        } catch (java.lang.NullPointerException e) {
        // Expected exception.
        }
    }
Method byte code: 
0: getstatic     #2
3: ifeq          24
6: getstatic     #3
9: ldc           #4
11: iconst_1
12: anewarray     #5
15: dup
16: iconst_0
17: ldc           #66
19: aastore
20: invokevirtual #7
23: pop
24: aconst_null
25: astore_1
26: aload_1
27: bipush        10
29: invokestatic  #20
32: astore_2
33: ldc           #10
35: invokestatic  #11
38: goto          42
41: astore_2
42: return
Exception table:
from    to  target type
26    38    41   Class java/lang/NullPointerException
Source File: /data/islam/DBT-workbench/resources/subjects/fixed/jsoup/39/src/test/java/org/jsoup/helper/RegressionTest0.java
Bytecode File: /data/islam/DBT-workbench/resources/subjects/fixed/jsoup/39/target/test-classes/org/jsoup/helper/RegressionTest0.class
Class name: RegressionTest0
Method name: test21
Start line: 296
End line: 311
Method source code: 
    public void test21() throws Throwable {
        if (debug)
            System.out.format("%n%s%n", "RegressionTest0.test21");
        java.io.InputStream inputStream0 = null;
        org.jsoup.parser.Parser parser3 = org.jsoup.parser.Parser.xmlParser();
        org.jsoup.parser.Parser parser5 = parser3.setTrackErrors((int) (short) 100);
        // The following exception was thrown during execution in test generation
        try {
            org.jsoup.nodes.Document document6 = org.jsoup.helper.DataUtil.load(inputStream0, "<html>\n <head></head>\n <body></body>\n</html>\n<html>\n <head></head>\n <body></body>\n</html>\n<html>\n <head></head>\n <body></body>\n</html>\n<html>\n <head></head>\n <body></body>\n</html>", "", parser3);
            org.junit.Assert.fail("Expected exception of type java.lang.NullPointerException; message: null");
        } catch (java.lang.NullPointerException e) {
        // Expected exception.
        }
        org.junit.Assert.assertNotNull(parser3);
        org.junit.Assert.assertNotNull(parser5);
    }
Method byte code: 
0: getstatic     #2
3: ifeq          24
6: getstatic     #3
9: ldc           #4
11: iconst_1
12: anewarray     #5
15: dup
16: iconst_0
17: ldc           #67
19: aastore
20: invokevirtual #7
23: pop
24: aconst_null
25: astore_1
26: invokestatic  #41
29: astore_2
30: aload_2
31: bipush        100
33: invokevirtual #42
36: astore_3
37: aload_1
38: ldc           #43
40: ldc           #8
42: aload_2
43: invokestatic  #9
46: astore        4
48: ldc           #10
50: invokestatic  #11
53: goto          58
56: astore        4
58: aload_2
59: invokestatic  #46
62: aload_3
63: invokestatic  #46
66: return
Exception table:
from    to  target type
37    53    56   Class java/lang/NullPointerException
Source File: /data/islam/DBT-workbench/resources/subjects/fixed/jsoup/39/src/test/java/org/jsoup/helper/RegressionTest0.java
Bytecode File: /data/islam/DBT-workbench/resources/subjects/fixed/jsoup/39/target/test-classes/org/jsoup/helper/RegressionTest0.class
Class name: RegressionTest0
Method name: test22
Start line: 314
End line: 325
Method source code: 
    public void test22() throws Throwable {
        if (debug)
            System.out.format("%n%s%n", "RegressionTest0.test22");
        java.io.InputStream inputStream0 = null;
        // The following exception was thrown during execution in test generation
        try {
            org.jsoup.nodes.Document document3 = org.jsoup.helper.DataUtil.load(inputStream0, "org.jsoup.select.Selector$SelectorParseException: hi!", ":containsOwn(");
            org.junit.Assert.fail("Expected exception of type java.lang.NullPointerException; message: null");
        } catch (java.lang.NullPointerException e) {
        // Expected exception.
        }
    }
Method byte code: 
0: getstatic     #2
3: ifeq          24
6: getstatic     #3
9: ldc           #4
11: iconst_1
12: anewarray     #5
15: dup
16: iconst_0
17: ldc           #68
19: aastore
20: invokevirtual #7
23: pop
24: aconst_null
25: astore_1
26: aload_1
27: ldc           #60
29: ldc           #69
31: invokestatic  #23
34: astore_2
35: ldc           #10
37: invokestatic  #11
40: goto          44
43: astore_2
44: return
Exception table:
from    to  target type
26    40    43   Class java/lang/NullPointerException
Source File: /data/islam/DBT-workbench/resources/subjects/fixed/jsoup/39/src/test/java/org/jsoup/helper/RegressionTest0.java
Bytecode File: /data/islam/DBT-workbench/resources/subjects/fixed/jsoup/39/target/test-classes/org/jsoup/helper/RegressionTest0.class
Class name: RegressionTest0
Method name: test23
Start line: 328
End line: 333
Method source code: 
    public void test23() throws Throwable {
        if (debug)
            System.out.format("%n%s%n", "RegressionTest0.test23");
        java.lang.String str1 = org.jsoup.helper.DataUtil.getCharsetFromContentType("UTF-8");
        org.junit.Assert.assertNull(str1);
    }
Method byte code: 
0: getstatic     #2
3: ifeq          24
6: getstatic     #3
9: ldc           #4
11: iconst_1
12: anewarray     #5
15: dup
16: iconst_0
17: ldc           #70
19: aastore
20: invokevirtual #7
23: pop
24: ldc           #34
26: invokestatic  #15
29: astore_1
30: aload_1
31: invokestatic  #16
34: return
Source File: /data/islam/DBT-workbench/resources/subjects/fixed/jsoup/39/src/test/java/org/jsoup/helper/RegressionTest0.java
Bytecode File: /data/islam/DBT-workbench/resources/subjects/fixed/jsoup/39/target/test-classes/org/jsoup/helper/RegressionTest0.class
Class name: RegressionTest0
Method name: test24
Start line: 336
End line: 347
Method source code: 
    public void test24() throws Throwable {
        if (debug)
            System.out.format("%n%s%n", "RegressionTest0.test24");
        java.io.File file0 = null;
        // The following exception was thrown during execution in test generation
        try {
            org.jsoup.nodes.Document document3 = org.jsoup.helper.DataUtil.load(file0, ":containsOwn(", "[*$=*]");
            org.junit.Assert.fail("Expected exception of type java.lang.NullPointerException; message: null");
        } catch (java.lang.NullPointerException e) {
        // Expected exception.
        }
    }
Method byte code: 
0: getstatic     #2
3: ifeq          24
6: getstatic     #3
9: ldc           #4
11: iconst_1
12: anewarray     #5
15: dup
16: iconst_0
17: ldc           #71
19: aastore
20: invokevirtual #7
23: pop
24: aconst_null
25: astore_1
26: aload_1
27: ldc           #69
29: ldc           #72
31: invokestatic  #35
34: astore_2
35: ldc           #10
37: invokestatic  #11
40: goto          44
43: astore_2
44: return
Exception table:
from    to  target type
26    40    43   Class java/lang/NullPointerException
Source File: /data/islam/DBT-workbench/resources/subjects/fixed/jsoup/39/src/test/java/org/jsoup/helper/RegressionTest0.java
Bytecode File: /data/islam/DBT-workbench/resources/subjects/fixed/jsoup/39/target/test-classes/org/jsoup/helper/RegressionTest0.class
Class name: RegressionTest0
Method name: test25
Start line: 350
End line: 355
Method source code: 
    public void test25() throws Throwable {
        if (debug)
            System.out.format("%n%s%n", "RegressionTest0.test25");
        java.lang.String str1 = org.jsoup.helper.DataUtil.getCharsetFromContentType(":containsOwn(");
        org.junit.Assert.assertNull(str1);
    }
Method byte code: 
0: getstatic     #2
3: ifeq          24
6: getstatic     #3
9: ldc           #4
11: iconst_1
12: anewarray     #5
15: dup
16: iconst_0
17: ldc           #73
19: aastore
20: invokevirtual #7
23: pop
24: ldc           #69
26: invokestatic  #15
29: astore_1
30: aload_1
31: invokestatic  #16
34: return
Source File: /data/islam/DBT-workbench/resources/subjects/fixed/jsoup/39/src/test/java/org/jsoup/helper/RegressionTest0.java
Bytecode File: /data/islam/DBT-workbench/resources/subjects/fixed/jsoup/39/target/test-classes/org/jsoup/helper/RegressionTest0.class
Class name: RegressionTest0
Method name: test26
Start line: 358
End line: 369
Method source code: 
    public void test26() throws Throwable {
        if (debug)
            System.out.format("%n%s%n", "RegressionTest0.test26");
        java.io.InputStream inputStream0 = null;
        // The following exception was thrown during execution in test generation
        try {
            org.jsoup.nodes.Document document3 = org.jsoup.helper.DataUtil.load(inputStream0, "<html>\n <head></head>\n <body></body>\n</html>, <html>\n <head></head>\n <body></body>\n</html>, <html>\n <head></head>\n <body></body>\n</html>]", ":empty");
            org.junit.Assert.fail("Expected exception of type java.lang.NullPointerException; message: null");
        } catch (java.lang.NullPointerException e) {
        // Expected exception.
        }
    }
Method byte code: 
0: getstatic     #2
3: ifeq          24
6: getstatic     #3
9: ldc           #4
11: iconst_1
12: anewarray     #5
15: dup
16: iconst_0
17: ldc           #74
19: aastore
20: invokevirtual #7
23: pop
24: aconst_null
25: astore_1
26: aload_1
27: ldc           #75
29: ldc           #65
31: invokestatic  #23
34: astore_2
35: ldc           #10
37: invokestatic  #11
40: goto          44
43: astore_2
44: return
Exception table:
from    to  target type
26    40    43   Class java/lang/NullPointerException
Source File: /data/islam/DBT-workbench/resources/subjects/fixed/jsoup/39/src/test/java/org/jsoup/helper/RegressionTest0.java
Bytecode File: /data/islam/DBT-workbench/resources/subjects/fixed/jsoup/39/target/test-classes/org/jsoup/helper/RegressionTest0.class
Class name: RegressionTest0
Method name: test27
Start line: 372
End line: 384
Method source code: 
    public void test27() throws Throwable {
        if (debug)
            System.out.format("%n%s%n", "RegressionTest0.test27");
        java.nio.ByteBuffer byteBuffer0 = null;
        org.jsoup.parser.Parser parser3 = null;
        // The following exception was thrown during execution in test generation
        try {
            org.jsoup.nodes.Document document4 = org.jsoup.helper.DataUtil.parseByteData(byteBuffer0, "<hi!></hi!>", ":lt(91)", parser3);
            org.junit.Assert.fail("Expected exception of type java.nio.charset.IllegalCharsetNameException; message: <hi!></hi!>");
        } catch (java.nio.charset.IllegalCharsetNameException e) {
        // Expected exception.
        }
    }
Method byte code: 
0: getstatic     #2
3: ifeq          24
6: getstatic     #3
9: ldc           #4
11: iconst_1
12: anewarray     #5
15: dup
16: iconst_0
17: ldc           #76
19: aastore
20: invokevirtual #7
23: pop
24: aconst_null
25: astore_1
26: aconst_null
27: astore_2
28: aload_1
29: ldc           #77
31: ldc           #78
33: aload_2
34: invokestatic  #27
37: astore_3
38: ldc           #79
40: invokestatic  #11
43: goto          47
46: astore_3
47: return
Exception table:
from    to  target type
28    43    46   Class java/nio/charset/IllegalCharsetNameException
Source File: /data/islam/DBT-workbench/resources/subjects/fixed/jsoup/39/src/test/java/org/jsoup/helper/RegressionTest0.java
Bytecode File: /data/islam/DBT-workbench/resources/subjects/fixed/jsoup/39/target/test-classes/org/jsoup/helper/RegressionTest0.class
Class name: RegressionTest0
Method name: test28
Start line: 387
End line: 398
Method source code: 
    public void test28() throws Throwable {
        if (debug)
            System.out.format("%n%s%n", "RegressionTest0.test28");
        java.io.InputStream inputStream0 = null;
        // The following exception was thrown during execution in test generation
        try {
            org.jsoup.nodes.Document document3 = org.jsoup.helper.DataUtil.load(inputStream0, "[:lt(100)!=]", "#doctype");
            org.junit.Assert.fail("Expected exception of type java.lang.NullPointerException; message: null");
        } catch (java.lang.NullPointerException e) {
        // Expected exception.
        }
    }
Method byte code: 
0: getstatic     #2
3: ifeq          24
6: getstatic     #3
9: ldc           #4
11: iconst_1
12: anewarray     #5
15: dup
16: iconst_0
17: ldc           #80
19: aastore
20: invokevirtual #7
23: pop
24: aconst_null
25: astore_1
26: aload_1
27: ldc           #81
29: ldc           #82
31: invokestatic  #23
34: astore_2
35: ldc           #10
37: invokestatic  #11
40: goto          44
43: astore_2
44: return
Exception table:
from    to  target type
26    40    43   Class java/lang/NullPointerException
Source File: /data/islam/DBT-workbench/resources/subjects/fixed/jsoup/39/src/test/java/org/jsoup/helper/RegressionTest0.java
Bytecode File: /data/islam/DBT-workbench/resources/subjects/fixed/jsoup/39/target/test-classes/org/jsoup/helper/RegressionTest0.class
Class name: RegressionTest0
Method name: test29
Start line: 401
End line: 413
Method source code: 
    public void test29() throws Throwable {
        if (debug)
            System.out.format("%n%s%n", "RegressionTest0.test29");
        java.nio.ByteBuffer byteBuffer0 = null;
        org.jsoup.parser.Parser parser3 = null;
        // The following exception was thrown during execution in test generation
        try {
            org.jsoup.nodes.Document document4 = org.jsoup.helper.DataUtil.parseByteData(byteBuffer0, " text=\":gt(0)\"", "[#document=*]", parser3);
            org.junit.Assert.fail("Expected exception of type java.nio.charset.IllegalCharsetNameException; message:  text=\":gt(0)\"");
        } catch (java.nio.charset.IllegalCharsetNameException e) {
        // Expected exception.
        }
    }
Method byte code: 
0: getstatic     #2
3: ifeq          24
6: getstatic     #3
9: ldc           #4
11: iconst_1
12: anewarray     #5
15: dup
16: iconst_0
17: ldc           #83
19: aastore
20: invokevirtual #7
23: pop
24: aconst_null
25: astore_1
26: aconst_null
27: astore_2
28: aload_1
29: ldc           #84
31: ldc           #85
33: aload_2
34: invokestatic  #27
37: astore_3
38: ldc           #86
40: invokestatic  #11
43: goto          47
46: astore_3
47: return
Exception table:
from    to  target type
28    43    46   Class java/nio/charset/IllegalCharsetNameException
Source File: /data/islam/DBT-workbench/resources/subjects/fixed/jsoup/39/src/test/java/org/jsoup/helper/RegressionTest0.java
Bytecode File: /data/islam/DBT-workbench/resources/subjects/fixed/jsoup/39/target/test-classes/org/jsoup/helper/RegressionTest0.class
Class name: RegressionTest0
Method name: test30
Start line: 416
End line: 427
Method source code: 
    public void test30() throws Throwable {
        if (debug)
            System.out.format("%n%s%n", "RegressionTest0.test30");
        java.io.InputStream inputStream0 = null;
        // The following exception was thrown during execution in test generation
        try {
            org.jsoup.nodes.Document document3 = org.jsoup.helper.DataUtil.load(inputStream0, "[*$=*]", "[:nth-last-child(32n+100)^=*]");
            org.junit.Assert.fail("Expected exception of type java.lang.NullPointerException; message: null");
        } catch (java.lang.NullPointerException e) {
        // Expected exception.
        }
    }
Method byte code: 
0: getstatic     #2
3: ifeq          24
6: getstatic     #3
9: ldc           #4
11: iconst_1
12: anewarray     #5
15: dup
16: iconst_0
17: ldc           #87
19: aastore
20: invokevirtual #7
23: pop
24: aconst_null
25: astore_1
26: aload_1
27: ldc           #72
29: ldc           #39
31: invokestatic  #23
34: astore_2
35: ldc           #10
37: invokestatic  #11
40: goto          44
43: astore_2
44: return
Exception table:
from    to  target type
26    40    43   Class java/lang/NullPointerException
Source File: /data/islam/DBT-workbench/resources/subjects/fixed/jsoup/39/src/test/java/org/jsoup/helper/RegressionTest0.java
Bytecode File: /data/islam/DBT-workbench/resources/subjects/fixed/jsoup/39/target/test-classes/org/jsoup/helper/RegressionTest0.class
Class name: RegressionTest0
Method name: test31
Start line: 430
End line: 441
Method source code: 
    public void test31() throws Throwable {
        if (debug)
            System.out.format("%n%s%n", "RegressionTest0.test31");
        java.io.InputStream inputStream0 = null;
        // The following exception was thrown during execution in test generation
        try {
            org.jsoup.nodes.Document document3 = org.jsoup.helper.DataUtil.load(inputStream0, "#document", "#document");
            org.junit.Assert.fail("Expected exception of type java.lang.NullPointerException; message: null");
        } catch (java.lang.NullPointerException e) {
        // Expected exception.
        }
    }
Method byte code: 
0: getstatic     #2
3: ifeq          24
6: getstatic     #3
9: ldc           #4
11: iconst_1
12: anewarray     #5
15: dup
16: iconst_0
17: ldc           #88
19: aastore
20: invokevirtual #7
23: pop
24: aconst_null
25: astore_1
26: aload_1
27: ldc           #26
29: ldc           #26
31: invokestatic  #23
34: astore_2
35: ldc           #10
37: invokestatic  #11
40: goto          44
43: astore_2
44: return
Exception table:
from    to  target type
26    40    43   Class java/lang/NullPointerException
Source File: /data/islam/DBT-workbench/resources/subjects/fixed/jsoup/39/src/test/java/org/jsoup/helper/RegressionTest0.java
Bytecode File: /data/islam/DBT-workbench/resources/subjects/fixed/jsoup/39/target/test-classes/org/jsoup/helper/RegressionTest0.class
Class name: RegressionTest0
Method name: test32
Start line: 444
End line: 455
Method source code: 
    public void test32() throws Throwable {
        if (debug)
            System.out.format("%n%s%n", "RegressionTest0.test32");
        java.io.File file0 = null;
        // The following exception was thrown during execution in test generation
        try {
            org.jsoup.nodes.Document document3 = org.jsoup.helper.DataUtil.load(file0, "[:nth-last-child(32n+100)^=*]", "#.");
            org.junit.Assert.fail("Expected exception of type java.lang.NullPointerException; message: null");
        } catch (java.lang.NullPointerException e) {
        // Expected exception.
        }
    }
Method byte code: 
0: getstatic     #2
3: ifeq          24
6: getstatic     #3
9: ldc           #4
11: iconst_1
12: anewarray     #5
15: dup
16: iconst_0
17: ldc           #89
19: aastore
20: invokevirtual #7
23: pop
24: aconst_null
25: astore_1
26: aload_1
27: ldc           #39
29: ldc           #57
31: invokestatic  #35
34: astore_2
35: ldc           #10
37: invokestatic  #11
40: goto          44
43: astore_2
44: return
Exception table:
from    to  target type
26    40    43   Class java/lang/NullPointerException
Source File: /data/islam/DBT-workbench/resources/subjects/fixed/jsoup/39/src/test/java/org/jsoup/helper/RegressionTest0.java
Bytecode File: /data/islam/DBT-workbench/resources/subjects/fixed/jsoup/39/target/test-classes/org/jsoup/helper/RegressionTest0.class
Class name: RegressionTest0
Method name: test33
Start line: 458
End line: 469
Method source code: 
    public void test33() throws Throwable {
        if (debug)
            System.out.format("%n%s%n", "RegressionTest0.test33");
        java.io.File file0 = null;
        // The following exception was thrown during execution in test generation
        try {
            org.jsoup.nodes.Document document3 = org.jsoup.helper.DataUtil.load(file0, "<html>\n <head>\n  <title>:contains(:only-child</title>\n </head>\n <body></body>\n</html>", "#comment");
            org.junit.Assert.fail("Expected exception of type java.lang.NullPointerException; message: null");
        } catch (java.lang.NullPointerException e) {
        // Expected exception.
        }
    }
Method byte code: 
0: getstatic     #2
3: ifeq          24
6: getstatic     #3
9: ldc           #4
11: iconst_1
12: anewarray     #5
15: dup
16: iconst_0
17: ldc           #90
19: aastore
20: invokevirtual #7
23: pop
24: aconst_null
25: astore_1
26: aload_1
27: ldc           #91
29: ldc           #92
31: invokestatic  #35
34: astore_2
35: ldc           #10
37: invokestatic  #11
40: goto          44
43: astore_2
44: return
Exception table:
from    to  target type
26    40    43   Class java/lang/NullPointerException
Source File: /data/islam/DBT-workbench/resources/subjects/fixed/jsoup/39/src/test/java/org/jsoup/helper/RegressionTest0.java
Bytecode File: /data/islam/DBT-workbench/resources/subjects/fixed/jsoup/39/target/test-classes/org/jsoup/helper/RegressionTest0.class
Class name: RegressionTest0
Method name: test34
Start line: 472
End line: 487
Method source code: 
    public void test34() throws Throwable {
        if (debug)
            System.out.format("%n%s%n", "RegressionTest0.test34");
        java.io.InputStream inputStream0 = null;
        org.jsoup.parser.Parser parser3 = org.jsoup.parser.Parser.xmlParser();
        java.util.List<org.jsoup.parser.ParseError> parseErrorList4 = parser3.getErrors();
        // The following exception was thrown during execution in test generation
        try {
            org.jsoup.nodes.Document document5 = org.jsoup.helper.DataUtil.load(inputStream0, "#document", "#data", parser3);
            org.junit.Assert.fail("Expected exception of type java.lang.NullPointerException; message: null");
        } catch (java.lang.NullPointerException e) {
        // Expected exception.
        }
        org.junit.Assert.assertNotNull(parser3);
        org.junit.Assert.assertNull(parseErrorList4);
    }
Method byte code: 
0: getstatic     #2
3: ifeq          24
6: getstatic     #3
9: ldc           #4
11: iconst_1
12: anewarray     #5
15: dup
16: iconst_0
17: ldc           #93
19: aastore
20: invokevirtual #7
23: pop
24: aconst_null
25: astore_1
26: invokestatic  #41
29: astore_2
30: aload_2
31: invokevirtual #94
34: astore_3
35: aload_1
36: ldc           #26
38: ldc           #95
40: aload_2
41: invokestatic  #9
44: astore        4
46: ldc           #10
48: invokestatic  #11
51: goto          56
54: astore        4
56: aload_2
57: invokestatic  #46
60: aload_3
61: invokestatic  #16
64: return
Exception table:
from    to  target type
35    51    54   Class java/lang/NullPointerException
Source File: /data/islam/DBT-workbench/resources/subjects/fixed/jsoup/39/src/test/java/org/jsoup/helper/RegressionTest0.java
Bytecode File: /data/islam/DBT-workbench/resources/subjects/fixed/jsoup/39/target/test-classes/org/jsoup/helper/RegressionTest0.class
Class name: RegressionTest0
Method name: test35
Start line: 490
End line: 502
Method source code: 
    public void test35() throws Throwable {
        if (debug)
            System.out.format("%n%s%n", "RegressionTest0.test35");
        java.nio.ByteBuffer byteBuffer0 = null;
        org.jsoup.parser.Parser parser3 = null;
        // The following exception was thrown during execution in test generation
        try {
            org.jsoup.nodes.Document document4 = org.jsoup.helper.DataUtil.parseByteData(byteBuffer0, "[#document=*]", ":last-of-type", parser3);
            org.junit.Assert.fail("Expected exception of type java.nio.charset.IllegalCharsetNameException; message: [#document=*]");
        } catch (java.nio.charset.IllegalCharsetNameException e) {
        // Expected exception.
        }
    }
Method byte code: 
0: getstatic     #2
3: ifeq          24
6: getstatic     #3
9: ldc           #4
11: iconst_1
12: anewarray     #5
15: dup
16: iconst_0
17: ldc           #96
19: aastore
20: invokevirtual #7
23: pop
24: aconst_null
25: astore_1
26: aconst_null
27: astore_2
28: aload_1
29: ldc           #85
31: ldc           #97
33: aload_2
34: invokestatic  #27
37: astore_3
38: ldc           #98
40: invokestatic  #11
43: goto          47
46: astore_3
47: return
Exception table:
from    to  target type
28    43    46   Class java/nio/charset/IllegalCharsetNameException
Source File: /data/islam/DBT-workbench/resources/subjects/fixed/jsoup/39/src/test/java/org/jsoup/helper/RegressionTest0.java
Bytecode File: /data/islam/DBT-workbench/resources/subjects/fixed/jsoup/39/target/test-classes/org/jsoup/helper/RegressionTest0.class
Class name: RegressionTest0
Method name: test36
Start line: 505
End line: 522
Method source code: 
    public void test36() throws Throwable {
        if (debug)
            System.out.format("%n%s%n", "RegressionTest0.test36");
        java.io.InputStream inputStream0 = null;
        org.jsoup.parser.Parser parser3 = org.jsoup.parser.Parser.xmlParser();
        org.jsoup.parser.Parser parser5 = parser3.setTrackErrors((int) '#');
        org.jsoup.parser.Parser parser7 = parser3.setTrackErrors(0);
        // The following exception was thrown during execution in test generation
        try {
            org.jsoup.nodes.Document document8 = org.jsoup.helper.DataUtil.load(inputStream0, "#:only-of-type", "#doctype", parser3);
            org.junit.Assert.fail("Expected exception of type java.lang.NullPointerException; message: null");
        } catch (java.lang.NullPointerException e) {
        // Expected exception.
        }
        org.junit.Assert.assertNotNull(parser3);
        org.junit.Assert.assertNotNull(parser5);
        org.junit.Assert.assertNotNull(parser7);
    }
Method byte code: 
0: getstatic     #2
3: ifeq          24
6: getstatic     #3
9: ldc           #4
11: iconst_1
12: anewarray     #5
15: dup
16: iconst_0
17: ldc           #99
19: aastore
20: invokevirtual #7
23: pop
24: aconst_null
25: astore_1
26: invokestatic  #41
29: astore_2
30: aload_2
31: bipush        35
33: invokevirtual #42
36: astore_3
37: aload_2
38: iconst_0
39: invokevirtual #42
42: astore        4
44: aload_1
45: ldc           #100
47: ldc           #82
49: aload_2
50: invokestatic  #9
53: astore        5
55: ldc           #10
57: invokestatic  #11
60: goto          65
63: astore        5
65: aload_2
66: invokestatic  #46
69: aload_3
70: invokestatic  #46
73: aload         4
75: invokestatic  #46
78: return
Exception table:
from    to  target type
44    60    63   Class java/lang/NullPointerException
Source File: /data/islam/DBT-workbench/resources/subjects/fixed/jsoup/39/src/test/java/org/jsoup/helper/RegressionTest0.java
Bytecode File: /data/islam/DBT-workbench/resources/subjects/fixed/jsoup/39/target/test-classes/org/jsoup/helper/RegressionTest0.class
Class name: RegressionTest0
Method name: test37
Start line: 525
End line: 536
Method source code: 
    public void test37() throws Throwable {
        if (debug)
            System.out.format("%n%s%n", "RegressionTest0.test37");
        java.io.File file0 = null;
        // The following exception was thrown during execution in test generation
        try {
            org.jsoup.nodes.Document document3 = org.jsoup.helper.DataUtil.load(file0, "#comment", ":first-of-type");
            org.junit.Assert.fail("Expected exception of type java.lang.NullPointerException; message: null");
        } catch (java.lang.NullPointerException e) {
        // Expected exception.
        }
    }
Method byte code: 
0: getstatic     #2
3: ifeq          24
6: getstatic     #3
9: ldc           #4
11: iconst_1
12: anewarray     #5
15: dup
16: iconst_0
17: ldc           #101
19: aastore
20: invokevirtual #7
23: pop
24: aconst_null
25: astore_1
26: aload_1
27: ldc           #92
29: ldc           #102
31: invokestatic  #35
34: astore_2
35: ldc           #10
37: invokestatic  #11
40: goto          44
43: astore_2
44: return
Exception table:
from    to  target type
26    40    43   Class java/lang/NullPointerException
Source File: /data/islam/DBT-workbench/resources/subjects/fixed/jsoup/39/src/test/java/org/jsoup/helper/RegressionTest0.java
Bytecode File: /data/islam/DBT-workbench/resources/subjects/fixed/jsoup/39/target/test-classes/org/jsoup/helper/RegressionTest0.class
Class name: RegressionTest0
Method name: test38
Start line: 539
End line: 544
Method source code: 
    public void test38() throws Throwable {
        if (debug)
            System.out.format("%n%s%n", "RegressionTest0.test38");
        java.lang.String str1 = org.jsoup.helper.DataUtil.getCharsetFromContentType("[#document=*]");
        org.junit.Assert.assertNull(str1);
    }
Method byte code: 
0: getstatic     #2
3: ifeq          24
6: getstatic     #3
9: ldc           #4
11: iconst_1
12: anewarray     #5
15: dup
16: iconst_0
17: ldc           #103
19: aastore
20: invokevirtual #7
23: pop
24: ldc           #85
26: invokestatic  #15
29: astore_1
30: aload_1
31: invokestatic  #16
34: return
Source File: /data/islam/DBT-workbench/resources/subjects/fixed/jsoup/39/src/test/java/org/jsoup/helper/RegressionTest0.java
Bytecode File: /data/islam/DBT-workbench/resources/subjects/fixed/jsoup/39/target/test-classes/org/jsoup/helper/RegressionTest0.class
Class name: RegressionTest0
Method name: test39
Start line: 547
End line: 566
Method source code: 
    public void test39() throws Throwable {
        if (debug)
            System.out.format("%n%s%n", "RegressionTest0.test39");
        java.nio.ByteBuffer byteBuffer0 = null;
        org.jsoup.parser.Parser parser3 = org.jsoup.parser.Parser.xmlParser();
        org.jsoup.parser.Parser parser5 = parser3.setTrackErrors((int) (short) 100);
        boolean boolean6 = parser5.isTrackErrors();
        org.jsoup.parser.Parser parser8 = parser5.setTrackErrors((int) 'a');
        // The following exception was thrown during execution in test generation
        try {
            org.jsoup.nodes.Document document9 = org.jsoup.helper.DataUtil.parseByteData(byteBuffer0, "<html>\n <head></head>\n <body></body>\n</html>\n<#root>\n <html>\n  <head></head>\n  <body></body>\n </html>\n</#root>:containsOwn(<html>\n <head></head>\n <body></body>\n</html>:containsOwn(<head></head>:containsOwn(<html>\n <head></head>\n <body></body>\n</html>:containsOwn(<head></head>", "<html>\n <head></head>\n <body></body>\n</html>", parser5);
            org.junit.Assert.fail("Expected exception of type java.nio.charset.IllegalCharsetNameException; message: <html>? <head></head>? <body></body>?</html>?<#root>? <html>?  <head></head>?  <body></body>? </html>?</#root>:containsOwn(<html>? <head></head>? <body></body>?</html>:containsOwn(<head></head>:containsOwn(<html>? <head></head>? <body></body>?</html>:containsOwn(<head></head>");
        } catch (java.nio.charset.IllegalCharsetNameException e) {
        // Expected exception.
        }
        org.junit.Assert.assertNotNull(parser3);
        org.junit.Assert.assertNotNull(parser5);
        org.junit.Assert.assertTrue("'" + boolean6 + "' != '" + true + "'", boolean6 == true);
        org.junit.Assert.assertNotNull(parser8);
    }
Method byte code: 
0: getstatic     #2
3: ifeq          24
6: getstatic     #3
9: ldc           #4
11: iconst_1
12: anewarray     #5
15: dup
16: iconst_0
17: ldc           #104
19: aastore
20: invokevirtual #7
23: pop
24: aconst_null
25: astore_1
26: invokestatic  #41
29: astore_2
30: aload_2
31: bipush        100
33: invokevirtual #42
36: astore_3
37: aload_3
38: invokevirtual #105
41: istore        4
43: aload_3
44: bipush        97
46: invokevirtual #42
49: astore        5
51: aload_1
52: ldc           #106
54: ldc           #50
56: aload_3
57: invokestatic  #27
60: astore        6
62: ldc           #107
64: invokestatic  #11
67: goto          72
70: astore        6
72: aload_2
73: invokestatic  #46
76: aload_3
77: invokestatic  #46
80: new           #108
83: dup
84: invokespecial #109
87: ldc           #110
89: invokevirtual #111
92: iload         4
94: invokevirtual #112
97: ldc           #113
99: invokevirtual #111
102: iconst_1
103: invokevirtual #112
106: ldc           #110
108: invokevirtual #111
111: invokevirtual #114
114: iload         4
116: iconst_1
117: if_icmpne     124
120: iconst_1
121: goto          125
124: iconst_0
125: invokestatic  #115
128: aload         5
130: invokestatic  #46
133: return
Exception table:
from    to  target type
51    67    70   Class java/nio/charset/IllegalCharsetNameException
Source File: /data/islam/DBT-workbench/resources/subjects/fixed/jsoup/39/src/test/java/org/jsoup/helper/RegressionTest0.java
Bytecode File: /data/islam/DBT-workbench/resources/subjects/fixed/jsoup/39/target/test-classes/org/jsoup/helper/RegressionTest0.class
Class name: RegressionTest0
Method name: test40
Start line: 569
End line: 580
Method source code: 
    public void test40() throws Throwable {
        if (debug)
            System.out.format("%n%s%n", "RegressionTest0.test40");
        java.io.InputStream inputStream0 = null;
        // The following exception was thrown during execution in test generation
        try {
            java.nio.ByteBuffer byteBuffer2 = org.jsoup.helper.DataUtil.readToByteBuffer(inputStream0, (int) (byte) -1);
            org.junit.Assert.fail("Expected exception of type java.lang.IllegalArgumentException; message: maxSize must be 0 (unlimited) or larger");
        } catch (java.lang.IllegalArgumentException e) {
        // Expected exception.
        }
    }
Method byte code: 
0: getstatic     #2
3: ifeq          24
6: getstatic     #3
9: ldc           #4
11: iconst_1
12: anewarray     #5
15: dup
16: iconst_0
17: ldc           #116
19: aastore
20: invokevirtual #7
23: pop
24: aconst_null
25: astore_1
26: aload_1
27: iconst_m1
28: invokestatic  #20
31: astore_2
32: ldc           #117
34: invokestatic  #11
37: goto          41
40: astore_2
41: return
Exception table:
from    to  target type
26    37    40   Class java/lang/IllegalArgumentException
Source File: /data/islam/DBT-workbench/resources/subjects/fixed/jsoup/39/src/test/java/org/jsoup/helper/RegressionTest0.java
Bytecode File: /data/islam/DBT-workbench/resources/subjects/fixed/jsoup/39/target/test-classes/org/jsoup/helper/RegressionTest0.class
Class name: RegressionTest0
Method name: test41
Start line: 583
End line: 594
Method source code: 
    public void test41() throws Throwable {
        if (debug)
            System.out.format("%n%s%n", "RegressionTest0.test41");
        java.io.InputStream inputStream0 = null;
        // The following exception was thrown during execution in test generation
        try {
            java.nio.ByteBuffer byteBuffer2 = org.jsoup.helper.DataUtil.readToByteBuffer(inputStream0, 1);
            org.junit.Assert.fail("Expected exception of type java.lang.NullPointerException; message: null");
        } catch (java.lang.NullPointerException e) {
        // Expected exception.
        }
    }
Method byte code: 
0: getstatic     #2
3: ifeq          24
6: getstatic     #3
9: ldc           #4
11: iconst_1
12: anewarray     #5
15: dup
16: iconst_0
17: ldc           #119
19: aastore
20: invokevirtual #7
23: pop
24: aconst_null
25: astore_1
26: aload_1
27: iconst_1
28: invokestatic  #20
31: astore_2
32: ldc           #10
34: invokestatic  #11
37: goto          41
40: astore_2
41: return
Exception table:
from    to  target type
26    37    40   Class java/lang/NullPointerException
Source File: /data/islam/DBT-workbench/resources/subjects/fixed/jsoup/39/src/test/java/org/jsoup/helper/RegressionTest0.java
Bytecode File: /data/islam/DBT-workbench/resources/subjects/fixed/jsoup/39/target/test-classes/org/jsoup/helper/RegressionTest0.class
Class name: RegressionTest0
Method name: test42
Start line: 597
End line: 620
Method source code: 
    public void test42() throws Throwable {
        if (debug)
            System.out.format("%n%s%n", "RegressionTest0.test42");
        java.io.InputStream inputStream0 = null;
        org.jsoup.parser.Parser parser3 = org.jsoup.parser.Parser.xmlParser();
        org.jsoup.parser.Parser parser5 = parser3.setTrackErrors((int) (short) 100);
        org.jsoup.nodes.Document document8 = parser5.parseInput(":gt(0)", "#.");
        java.util.List<org.jsoup.parser.ParseError> parseErrorList9 = parser5.getErrors();
        org.jsoup.parser.Parser parser11 = parser5.setTrackErrors(1);
        org.jsoup.nodes.Document document14 = parser11.parseInput("[:nth-last-child(32n+100)^=*]", ":root");
        // The following exception was thrown during execution in test generation
        try {
            org.jsoup.nodes.Document document15 = org.jsoup.helper.DataUtil.load(inputStream0, "", "#document", parser11);
            org.junit.Assert.fail("Expected exception of type java.lang.NullPointerException; message: null");
        } catch (java.lang.NullPointerException e) {
        // Expected exception.
        }
        org.junit.Assert.assertNotNull(parser3);
        org.junit.Assert.assertNotNull(parser5);
        org.junit.Assert.assertNotNull(document8);
        org.junit.Assert.assertNotNull(parseErrorList9);
        org.junit.Assert.assertNotNull(parser11);
        org.junit.Assert.assertNotNull(document14);
    }
Method byte code: 
0: getstatic     #2
3: ifeq          24
6: getstatic     #3
9: ldc           #4
11: iconst_1
12: anewarray     #5
15: dup
16: iconst_0
17: ldc           #120
19: aastore
20: invokevirtual #7
23: pop
24: aconst_null
25: astore_1
26: invokestatic  #41
29: astore_2
30: aload_2
31: bipush        100
33: invokevirtual #42
36: astore_3
37: aload_3
38: ldc           #18
40: ldc           #57
42: invokevirtual #58
45: astore        4
47: aload_3
48: invokevirtual #94
51: astore        5
53: aload_3
54: iconst_1
55: invokevirtual #42
58: astore        6
60: aload         6
62: ldc           #39
64: ldc           #121
66: invokevirtual #58
69: astore        7
71: aload_1
72: ldc           #8
74: ldc           #26
76: aload         6
78: invokestatic  #9
81: astore        8
83: ldc           #10
85: invokestatic  #11
88: goto          93
91: astore        8
93: aload_2
94: invokestatic  #46
97: aload_3
98: invokestatic  #46
101: aload         4
103: invokestatic  #46
106: aload         5
108: invokestatic  #46
111: aload         6
113: invokestatic  #46
116: aload         7
118: invokestatic  #46
121: return
Exception table:
from    to  target type
71    88    91   Class java/lang/NullPointerException
Source File: /data/islam/DBT-workbench/resources/subjects/fixed/jsoup/39/src/test/java/org/jsoup/helper/RegressionTest0.java
Bytecode File: /data/islam/DBT-workbench/resources/subjects/fixed/jsoup/39/target/test-classes/org/jsoup/helper/RegressionTest0.class
Class name: RegressionTest0
Method name: test43
Start line: 623
End line: 634
Method source code: 
    public void test43() throws Throwable {
        if (debug)
            System.out.format("%n%s%n", "RegressionTest0.test43");
        java.io.InputStream inputStream0 = null;
        // The following exception was thrown during execution in test generation
        try {
            java.nio.ByteBuffer byteBuffer2 = org.jsoup.helper.DataUtil.readToByteBuffer(inputStream0, (-1));
            org.junit.Assert.fail("Expected exception of type java.lang.IllegalArgumentException; message: maxSize must be 0 (unlimited) or larger");
        } catch (java.lang.IllegalArgumentException e) {
        // Expected exception.
        }
    }
Method byte code: 
0: getstatic     #2
3: ifeq          24
6: getstatic     #3
9: ldc           #4
11: iconst_1
12: anewarray     #5
15: dup
16: iconst_0
17: ldc           #122
19: aastore
20: invokevirtual #7
23: pop
24: aconst_null
25: astore_1
26: aload_1
27: iconst_m1
28: invokestatic  #20
31: astore_2
32: ldc           #117
34: invokestatic  #11
37: goto          41
40: astore_2
41: return
Exception table:
from    to  target type
26    37    40   Class java/lang/IllegalArgumentException
Source File: /data/islam/DBT-workbench/resources/subjects/fixed/jsoup/39/src/test/java/org/jsoup/helper/RegressionTest0.java
Bytecode File: /data/islam/DBT-workbench/resources/subjects/fixed/jsoup/39/target/test-classes/org/jsoup/helper/RegressionTest0.class
Class name: RegressionTest0
Method name: test44
Start line: 637
End line: 753
Method source code: 
    public void test44() throws Throwable {
        if (debug)
            System.out.format("%n%s%n", "RegressionTest0.test44");
        java.io.InputStream inputStream0 = null;
        org.jsoup.nodes.Document document4 = org.jsoup.nodes.Document.createShell("hi!");
        java.util.List<org.jsoup.nodes.TextNode> textNodeList5 = document4.textNodes();
        org.jsoup.nodes.Element element6 = document4.nextElementSibling();
        java.lang.String str7 = document4.title();
        java.util.List<org.jsoup.nodes.Node> nodeList8 = document4.childNodes();
        org.jsoup.nodes.Document document10 = org.jsoup.nodes.Document.createShell("hi!");
        java.util.List<org.jsoup.nodes.TextNode> textNodeList11 = document10.textNodes();
        org.jsoup.nodes.Document document13 = org.jsoup.nodes.Document.createShell("hi!");
        java.util.List<org.jsoup.nodes.TextNode> textNodeList14 = document13.textNodes();
        org.jsoup.nodes.Element element15 = document13.nextElementSibling();
        org.jsoup.nodes.Document document17 = org.jsoup.nodes.Document.createShell("hi!");
        java.util.List<org.jsoup.nodes.TextNode> textNodeList18 = document17.textNodes();
        org.jsoup.nodes.Document document20 = org.jsoup.nodes.Document.createShell("hi!");
        java.util.List<org.jsoup.nodes.TextNode> textNodeList21 = document20.textNodes();
        org.jsoup.nodes.Element element22 = document20.nextElementSibling();
        org.jsoup.nodes.Element[] elementArray23 = new org.jsoup.nodes.Element[] { document10, document13, document17, document20 };
        java.util.ArrayList<org.jsoup.nodes.Element> elementList24 = new java.util.ArrayList<org.jsoup.nodes.Element>();
        boolean boolean25 = java.util.Collections.addAll((java.util.Collection<org.jsoup.nodes.Element>) elementList24, elementArray23);
        org.jsoup.select.Elements elements26 = new org.jsoup.select.Elements((java.util.Collection<org.jsoup.nodes.Element>) elementList24);
        org.jsoup.nodes.Document document29 = org.jsoup.nodes.Document.createShell("hi!");
        org.jsoup.nodes.Element element30 = elements26.set(0, (org.jsoup.nodes.Element) document29);
        java.util.List<org.jsoup.nodes.TextNode> textNodeList31 = element30.textNodes();
        org.jsoup.nodes.Element element32 = document4.appendChild((org.jsoup.nodes.Node) element30);
        java.util.Set<java.lang.String> strSet33 = document4.classNames();
        java.util.LinkedList<java.util.Set<java.lang.String>> strSetList34 = new java.util.LinkedList<java.util.Set<java.lang.String>>();
        boolean boolean35 = strSetList34.add(strSet33);
        org.jsoup.nodes.Document document37 = org.jsoup.nodes.Document.createShell("hi!");
        java.util.List<org.jsoup.nodes.TextNode> textNodeList38 = document37.textNodes();
        org.jsoup.nodes.Document document40 = org.jsoup.nodes.Document.createShell("hi!");
        java.util.List<org.jsoup.nodes.TextNode> textNodeList41 = document40.textNodes();
        org.jsoup.nodes.Element element42 = document40.nextElementSibling();
        org.jsoup.nodes.Document document44 = org.jsoup.nodes.Document.createShell("hi!");
        java.util.List<org.jsoup.nodes.TextNode> textNodeList45 = document44.textNodes();
        org.jsoup.nodes.Document document47 = org.jsoup.nodes.Document.createShell("hi!");
        java.util.List<org.jsoup.nodes.TextNode> textNodeList48 = document47.textNodes();
        org.jsoup.nodes.Element element49 = document47.nextElementSibling();
        org.jsoup.nodes.Element[] elementArray50 = new org.jsoup.nodes.Element[] { document37, document40, document44, document47 };
        java.util.ArrayList<org.jsoup.nodes.Element> elementList51 = new java.util.ArrayList<org.jsoup.nodes.Element>();
        boolean boolean52 = java.util.Collections.addAll((java.util.Collection<org.jsoup.nodes.Element>) elementList51, elementArray50);
        org.jsoup.select.Elements elements53 = new org.jsoup.select.Elements((java.util.Collection<org.jsoup.nodes.Element>) elementList51);
        org.jsoup.nodes.Document document56 = org.jsoup.nodes.Document.createShell("hi!");
        org.jsoup.nodes.Element element57 = elements53.set(0, (org.jsoup.nodes.Element) document56);
        java.lang.String[] strArray60 = new java.lang.String[] { "UTF-8", "UTF-8" };
        java.util.LinkedHashSet<java.lang.String> strSet61 = new java.util.LinkedHashSet<java.lang.String>();
        boolean boolean62 = java.util.Collections.addAll((java.util.Collection<java.lang.String>) strSet61, strArray60);
        org.jsoup.nodes.Element element63 = element57.classNames((java.util.Set<java.lang.String>) strSet61);
        org.jsoup.select.Elements elements65 = element57.getElementsContainingText("UTF-8");
        org.jsoup.select.Elements elements67 = element57.getElementsContainingText(".");
        java.util.Set<java.lang.String> strSet68 = element57.classNames();
        boolean boolean69 = strSetList34.offer(strSet68);
        org.jsoup.select.Evaluator.AttributeWithValueNot attributeWithValueNot72 = new org.jsoup.select.Evaluator.AttributeWithValueNot("[<html>\n <head></head>\n <body></body>\n</html>, <html>\n <head></head>\n <body></body>\n</html>, <html>\n <head></head>\n <body></body>\n</html>]", "<html>\n <head></head>\n <body></body>\n</html>");
        boolean boolean73 = strSetList34.contains((java.lang.Object) "[<html>\n <head></head>\n <body></body>\n</html>, <html>\n <head></head>\n <body></body>\n</html>, <html>\n <head></head>\n <body></body>\n</html>]");
        org.jsoup.parser.Parser parser74 = org.jsoup.parser.Parser.xmlParser();
        org.jsoup.parser.Parser parser76 = parser74.setTrackErrors((int) (short) 100);
        java.util.List<org.jsoup.parser.ParseError> parseErrorList77 = parser76.getErrors();
        boolean boolean78 = strSetList34.remove((java.lang.Object) parser76);
        // The following exception was thrown during execution in test generation
        try {
            org.jsoup.nodes.Document document79 = org.jsoup.helper.DataUtil.load(inputStream0, ":last-child", ":nth-last-of-type(32n+10)", parser76);
            org.junit.Assert.fail("Expected exception of type java.lang.NullPointerException; message: null");
        } catch (java.lang.NullPointerException e) {
        // Expected exception.
        }
        org.junit.Assert.assertNotNull(document4);
        org.junit.Assert.assertNotNull(textNodeList5);
        org.junit.Assert.assertNull(element6);
        org.junit.Assert.assertEquals("'" + str7 + "' != '" + "" + "'", str7, "");
        org.junit.Assert.assertNotNull(nodeList8);
        org.junit.Assert.assertNotNull(document10);
        org.junit.Assert.assertNotNull(textNodeList11);
        org.junit.Assert.assertNotNull(document13);
        org.junit.Assert.assertNotNull(textNodeList14);
        org.junit.Assert.assertNull(element15);
        org.junit.Assert.assertNotNull(document17);
        org.junit.Assert.assertNotNull(textNodeList18);
        org.junit.Assert.assertNotNull(document20);
        org.junit.Assert.assertNotNull(textNodeList21);
        org.junit.Assert.assertNull(element22);
        org.junit.Assert.assertNotNull(elementArray23);
        org.junit.Assert.assertTrue("'" + boolean25 + "' != '" + true + "'", boolean25 == true);
        org.junit.Assert.assertNotNull(document29);
        org.junit.Assert.assertNotNull(element30);
        org.junit.Assert.assertNotNull(textNodeList31);
        org.junit.Assert.assertNotNull(element32);
        org.junit.Assert.assertNotNull(strSet33);
        org.junit.Assert.assertTrue("'" + boolean35 + "' != '" + true + "'", boolean35 == true);
        org.junit.Assert.assertNotNull(document37);
        org.junit.Assert.assertNotNull(textNodeList38);
        org.junit.Assert.assertNotNull(document40);
        org.junit.Assert.assertNotNull(textNodeList41);
        org.junit.Assert.assertNull(element42);
        org.junit.Assert.assertNotNull(document44);
        org.junit.Assert.assertNotNull(textNodeList45);
        org.junit.Assert.assertNotNull(document47);
        org.junit.Assert.assertNotNull(textNodeList48);
        org.junit.Assert.assertNull(element49);
        org.junit.Assert.assertNotNull(elementArray50);
        org.junit.Assert.assertTrue("'" + boolean52 + "' != '" + true + "'", boolean52 == true);
        org.junit.Assert.assertNotNull(document56);
        org.junit.Assert.assertNotNull(element57);
        org.junit.Assert.assertNotNull(strArray60);
        org.junit.Assert.assertTrue("'" + boolean62 + "' != '" + true + "'", boolean62 == true);
        org.junit.Assert.assertNotNull(element63);
        org.junit.Assert.assertNotNull(elements65);
        org.junit.Assert.assertNotNull(elements67);
        org.junit.Assert.assertNotNull(strSet68);
        org.junit.Assert.assertTrue("'" + boolean69 + "' != '" + true + "'", boolean69 == true);
        org.junit.Assert.assertTrue("'" + boolean73 + "' != '" + false + "'", boolean73 == false);
        org.junit.Assert.assertNotNull(parser74);
        org.junit.Assert.assertNotNull(parser76);
        org.junit.Assert.assertNull(parseErrorList77);
        org.junit.Assert.assertTrue("'" + boolean78 + "' != '" + false + "'", boolean78 == false);
    }
Method byte code: 
0: getstatic     #2
3: ifeq          24
6: getstatic     #3
9: ldc           #4
11: iconst_1
12: anewarray     #5
15: dup
16: iconst_0
17: ldc           #123
19: aastore
20: invokevirtual #7
23: pop
24: aconst_null
25: astore_1
26: ldc           #14
28: invokestatic  #124
31: astore_2
32: aload_2
33: invokevirtual #125
36: astore_3
37: aload_2
38: invokevirtual #126
41: astore        4
43: aload_2
44: invokevirtual #127
47: astore        5
49: aload_2
50: invokevirtual #128
53: astore        6
55: ldc           #14
57: invokestatic  #124
60: astore        7
62: aload         7
64: invokevirtual #125
67: astore        8
69: ldc           #14
71: invokestatic  #124
74: astore        9
76: aload         9
78: invokevirtual #125
81: astore        10
83: aload         9
85: invokevirtual #126
88: astore        11
90: ldc           #14
92: invokestatic  #124
95: astore        12
97: aload         12
99: invokevirtual #125
102: astore        13
104: ldc           #14
106: invokestatic  #124
109: astore        14
111: aload         14
113: invokevirtual #125
116: astore        15
118: aload         14
120: invokevirtual #126
123: astore        16
125: iconst_4
126: anewarray     #129
129: dup
130: iconst_0
131: aload         7
133: aastore
134: dup
135: iconst_1
136: aload         9
138: aastore
139: dup
140: iconst_2
141: aload         12
143: aastore
144: dup
145: iconst_3
146: aload         14
148: aastore
149: astore        17
151: new           #130
154: dup
155: invokespecial #131
158: astore        18
160: aload         18
162: aload         17
164: invokestatic  #132
167: istore        19
169: new           #133
172: dup
173: aload         18
175: invokespecial #134
178: astore        20
180: ldc           #14
182: invokestatic  #124
185: astore        21
187: aload         20
189: iconst_0
190: aload         21
192: invokevirtual #135
195: astore        22
197: aload         22
199: invokevirtual #136
202: astore        23
204: aload_2
205: aload         22
207: invokevirtual #137
210: astore        24
212: aload_2
213: invokevirtual #138
216: astore        25
218: new           #139
221: dup
222: invokespecial #140
225: astore        26
227: aload         26
229: aload         25
231: invokevirtual #141
234: istore        27
236: ldc           #14
238: invokestatic  #124
241: astore        28
243: aload         28
245: invokevirtual #125
248: astore        29
250: ldc           #14
252: invokestatic  #124
255: astore        30
257: aload         30
259: invokevirtual #125
262: astore        31
264: aload         30
266: invokevirtual #126
269: astore        32
271: ldc           #14
273: invokestatic  #124
276: astore        33
278: aload         33
280: invokevirtual #125
283: astore        34
285: ldc           #14
287: invokestatic  #124
290: astore        35
292: aload         35
294: invokevirtual #125
297: astore        36
299: aload         35
301: invokevirtual #126
304: astore        37
306: iconst_4
307: anewarray     #129
310: dup
311: iconst_0
312: aload         28
314: aastore
315: dup
316: iconst_1
317: aload         30
319: aastore
320: dup
321: iconst_2
322: aload         33
324: aastore
325: dup
326: iconst_3
327: aload         35
329: aastore
330: astore        38
332: new           #130
335: dup
336: invokespecial #131
339: astore        39
341: aload         39
343: aload         38
345: invokestatic  #132
348: istore        40
350: new           #133
353: dup
354: aload         39
356: invokespecial #134
359: astore        41
361: ldc           #14
363: invokestatic  #124
366: astore        42
368: aload         41
370: iconst_0
371: aload         42
373: invokevirtual #135
376: astore        43
378: iconst_2
379: anewarray     #142
382: dup
383: iconst_0
384: ldc           #34
386: aastore
387: dup
388: iconst_1
389: ldc           #34
391: aastore
392: astore        44
394: new           #143
397: dup
398: invokespecial #144
401: astore        45
403: aload         45
405: aload         44
407: invokestatic  #132
410: istore        46
412: aload         43
414: aload         45
416: invokevirtual #145
419: astore        47
421: aload         43
423: ldc           #34
425: invokevirtual #146
428: astore        48
430: aload         43
432: ldc           #22
434: invokevirtual #146
437: astore        49
439: aload         43
441: invokevirtual #147
444: astore        50
446: aload         26
448: aload         50
450: invokevirtual #148
453: istore        51
455: new           #149
458: dup
459: ldc           #25
461: ldc           #50
463: invokespecial #150
466: astore        52
468: aload         26
470: ldc           #25
472: invokevirtual #151
475: istore        53
477: invokestatic  #41
480: astore        54
482: aload         54
484: bipush        100
486: invokevirtual #42
489: astore        55
491: aload         55
493: invokevirtual #94
496: astore        56
498: aload         26
500: aload         55
502: invokevirtual #152
505: istore        57
507: aload_1
508: ldc           #153
510: ldc           #154
512: aload         55
514: invokestatic  #9
517: astore        58
519: ldc           #10
521: invokestatic  #11
524: goto          529
527: astore        58
529: aload_2
530: invokestatic  #46
533: aload_3
534: invokestatic  #46
537: aload         4
539: invokestatic  #16
542: new           #108
545: dup
546: invokespecial #109
549: ldc           #110
551: invokevirtual #111
554: aload         5
556: invokevirtual #111
559: ldc           #155
561: invokevirtual #111
564: invokevirtual #114
567: aload         5
569: ldc           #8
571: invokestatic  #156
574: aload         6
576: invokestatic  #46
579: aload         7
581: invokestatic  #46
584: aload         8
586: invokestatic  #46
589: aload         9
591: invokestatic  #46
594: aload         10
596: invokestatic  #46
599: aload         11
601: invokestatic  #16
604: aload         12
606: invokestatic  #46
609: aload         13
611: invokestatic  #46
614: aload         14
616: invokestatic  #46
619: aload         15
621: invokestatic  #46
624: aload         16
626: invokestatic  #16
629: aload         17
631: invokestatic  #46
634: new           #108
637: dup
638: invokespecial #109
641: ldc           #110
643: invokevirtual #111
646: iload         19
648: invokevirtual #112
651: ldc           #113
653: invokevirtual #111
656: iconst_1
657: invokevirtual #112
660: ldc           #110
662: invokevirtual #111
665: invokevirtual #114
668: iload         19
670: iconst_1
671: if_icmpne     678
674: iconst_1
675: goto          679
678: iconst_0
679: invokestatic  #115
682: aload         21
684: invokestatic  #46
687: aload         22
689: invokestatic  #46
692: aload         23
694: invokestatic  #46
697: aload         24
699: invokestatic  #46
702: aload         25
704: invokestatic  #46
707: new           #108
710: dup
711: invokespecial #109
714: ldc           #110
716: invokevirtual #111
719: iload         27
721: invokevirtual #112
724: ldc           #113
726: invokevirtual #111
729: iconst_1
730: invokevirtual #112
733: ldc           #110
735: invokevirtual #111
738: invokevirtual #114
741: iload         27
743: iconst_1
744: if_icmpne     751
747: iconst_1
748: goto          752
751: iconst_0
752: invokestatic  #115
755: aload         28
757: invokestatic  #46
760: aload         29
762: invokestatic  #46
765: aload         30
767: invokestatic  #46
770: aload         31
772: invokestatic  #46
775: aload         32
777: invokestatic  #16
780: aload         33
782: invokestatic  #46
785: aload         34
787: invokestatic  #46
790: aload         35
792: invokestatic  #46
795: aload         36
797: invokestatic  #46
800: aload         37
802: invokestatic  #16
805: aload         38
807: invokestatic  #46
810: new           #108
813: dup
814: invokespecial #109
817: ldc           #110
819: invokevirtual #111
822: iload         40
824: invokevirtual #112
827: ldc           #113
829: invokevirtual #111
832: iconst_1
833: invokevirtual #112
836: ldc           #110
838: invokevirtual #111
841: invokevirtual #114
844: iload         40
846: iconst_1
847: if_icmpne     854
850: iconst_1
851: goto          855
854: iconst_0
855: invokestatic  #115
858: aload         42
860: invokestatic  #46
863: aload         43
865: invokestatic  #46
868: aload         44
870: invokestatic  #46
873: new           #108
876: dup
877: invokespecial #109
880: ldc           #110
882: invokevirtual #111
885: iload         46
887: invokevirtual #112
890: ldc           #113
892: invokevirtual #111
895: iconst_1
896: invokevirtual #112
899: ldc           #110
901: invokevirtual #111
904: invokevirtual #114
907: iload         46
909: iconst_1
910: if_icmpne     917
913: iconst_1
914: goto          918
917: iconst_0
918: invokestatic  #115
921: aload         47
923: invokestatic  #46
926: aload         48
928: invokestatic  #46
931: aload         49
933: invokestatic  #46
936: aload         50
938: invokestatic  #46
941: new           #108
944: dup
945: invokespecial #109
948: ldc           #110
950: invokevirtual #111
953: iload         51
955: invokevirtual #112
958: ldc           #113
960: invokevirtual #111
963: iconst_1
964: invokevirtual #112
967: ldc           #110
969: invokevirtual #111
972: invokevirtual #114
975: iload         51
977: iconst_1
978: if_icmpne     985
981: iconst_1
982: goto          986
985: iconst_0
986: invokestatic  #115
989: new           #108
992: dup
993: invokespecial #109
996: ldc           #110
998: invokevirtual #111
1001: iload         53
1003: invokevirtual #112
1006: ldc           #113
1008: invokevirtual #111
1011: iconst_0
1012: invokevirtual #112
1015: ldc           #110
1017: invokevirtual #111
1020: invokevirtual #114
1023: iload         53
1025: ifne          1032
1028: iconst_1
1029: goto          1033
1032: iconst_0
1033: invokestatic  #115
1036: aload         54
1038: invokestatic  #46
1041: aload         55
1043: invokestatic  #46
1046: aload         56
1048: invokestatic  #16
1051: new           #108
1054: dup
1055: invokespecial #109
1058: ldc           #110
1060: invokevirtual #111
1063: iload         57
1065: invokevirtual #112
1068: ldc           #113
1070: invokevirtual #111
1073: iconst_0
1074: invokevirtual #112
1077: ldc           #110
1079: invokevirtual #111
1082: invokevirtual #114
1085: iload         57
1087: ifne          1094
1090: iconst_1
1091: goto          1095
1094: iconst_0
1095: invokestatic  #115
1098: return
Exception table:
from    to  target type
507   524   527   Class java/lang/NullPointerException
Source File: /data/islam/DBT-workbench/resources/subjects/fixed/jsoup/39/src/test/java/org/jsoup/helper/RegressionTest0.java
Bytecode File: /data/islam/DBT-workbench/resources/subjects/fixed/jsoup/39/target/test-classes/org/jsoup/helper/RegressionTest0.class
Class name: RegressionTest0
Method name: test45
Start line: 756
End line: 872
Method source code: 
    public void test45() throws Throwable {
        if (debug)
            System.out.format("%n%s%n", "RegressionTest0.test45");
        java.io.InputStream inputStream0 = null;
        org.jsoup.nodes.Document document4 = org.jsoup.nodes.Document.createShell("hi!");
        java.util.List<org.jsoup.nodes.TextNode> textNodeList5 = document4.textNodes();
        org.jsoup.nodes.Element element6 = document4.nextElementSibling();
        java.lang.String str7 = document4.title();
        java.util.List<org.jsoup.nodes.Node> nodeList8 = document4.childNodes();
        org.jsoup.nodes.Document document10 = org.jsoup.nodes.Document.createShell("hi!");
        java.util.List<org.jsoup.nodes.TextNode> textNodeList11 = document10.textNodes();
        org.jsoup.nodes.Document document13 = org.jsoup.nodes.Document.createShell("hi!");
        java.util.List<org.jsoup.nodes.TextNode> textNodeList14 = document13.textNodes();
        org.jsoup.nodes.Element element15 = document13.nextElementSibling();
        org.jsoup.nodes.Document document17 = org.jsoup.nodes.Document.createShell("hi!");
        java.util.List<org.jsoup.nodes.TextNode> textNodeList18 = document17.textNodes();
        org.jsoup.nodes.Document document20 = org.jsoup.nodes.Document.createShell("hi!");
        java.util.List<org.jsoup.nodes.TextNode> textNodeList21 = document20.textNodes();
        org.jsoup.nodes.Element element22 = document20.nextElementSibling();
        org.jsoup.nodes.Element[] elementArray23 = new org.jsoup.nodes.Element[] { document10, document13, document17, document20 };
        java.util.ArrayList<org.jsoup.nodes.Element> elementList24 = new java.util.ArrayList<org.jsoup.nodes.Element>();
        boolean boolean25 = java.util.Collections.addAll((java.util.Collection<org.jsoup.nodes.Element>) elementList24, elementArray23);
        org.jsoup.select.Elements elements26 = new org.jsoup.select.Elements((java.util.Collection<org.jsoup.nodes.Element>) elementList24);
        org.jsoup.nodes.Document document29 = org.jsoup.nodes.Document.createShell("hi!");
        org.jsoup.nodes.Element element30 = elements26.set(0, (org.jsoup.nodes.Element) document29);
        java.util.List<org.jsoup.nodes.TextNode> textNodeList31 = element30.textNodes();
        org.jsoup.nodes.Element element32 = document4.appendChild((org.jsoup.nodes.Node) element30);
        java.util.Set<java.lang.String> strSet33 = document4.classNames();
        java.util.LinkedList<java.util.Set<java.lang.String>> strSetList34 = new java.util.LinkedList<java.util.Set<java.lang.String>>();
        boolean boolean35 = strSetList34.add(strSet33);
        org.jsoup.nodes.Document document37 = org.jsoup.nodes.Document.createShell("hi!");
        java.util.List<org.jsoup.nodes.TextNode> textNodeList38 = document37.textNodes();
        org.jsoup.nodes.Document document40 = org.jsoup.nodes.Document.createShell("hi!");
        java.util.List<org.jsoup.nodes.TextNode> textNodeList41 = document40.textNodes();
        org.jsoup.nodes.Element element42 = document40.nextElementSibling();
        org.jsoup.nodes.Document document44 = org.jsoup.nodes.Document.createShell("hi!");
        java.util.List<org.jsoup.nodes.TextNode> textNodeList45 = document44.textNodes();
        org.jsoup.nodes.Document document47 = org.jsoup.nodes.Document.createShell("hi!");
        java.util.List<org.jsoup.nodes.TextNode> textNodeList48 = document47.textNodes();
        org.jsoup.nodes.Element element49 = document47.nextElementSibling();
        org.jsoup.nodes.Element[] elementArray50 = new org.jsoup.nodes.Element[] { document37, document40, document44, document47 };
        java.util.ArrayList<org.jsoup.nodes.Element> elementList51 = new java.util.ArrayList<org.jsoup.nodes.Element>();
        boolean boolean52 = java.util.Collections.addAll((java.util.Collection<org.jsoup.nodes.Element>) elementList51, elementArray50);
        org.jsoup.select.Elements elements53 = new org.jsoup.select.Elements((java.util.Collection<org.jsoup.nodes.Element>) elementList51);
        org.jsoup.nodes.Document document56 = org.jsoup.nodes.Document.createShell("hi!");
        org.jsoup.nodes.Element element57 = elements53.set(0, (org.jsoup.nodes.Element) document56);
        java.lang.String[] strArray60 = new java.lang.String[] { "UTF-8", "UTF-8" };
        java.util.LinkedHashSet<java.lang.String> strSet61 = new java.util.LinkedHashSet<java.lang.String>();
        boolean boolean62 = java.util.Collections.addAll((java.util.Collection<java.lang.String>) strSet61, strArray60);
        org.jsoup.nodes.Element element63 = element57.classNames((java.util.Set<java.lang.String>) strSet61);
        org.jsoup.select.Elements elements65 = element57.getElementsContainingText("UTF-8");
        org.jsoup.select.Elements elements67 = element57.getElementsContainingText(".");
        java.util.Set<java.lang.String> strSet68 = element57.classNames();
        boolean boolean69 = strSetList34.offer(strSet68);
        org.jsoup.select.Evaluator.AttributeWithValueNot attributeWithValueNot72 = new org.jsoup.select.Evaluator.AttributeWithValueNot("[<html>\n <head></head>\n <body></body>\n</html>, <html>\n <head></head>\n <body></body>\n</html>, <html>\n <head></head>\n <body></body>\n</html>]", "<html>\n <head></head>\n <body></body>\n</html>");
        boolean boolean73 = strSetList34.contains((java.lang.Object) "[<html>\n <head></head>\n <body></body>\n</html>, <html>\n <head></head>\n <body></body>\n</html>, <html>\n <head></head>\n <body></body>\n</html>]");
        org.jsoup.parser.Parser parser74 = org.jsoup.parser.Parser.xmlParser();
        org.jsoup.parser.Parser parser76 = parser74.setTrackErrors((int) (short) 100);
        java.util.List<org.jsoup.parser.ParseError> parseErrorList77 = parser76.getErrors();
        boolean boolean78 = strSetList34.remove((java.lang.Object) parser76);
        // The following exception was thrown during execution in test generation
        try {
            org.jsoup.nodes.Document document79 = org.jsoup.helper.DataUtil.load(inputStream0, ":contains(:only-child", "<html></html>", parser76);
            org.junit.Assert.fail("Expected exception of type java.lang.NullPointerException; message: null");
        } catch (java.lang.NullPointerException e) {
        // Expected exception.
        }
        org.junit.Assert.assertNotNull(document4);
        org.junit.Assert.assertNotNull(textNodeList5);
        org.junit.Assert.assertNull(element6);
        org.junit.Assert.assertEquals("'" + str7 + "' != '" + "" + "'", str7, "");
        org.junit.Assert.assertNotNull(nodeList8);
        org.junit.Assert.assertNotNull(document10);
        org.junit.Assert.assertNotNull(textNodeList11);
        org.junit.Assert.assertNotNull(document13);
        org.junit.Assert.assertNotNull(textNodeList14);
        org.junit.Assert.assertNull(element15);
        org.junit.Assert.assertNotNull(document17);
        org.junit.Assert.assertNotNull(textNodeList18);
        org.junit.Assert.assertNotNull(document20);
        org.junit.Assert.assertNotNull(textNodeList21);
        org.junit.Assert.assertNull(element22);
        org.junit.Assert.assertNotNull(elementArray23);
        org.junit.Assert.assertTrue("'" + boolean25 + "' != '" + true + "'", boolean25 == true);
        org.junit.Assert.assertNotNull(document29);
        org.junit.Assert.assertNotNull(element30);
        org.junit.Assert.assertNotNull(textNodeList31);
        org.junit.Assert.assertNotNull(element32);
        org.junit.Assert.assertNotNull(strSet33);
        org.junit.Assert.assertTrue("'" + boolean35 + "' != '" + true + "'", boolean35 == true);
        org.junit.Assert.assertNotNull(document37);
        org.junit.Assert.assertNotNull(textNodeList38);
        org.junit.Assert.assertNotNull(document40);
        org.junit.Assert.assertNotNull(textNodeList41);
        org.junit.Assert.assertNull(element42);
        org.junit.Assert.assertNotNull(document44);
        org.junit.Assert.assertNotNull(textNodeList45);
        org.junit.Assert.assertNotNull(document47);
        org.junit.Assert.assertNotNull(textNodeList48);
        org.junit.Assert.assertNull(element49);
        org.junit.Assert.assertNotNull(elementArray50);
        org.junit.Assert.assertTrue("'" + boolean52 + "' != '" + true + "'", boolean52 == true);
        org.junit.Assert.assertNotNull(document56);
        org.junit.Assert.assertNotNull(element57);
        org.junit.Assert.assertNotNull(strArray60);
        org.junit.Assert.assertTrue("'" + boolean62 + "' != '" + true + "'", boolean62 == true);
        org.junit.Assert.assertNotNull(element63);
        org.junit.Assert.assertNotNull(elements65);
        org.junit.Assert.assertNotNull(elements67);
        org.junit.Assert.assertNotNull(strSet68);
        org.junit.Assert.assertTrue("'" + boolean69 + "' != '" + true + "'", boolean69 == true);
        org.junit.Assert.assertTrue("'" + boolean73 + "' != '" + false + "'", boolean73 == false);
        org.junit.Assert.assertNotNull(parser74);
        org.junit.Assert.assertNotNull(parser76);
        org.junit.Assert.assertNull(parseErrorList77);
        org.junit.Assert.assertTrue("'" + boolean78 + "' != '" + false + "'", boolean78 == false);
    }
Method byte code: 
0: getstatic     #2
3: ifeq          24
6: getstatic     #3
9: ldc           #4
11: iconst_1
12: anewarray     #5
15: dup
16: iconst_0
17: ldc           #157
19: aastore
20: invokevirtual #7
23: pop
24: aconst_null
25: astore_1
26: ldc           #14
28: invokestatic  #124
31: astore_2
32: aload_2
33: invokevirtual #125
36: astore_3
37: aload_2
38: invokevirtual #126
41: astore        4
43: aload_2
44: invokevirtual #127
47: astore        5
49: aload_2
50: invokevirtual #128
53: astore        6
55: ldc           #14
57: invokestatic  #124
60: astore        7
62: aload         7
64: invokevirtual #125
67: astore        8
69: ldc           #14
71: invokestatic  #124
74: astore        9
76: aload         9
78: invokevirtual #125
81: astore        10
83: aload         9
85: invokevirtual #126
88: astore        11
90: ldc           #14
92: invokestatic  #124
95: astore        12
97: aload         12
99: invokevirtual #125
102: astore        13
104: ldc           #14
106: invokestatic  #124
109: astore        14
111: aload         14
113: invokevirtual #125
116: astore        15
118: aload         14
120: invokevirtual #126
123: astore        16
125: iconst_4
126: anewarray     #129
129: dup
130: iconst_0
131: aload         7
133: aastore
134: dup
135: iconst_1
136: aload         9
138: aastore
139: dup
140: iconst_2
141: aload         12
143: aastore
144: dup
145: iconst_3
146: aload         14
148: aastore
149: astore        17
151: new           #130
154: dup
155: invokespecial #131
158: astore        18
160: aload         18
162: aload         17
164: invokestatic  #132
167: istore        19
169: new           #133
172: dup
173: aload         18
175: invokespecial #134
178: astore        20
180: ldc           #14
182: invokestatic  #124
185: astore        21
187: aload         20
189: iconst_0
190: aload         21
192: invokevirtual #135
195: astore        22
197: aload         22
199: invokevirtual #136
202: astore        23
204: aload_2
205: aload         22
207: invokevirtual #137
210: astore        24
212: aload_2
213: invokevirtual #138
216: astore        25
218: new           #139
221: dup
222: invokespecial #140
225: astore        26
227: aload         26
229: aload         25
231: invokevirtual #141
234: istore        27
236: ldc           #14
238: invokestatic  #124
241: astore        28
243: aload         28
245: invokevirtual #125
248: astore        29
250: ldc           #14
252: invokestatic  #124
255: astore        30
257: aload         30
259: invokevirtual #125
262: astore        31
264: aload         30
266: invokevirtual #126
269: astore        32
271: ldc           #14
273: invokestatic  #124
276: astore        33
278: aload         33
280: invokevirtual #125
283: astore        34
285: ldc           #14
287: invokestatic  #124
290: astore        35
292: aload         35
294: invokevirtual #125
297: astore        36
299: aload         35
301: invokevirtual #126
304: astore        37
306: iconst_4
307: anewarray     #129
310: dup
311: iconst_0
312: aload         28
314: aastore
315: dup
316: iconst_1
317: aload         30
319: aastore
320: dup
321: iconst_2
322: aload         33
324: aastore
325: dup
326: iconst_3
327: aload         35
329: aastore
330: astore        38
332: new           #130
335: dup
336: invokespecial #131
339: astore        39
341: aload         39
343: aload         38
345: invokestatic  #132
348: istore        40
350: new           #133
353: dup
354: aload         39
356: invokespecial #134
359: astore        41
361: ldc           #14
363: invokestatic  #124
366: astore        42
368: aload         41
370: iconst_0
371: aload         42
373: invokevirtual #135
376: astore        43
378: iconst_2
379: anewarray     #142
382: dup
383: iconst_0
384: ldc           #34
386: aastore
387: dup
388: iconst_1
389: ldc           #34
391: aastore
392: astore        44
394: new           #143
397: dup
398: invokespecial #144
401: astore        45
403: aload         45
405: aload         44
407: invokestatic  #132
410: istore        46
412: aload         43
414: aload         45
416: invokevirtual #145
419: astore        47
421: aload         43
423: ldc           #34
425: invokevirtual #146
428: astore        48
430: aload         43
432: ldc           #22
434: invokevirtual #146
437: astore        49
439: aload         43
441: invokevirtual #147
444: astore        50
446: aload         26
448: aload         50
450: invokevirtual #148
453: istore        51
455: new           #149
458: dup
459: ldc           #25
461: ldc           #50
463: invokespecial #150
466: astore        52
468: aload         26
470: ldc           #25
472: invokevirtual #151
475: istore        53
477: invokestatic  #41
480: astore        54
482: aload         54
484: bipush        100
486: invokevirtual #42
489: astore        55
491: aload         55
493: invokevirtual #94
496: astore        56
498: aload         26
500: aload         55
502: invokevirtual #152
505: istore        57
507: aload_1
508: ldc           #158
510: ldc           #159
512: aload         55
514: invokestatic  #9
517: astore        58
519: ldc           #10
521: invokestatic  #11
524: goto          529
527: astore        58
529: aload_2
530: invokestatic  #46
533: aload_3
534: invokestatic  #46
537: aload         4
539: invokestatic  #16
542: new           #108
545: dup
546: invokespecial #109
549: ldc           #110
551: invokevirtual #111
554: aload         5
556: invokevirtual #111
559: ldc           #155
561: invokevirtual #111
564: invokevirtual #114
567: aload         5
569: ldc           #8
571: invokestatic  #156
574: aload         6
576: invokestatic  #46
579: aload         7
581: invokestatic  #46
584: aload         8
586: invokestatic  #46
589: aload         9
591: invokestatic  #46
594: aload         10
596: invokestatic  #46
599: aload         11
601: invokestatic  #16
604: aload         12
606: invokestatic  #46
609: aload         13
611: invokestatic  #46
614: aload         14
616: invokestatic  #46
619: aload         15
621: invokestatic  #46
624: aload         16
626: invokestatic  #16
629: aload         17
631: invokestatic  #46
634: new           #108
637: dup
638: invokespecial #109
641: ldc           #110
643: invokevirtual #111
646: iload         19
648: invokevirtual #112
651: ldc           #113
653: invokevirtual #111
656: iconst_1
657: invokevirtual #112
660: ldc           #110
662: invokevirtual #111
665: invokevirtual #114
668: iload         19
670: iconst_1
671: if_icmpne     678
674: iconst_1
675: goto          679
678: iconst_0
679: invokestatic  #115
682: aload         21
684: invokestatic  #46
687: aload         22
689: invokestatic  #46
692: aload         23
694: invokestatic  #46
697: aload         24
699: invokestatic  #46
702: aload         25
704: invokestatic  #46
707: new           #108
710: dup
711: invokespecial #109
714: ldc           #110
716: invokevirtual #111
719: iload         27
721: invokevirtual #112
724: ldc           #113
726: invokevirtual #111
729: iconst_1
730: invokevirtual #112
733: ldc           #110
735: invokevirtual #111
738: invokevirtual #114
741: iload         27
743: iconst_1
744: if_icmpne     751
747: iconst_1
748: goto          752
751: iconst_0
752: invokestatic  #115
755: aload         28
757: invokestatic  #46
760: aload         29
762: invokestatic  #46
765: aload         30
767: invokestatic  #46
770: aload         31
772: invokestatic  #46
775: aload         32
777: invokestatic  #16
780: aload         33
782: invokestatic  #46
785: aload         34
787: invokestatic  #46
790: aload         35
792: invokestatic  #46
795: aload         36
797: invokestatic  #46
800: aload         37
802: invokestatic  #16
805: aload         38
807: invokestatic  #46
810: new           #108
813: dup
814: invokespecial #109
817: ldc           #110
819: invokevirtual #111
822: iload         40
824: invokevirtual #112
827: ldc           #113
829: invokevirtual #111
832: iconst_1
833: invokevirtual #112
836: ldc           #110
838: invokevirtual #111
841: invokevirtual #114
844: iload         40
846: iconst_1
847: if_icmpne     854
850: iconst_1
851: goto          855
854: iconst_0
855: invokestatic  #115
858: aload         42
860: invokestatic  #46
863: aload         43
865: invokestatic  #46
868: aload         44
870: invokestatic  #46
873: new           #108
876: dup
877: invokespecial #109
880: ldc           #110
882: invokevirtual #111
885: iload         46
887: invokevirtual #112
890: ldc           #113
892: invokevirtual #111
895: iconst_1
896: invokevirtual #112
899: ldc           #110
901: invokevirtual #111
904: invokevirtual #114
907: iload         46
909: iconst_1
910: if_icmpne     917
913: iconst_1
914: goto          918
917: iconst_0
918: invokestatic  #115
921: aload         47
923: invokestatic  #46
926: aload         48
928: invokestatic  #46
931: aload         49
933: invokestatic  #46
936: aload         50
938: invokestatic  #46
941: new           #108
944: dup
945: invokespecial #109
948: ldc           #110
950: invokevirtual #111
953: iload         51
955: invokevirtual #112
958: ldc           #113
960: invokevirtual #111
963: iconst_1
964: invokevirtual #112
967: ldc           #110
969: invokevirtual #111
972: invokevirtual #114
975: iload         51
977: iconst_1
978: if_icmpne     985
981: iconst_1
982: goto          986
985: iconst_0
986: invokestatic  #115
989: new           #108
992: dup
993: invokespecial #109
996: ldc           #110
998: invokevirtual #111
1001: iload         53
1003: invokevirtual #112
1006: ldc           #113
1008: invokevirtual #111
1011: iconst_0
1012: invokevirtual #112
1015: ldc           #110
1017: invokevirtual #111
1020: invokevirtual #114
1023: iload         53
1025: ifne          1032
1028: iconst_1
1029: goto          1033
1032: iconst_0
1033: invokestatic  #115
1036: aload         54
1038: invokestatic  #46
1041: aload         55
1043: invokestatic  #46
1046: aload         56
1048: invokestatic  #16
1051: new           #108
1054: dup
1055: invokespecial #109
1058: ldc           #110
1060: invokevirtual #111
1063: iload         57
1065: invokevirtual #112
1068: ldc           #113
1070: invokevirtual #111
1073: iconst_0
1074: invokevirtual #112
1077: ldc           #110
1079: invokevirtual #111
1082: invokevirtual #114
1085: iload         57
1087: ifne          1094
1090: iconst_1
1091: goto          1095
1094: iconst_0
1095: invokestatic  #115
1098: return
Exception table:
from    to  target type
507   524   527   Class java/lang/NullPointerException
Source File: /data/islam/DBT-workbench/resources/subjects/fixed/jsoup/39/src/test/java/org/jsoup/helper/RegressionTest0.java
Bytecode File: /data/islam/DBT-workbench/resources/subjects/fixed/jsoup/39/target/test-classes/org/jsoup/helper/RegressionTest0.class
Class name: RegressionTest0
Method name: test46
Start line: 875
End line: 880
Method source code: 
    public void test46() throws Throwable {
        if (debug)
            System.out.format("%n%s%n", "RegressionTest0.test46");
        java.lang.String str1 = org.jsoup.helper.DataUtil.getCharsetFromContentType("");
        org.junit.Assert.assertNull(str1);
    }
Method byte code: 
0: getstatic     #2
3: ifeq          24
6: getstatic     #3
9: ldc           #4
11: iconst_1
12: anewarray     #5
15: dup
16: iconst_0
17: ldc           #160
19: aastore
20: invokevirtual #7
23: pop
24: ldc           #8
26: invokestatic  #15
29: astore_1
30: aload_1
31: invokestatic  #16
34: return
Source File: /data/islam/DBT-workbench/resources/subjects/fixed/jsoup/39/src/test/java/org/jsoup/helper/RegressionTest0.java
Bytecode File: /data/islam/DBT-workbench/resources/subjects/fixed/jsoup/39/target/test-classes/org/jsoup/helper/RegressionTest0.class
Class name: RegressionTest0
Method name: test47
Start line: 883
End line: 894
Method source code: 
    public void test47() throws Throwable {
        if (debug)
            System.out.format("%n%s%n", "RegressionTest0.test47");
        java.io.File file0 = null;
        // The following exception was thrown during execution in test generation
        try {
            org.jsoup.nodes.Document document3 = org.jsoup.helper.DataUtil.load(file0, "<html> <head></head> <body></body> </html> <html> <head></head> <body></body> </html> <html> <head></head> <body></body> </html> <html> <head></head> <body></body> </html>", "[#root*=:matches(null]");
            org.junit.Assert.fail("Expected exception of type java.lang.NullPointerException; message: null");
        } catch (java.lang.NullPointerException e) {
        // Expected exception.
        }
    }
Method byte code: 
0: getstatic     #2
3: ifeq          24
6: getstatic     #3
9: ldc           #4
11: iconst_1
12: anewarray     #5
15: dup
16: iconst_0
17: ldc           #161
19: aastore
20: invokevirtual #7
23: pop
24: aconst_null
25: astore_1
26: aload_1
27: ldc           #64
29: ldc           #162
31: invokestatic  #35
34: astore_2
35: ldc           #10
37: invokestatic  #11
40: goto          44
43: astore_2
44: return
Exception table:
from    to  target type
26    40    43   Class java/lang/NullPointerException
Source File: /data/islam/DBT-workbench/resources/subjects/fixed/jsoup/39/src/test/java/org/jsoup/helper/RegressionTest0.java
Bytecode File: /data/islam/DBT-workbench/resources/subjects/fixed/jsoup/39/target/test-classes/org/jsoup/helper/RegressionTest0.class
Class name: RegressionTest0
Method name: test48
Start line: 897
End line: 912
Method source code: 
    public void test48() throws Throwable {
        if (debug)
            System.out.format("%n%s%n", "RegressionTest0.test48");
        java.io.InputStream inputStream0 = null;
        org.jsoup.parser.Parser parser3 = org.jsoup.parser.Parser.xmlParser();
        org.jsoup.nodes.Document document6 = parser3.parseInput("#root", "#doctype");
        // The following exception was thrown during execution in test generation
        try {
            org.jsoup.nodes.Document document7 = org.jsoup.helper.DataUtil.load(inputStream0, "<html>\n <head></head>\n <body></body>\n</html>\n<html>\n <head></head>\n <body></body>\n</html>\n<html>\n <head></head>\n <body></body>\n</html>\n<#root>\n <html>\n  <head></head>\n  <body></body>\n </html>\n</#root>\n<html>\n <head></head>\n <body></body>\n</html>\n<html>\n <head></head>\n <body></body>\n</html>", ":contains(#comment", parser3);
            org.junit.Assert.fail("Expected exception of type java.lang.NullPointerException; message: null");
        } catch (java.lang.NullPointerException e) {
        // Expected exception.
        }
        org.junit.Assert.assertNotNull(parser3);
        org.junit.Assert.assertNotNull(document6);
    }
Method byte code: 
0: getstatic     #2
3: ifeq          24
6: getstatic     #3
9: ldc           #4
11: iconst_1
12: anewarray     #5
15: dup
16: iconst_0
17: ldc           #163
19: aastore
20: invokevirtual #7
23: pop
24: aconst_null
25: astore_1
26: invokestatic  #41
29: astore_2
30: aload_2
31: ldc           #164
33: ldc           #82
35: invokevirtual #58
38: astore_3
39: aload_1
40: ldc           #165
42: ldc           #166
44: aload_2
45: invokestatic  #9
48: astore        4
50: ldc           #10
52: invokestatic  #11
55: goto          60
58: astore        4
60: aload_2
61: invokestatic  #46
64: aload_3
65: invokestatic  #46
68: return
Exception table:
from    to  target type
39    55    58   Class java/lang/NullPointerException
Source File: /data/islam/DBT-workbench/resources/subjects/fixed/jsoup/39/src/test/java/org/jsoup/helper/RegressionTest0.java
Bytecode File: /data/islam/DBT-workbench/resources/subjects/fixed/jsoup/39/target/test-classes/org/jsoup/helper/RegressionTest0.class
Class name: RegressionTest0
Method name: test49
Start line: 915
End line: 926
Method source code: 
    public void test49() throws Throwable {
        if (debug)
            System.out.format("%n%s%n", "RegressionTest0.test49");
        java.io.InputStream inputStream0 = null;
        // The following exception was thrown during execution in test generation
        try {
            org.jsoup.nodes.Document document3 = org.jsoup.helper.DataUtil.load(inputStream0, ":only-child", ":containsOwn(:containsown(");
            org.junit.Assert.fail("Expected exception of type java.lang.NullPointerException; message: null");
        } catch (java.lang.NullPointerException e) {
        // Expected exception.
        }
    }
Method byte code: 
0: getstatic     #2
3: ifeq          24
6: getstatic     #3
9: ldc           #4
11: iconst_1
12: anewarray     #5
15: dup
16: iconst_0
17: ldc           #167
19: aastore
20: invokevirtual #7
23: pop
24: aconst_null
25: astore_1
26: aload_1
27: ldc           #44
29: ldc           #168
31: invokestatic  #23
34: astore_2
35: ldc           #10
37: invokestatic  #11
40: goto          44
43: astore_2
44: return
Exception table:
from    to  target type
26    40    43   Class java/lang/NullPointerException
Source File: /data/islam/DBT-workbench/resources/subjects/fixed/jsoup/39/src/test/java/org/jsoup/helper/RegressionTest0.java
Bytecode File: /data/islam/DBT-workbench/resources/subjects/fixed/jsoup/39/target/test-classes/org/jsoup/helper/RegressionTest0.class
Class name: RegressionTest0
Method name: test50
Start line: 929
End line: 940
Method source code: 
    public void test50() throws Throwable {
        if (debug)
            System.out.format("%n%s%n", "RegressionTest0.test50");
        java.io.File file0 = null;
        // The following exception was thrown during execution in test generation
        try {
            org.jsoup.nodes.Document document3 = org.jsoup.helper.DataUtil.load(file0, ":nth-last-of-type(-1n+1)", "");
            org.junit.Assert.fail("Expected exception of type java.lang.NullPointerException; message: null");
        } catch (java.lang.NullPointerException e) {
        // Expected exception.
        }
    }
Method byte code: 
0: getstatic     #2
3: ifeq          24
6: getstatic     #3
9: ldc           #4
11: iconst_1
12: anewarray     #5
15: dup
16: iconst_0
17: ldc           #169
19: aastore
20: invokevirtual #7
23: pop
24: aconst_null
25: astore_1
26: aload_1
27: ldc           #170
29: ldc           #8
31: invokestatic  #35
34: astore_2
35: ldc           #10
37: invokestatic  #11
40: goto          44
43: astore_2
44: return
Exception table:
from    to  target type
26    40    43   Class java/lang/NullPointerException
Source File: /data/islam/DBT-workbench/resources/subjects/fixed/jsoup/39/src/test/java/org/jsoup/helper/RegressionTest0.java
Bytecode File: /data/islam/DBT-workbench/resources/subjects/fixed/jsoup/39/target/test-classes/org/jsoup/helper/RegressionTest0.class
Class name: RegressionTest0
Method name: test51
Start line: 943
End line: 954
Method source code: 
    public void test51() throws Throwable {
        if (debug)
            System.out.format("%n%s%n", "RegressionTest0.test51");
        java.io.File file0 = null;
        // The following exception was thrown during execution in test generation
        try {
            org.jsoup.nodes.Document document3 = org.jsoup.helper.DataUtil.load(file0, "[<html>\n <head></head>\n <body></body>\n</html>, <html>\n <head></head>\n <body></body>\n</html>, <html>\n <head></head>\n <body></body>\n</html>]", "<html>\n <head></head>\n <body></body>\n</html>\n<#root>\n <html>\n  <head></head>\n  <body></body>\n </html>\n</#root>");
            org.junit.Assert.fail("Expected exception of type java.lang.NullPointerException; message: null");
        } catch (java.lang.NullPointerException e) {
        // Expected exception.
        }
    }
Method byte code: 
0: getstatic     #2
3: ifeq          24
6: getstatic     #3
9: ldc           #4
11: iconst_1
12: anewarray     #5
15: dup
16: iconst_0
17: ldc           #171
19: aastore
20: invokevirtual #7
23: pop
24: aconst_null
25: astore_1
26: aload_1
27: ldc           #25
29: ldc           #48
31: invokestatic  #35
34: astore_2
35: ldc           #10
37: invokestatic  #11
40: goto          44
43: astore_2
44: return
Exception table:
from    to  target type
26    40    43   Class java/lang/NullPointerException
Source File: /data/islam/DBT-workbench/resources/subjects/fixed/jsoup/39/src/test/java/org/jsoup/helper/RegressionTest0.java
Bytecode File: /data/islam/DBT-workbench/resources/subjects/fixed/jsoup/39/target/test-classes/org/jsoup/helper/RegressionTest0.class
Class name: RegressionTest0
Method name: test52
Start line: 957
End line: 968
Method source code: 
    public void test52() throws Throwable {
        if (debug)
            System.out.format("%n%s%n", "RegressionTest0.test52");
        java.io.InputStream inputStream0 = null;
        // The following exception was thrown during execution in test generation
        try {
            java.nio.ByteBuffer byteBuffer2 = org.jsoup.helper.DataUtil.readToByteBuffer(inputStream0, 0);
            org.junit.Assert.fail("Expected exception of type java.lang.NullPointerException; message: null");
        } catch (java.lang.NullPointerException e) {
        // Expected exception.
        }
    }
Method byte code: 
0: getstatic     #2
3: ifeq          24
6: getstatic     #3
9: ldc           #4
11: iconst_1
12: anewarray     #5
15: dup
16: iconst_0
17: ldc           #172
19: aastore
20: invokevirtual #7
23: pop
24: aconst_null
25: astore_1
26: aload_1
27: iconst_0
28: invokestatic  #20
31: astore_2
32: ldc           #10
34: invokestatic  #11
37: goto          41
40: astore_2
41: return
Exception table:
from    to  target type
26    37    40   Class java/lang/NullPointerException
Source File: /data/islam/DBT-workbench/resources/subjects/fixed/jsoup/39/src/test/java/org/jsoup/helper/RegressionTest0.java
Bytecode File: /data/islam/DBT-workbench/resources/subjects/fixed/jsoup/39/target/test-classes/org/jsoup/helper/RegressionTest0.class
Class name: RegressionTest0
Method name: test53
Start line: 971
End line: 992
Method source code: 
    public void test53() throws Throwable {
        if (debug)
            System.out.format("%n%s%n", "RegressionTest0.test53");
        java.nio.ByteBuffer byteBuffer0 = null;
        org.jsoup.parser.Parser parser3 = org.jsoup.parser.Parser.xmlParser();
        org.jsoup.parser.Parser parser5 = parser3.setTrackErrors((int) (short) 100);
        boolean boolean6 = parser5.isTrackErrors();
        org.jsoup.parser.Parser parser8 = parser5.setTrackErrors(2);
        java.util.List<org.jsoup.parser.ParseError> parseErrorList9 = parser8.getErrors();
        // The following exception was thrown during execution in test generation
        try {
            org.jsoup.nodes.Document document10 = org.jsoup.helper.DataUtil.parseByteData(byteBuffer0, "#text", "#text", parser8);
            org.junit.Assert.fail("Expected exception of type java.nio.charset.IllegalCharsetNameException; message: #text");
        } catch (java.nio.charset.IllegalCharsetNameException e) {
        // Expected exception.
        }
        org.junit.Assert.assertNotNull(parser3);
        org.junit.Assert.assertNotNull(parser5);
        org.junit.Assert.assertTrue("'" + boolean6 + "' != '" + true + "'", boolean6 == true);
        org.junit.Assert.assertNotNull(parser8);
        org.junit.Assert.assertNull(parseErrorList9);
    }
Method byte code: 
0: getstatic     #2
3: ifeq          24
6: getstatic     #3
9: ldc           #4
11: iconst_1
12: anewarray     #5
15: dup
16: iconst_0
17: ldc           #173
19: aastore
20: invokevirtual #7
23: pop
24: aconst_null
25: astore_1
26: invokestatic  #41
29: astore_2
30: aload_2
31: bipush        100
33: invokevirtual #42
36: astore_3
37: aload_3
38: invokevirtual #105
41: istore        4
43: aload_3
44: iconst_2
45: invokevirtual #42
48: astore        5
50: aload         5
52: invokevirtual #94
55: astore        6
57: aload_1
58: ldc           #59
60: ldc           #59
62: aload         5
64: invokestatic  #27
67: astore        7
69: ldc           #61
71: invokestatic  #11
74: goto          79
77: astore        7
79: aload_2
80: invokestatic  #46
83: aload_3
84: invokestatic  #46
87: new           #108
90: dup
91: invokespecial #109
94: ldc           #110
96: invokevirtual #111
99: iload         4
101: invokevirtual #112
104: ldc           #113
106: invokevirtual #111
109: iconst_1
110: invokevirtual #112
113: ldc           #110
115: invokevirtual #111
118: invokevirtual #114
121: iload         4
123: iconst_1
124: if_icmpne     131
127: iconst_1
128: goto          132
131: iconst_0
132: invokestatic  #115
135: aload         5
137: invokestatic  #46
140: aload         6
142: invokestatic  #16
145: return
Exception table:
from    to  target type
57    74    77   Class java/nio/charset/IllegalCharsetNameException
Source File: /data/islam/DBT-workbench/resources/subjects/fixed/jsoup/39/src/test/java/org/jsoup/helper/RegressionTest0.java
Bytecode File: /data/islam/DBT-workbench/resources/subjects/fixed/jsoup/39/target/test-classes/org/jsoup/helper/RegressionTest0.class
Class name: RegressionTest0
Method name: test54
Start line: 995
End line: 1006
Method source code: 
    public void test54() throws Throwable {
        if (debug)
            System.out.format("%n%s%n", "RegressionTest0.test54");
        java.io.InputStream inputStream0 = null;
        // The following exception was thrown during execution in test generation
        try {
            org.jsoup.nodes.Document document3 = org.jsoup.helper.DataUtil.load(inputStream0, "", ":first-child");
            org.junit.Assert.fail("Expected exception of type java.lang.NullPointerException; message: null");
        } catch (java.lang.NullPointerException e) {
        // Expected exception.
        }
    }
Method byte code: 
0: getstatic     #2
3: ifeq          24
6: getstatic     #3
9: ldc           #4
11: iconst_1
12: anewarray     #5
15: dup
16: iconst_0
17: ldc           #174
19: aastore
20: invokevirtual #7
23: pop
24: aconst_null
25: astore_1
26: aload_1
27: ldc           #8
29: ldc           #175
31: invokestatic  #23
34: astore_2
35: ldc           #10
37: invokestatic  #11
40: goto          44
43: astore_2
44: return
Exception table:
from    to  target type
26    40    43   Class java/lang/NullPointerException
Source File: /data/islam/DBT-workbench/resources/subjects/fixed/jsoup/39/src/test/java/org/jsoup/helper/RegressionTest0.java
Bytecode File: /data/islam/DBT-workbench/resources/subjects/fixed/jsoup/39/target/test-classes/org/jsoup/helper/RegressionTest0.class
Class name: RegressionTest0
Method name: test55
Start line: 1009
End line: 1026
Method source code: 
    public void test55() throws Throwable {
        if (debug)
            System.out.format("%n%s%n", "RegressionTest0.test55");
        java.nio.ByteBuffer byteBuffer0 = null;
        org.jsoup.parser.Parser parser3 = org.jsoup.parser.Parser.xmlParser();
        org.jsoup.parser.Parser parser5 = parser3.setTrackErrors((int) '#');
        org.jsoup.parser.Parser parser7 = parser3.setTrackErrors(0);
        // The following exception was thrown during execution in test generation
        try {
            org.jsoup.nodes.Document document8 = org.jsoup.helper.DataUtil.parseByteData(byteBuffer0, "[#root*=:matches(null]", ":matchesOwn(null", parser3);
            org.junit.Assert.fail("Expected exception of type java.nio.charset.IllegalCharsetNameException; message: [#root*=:matches(null]");
        } catch (java.nio.charset.IllegalCharsetNameException e) {
        // Expected exception.
        }
        org.junit.Assert.assertNotNull(parser3);
        org.junit.Assert.assertNotNull(parser5);
        org.junit.Assert.assertNotNull(parser7);
    }
Method byte code: 
0: getstatic     #2
3: ifeq          24
6: getstatic     #3
9: ldc           #4
11: iconst_1
12: anewarray     #5
15: dup
16: iconst_0
17: ldc           #176
19: aastore
20: invokevirtual #7
23: pop
24: aconst_null
25: astore_1
26: invokestatic  #41
29: astore_2
30: aload_2
31: bipush        35
33: invokevirtual #42
36: astore_3
37: aload_2
38: iconst_0
39: invokevirtual #42
42: astore        4
44: aload_1
45: ldc           #162
47: ldc           #177
49: aload_2
50: invokestatic  #27
53: astore        5
55: ldc           #178
57: invokestatic  #11
60: goto          65
63: astore        5
65: aload_2
66: invokestatic  #46
69: aload_3
70: invokestatic  #46
73: aload         4
75: invokestatic  #46
78: return
Exception table:
from    to  target type
44    60    63   Class java/nio/charset/IllegalCharsetNameException
Source File: /data/islam/DBT-workbench/resources/subjects/fixed/jsoup/39/src/test/java/org/jsoup/helper/RegressionTest0.java
Bytecode File: /data/islam/DBT-workbench/resources/subjects/fixed/jsoup/39/target/test-classes/org/jsoup/helper/RegressionTest0.class
Class name: RegressionTest0
Method name: test56
Start line: 1029
End line: 1044
Method source code: 
    public void test56() throws Throwable {
        if (debug)
            System.out.format("%n%s%n", "RegressionTest0.test56");
        java.nio.ByteBuffer byteBuffer0 = null;
        org.jsoup.parser.Parser parser3 = org.jsoup.parser.Parser.xmlParser();
        java.util.List<org.jsoup.parser.ParseError> parseErrorList4 = parser3.getErrors();
        // The following exception was thrown during execution in test generation
        try {
            org.jsoup.nodes.Document document5 = org.jsoup.helper.DataUtil.parseByteData(byteBuffer0, "[:nth-last-child(32n+100)^=*]", ":containsOwn(", parser3);
            org.junit.Assert.fail("Expected exception of type java.nio.charset.IllegalCharsetNameException; message: [:nth-last-child(32n+100)^=*]");
        } catch (java.nio.charset.IllegalCharsetNameException e) {
        // Expected exception.
        }
        org.junit.Assert.assertNotNull(parser3);
        org.junit.Assert.assertNull(parseErrorList4);
    }
Method byte code: 
0: getstatic     #2
3: ifeq          24
6: getstatic     #3
9: ldc           #4
11: iconst_1
12: anewarray     #5
15: dup
16: iconst_0
17: ldc           #179
19: aastore
20: invokevirtual #7
23: pop
24: aconst_null
25: astore_1
26: invokestatic  #41
29: astore_2
30: aload_2
31: invokevirtual #94
34: astore_3
35: aload_1
36: ldc           #39
38: ldc           #69
40: aload_2
41: invokestatic  #27
44: astore        4
46: ldc           #180
48: invokestatic  #11
51: goto          56
54: astore        4
56: aload_2
57: invokestatic  #46
60: aload_3
61: invokestatic  #16
64: return
Exception table:
from    to  target type
35    51    54   Class java/nio/charset/IllegalCharsetNameException
Source File: /data/islam/DBT-workbench/resources/subjects/fixed/jsoup/39/src/test/java/org/jsoup/helper/RegressionTest0.java
Bytecode File: /data/islam/DBT-workbench/resources/subjects/fixed/jsoup/39/target/test-classes/org/jsoup/helper/RegressionTest0.class
Class name: RegressionTest0
Method name: test57
Start line: 1047
End line: 1058
Method source code: 
    public void test57() throws Throwable {
        if (debug)
            System.out.format("%n%s%n", "RegressionTest0.test57");
        java.io.InputStream inputStream0 = null;
        // The following exception was thrown during execution in test generation
        try {
            org.jsoup.nodes.Document document3 = org.jsoup.helper.DataUtil.load(inputStream0, ":containsOwn(:containsown(", "[[:only-of-type*=[:nth-last-child(32n+100)^=*]]^=org.jsoup.select.selector$selectorparseexception: hi!]");
            org.junit.Assert.fail("Expected exception of type java.lang.NullPointerException; message: null");
        } catch (java.lang.NullPointerException e) {
        // Expected exception.
        }
    }
Method byte code: 
0: getstatic     #2
3: ifeq          24
6: getstatic     #3
9: ldc           #4
11: iconst_1
12: anewarray     #5
15: dup
16: iconst_0
17: ldc           #181
19: aastore
20: invokevirtual #7
23: pop
24: aconst_null
25: astore_1
26: aload_1
27: ldc           #168
29: ldc           #182
31: invokestatic  #23
34: astore_2
35: ldc           #10
37: invokestatic  #11
40: goto          44
43: astore_2
44: return
Exception table:
from    to  target type
26    40    43   Class java/lang/NullPointerException
Source File: /data/islam/DBT-workbench/resources/subjects/fixed/jsoup/39/src/test/java/org/jsoup/helper/RegressionTest0.java
Bytecode File: /data/islam/DBT-workbench/resources/subjects/fixed/jsoup/39/target/test-classes/org/jsoup/helper/RegressionTest0.class
Class name: RegressionTest0
Method name: test58
Start line: 1061
End line: 1080
Method source code: 
    public void test58() throws Throwable {
        if (debug)
            System.out.format("%n%s%n", "RegressionTest0.test58");
        java.nio.ByteBuffer byteBuffer0 = null;
        org.jsoup.parser.Parser parser3 = org.jsoup.parser.Parser.xmlParser();
        org.jsoup.parser.Parser parser5 = parser3.setTrackErrors((int) (short) 100);
        java.util.List<org.jsoup.parser.ParseError> parseErrorList6 = parser5.getErrors();
        boolean boolean7 = parser5.isTrackErrors();
        // The following exception was thrown during execution in test generation
        try {
            org.jsoup.nodes.Document document8 = org.jsoup.helper.DataUtil.parseByteData(byteBuffer0, "\n<!---->", "#document", parser5);
            org.junit.Assert.fail("Expected exception of type java.nio.charset.IllegalCharsetNameException; message: ?<!---->");
        } catch (java.nio.charset.IllegalCharsetNameException e) {
        // Expected exception.
        }
        org.junit.Assert.assertNotNull(parser3);
        org.junit.Assert.assertNotNull(parser5);
        org.junit.Assert.assertNull(parseErrorList6);
        org.junit.Assert.assertTrue("'" + boolean7 + "' != '" + true + "'", boolean7 == true);
    }
Method byte code: 
0: getstatic     #2
3: ifeq          24
6: getstatic     #3
9: ldc           #4
11: iconst_1
12: anewarray     #5
15: dup
16: iconst_0
17: ldc           #183
19: aastore
20: invokevirtual #7
23: pop
24: aconst_null
25: astore_1
26: invokestatic  #41
29: astore_2
30: aload_2
31: bipush        100
33: invokevirtual #42
36: astore_3
37: aload_3
38: invokevirtual #94
41: astore        4
43: aload_3
44: invokevirtual #105
47: istore        5
49: aload_1
50: ldc           #184
52: ldc           #26
54: aload_3
55: invokestatic  #27
58: astore        6
60: ldc           #185
62: invokestatic  #11
65: goto          70
68: astore        6
70: aload_2
71: invokestatic  #46
74: aload_3
75: invokestatic  #46
78: aload         4
80: invokestatic  #16
83: new           #108
86: dup
87: invokespecial #109
90: ldc           #110
92: invokevirtual #111
95: iload         5
97: invokevirtual #112
100: ldc           #113
102: invokevirtual #111
105: iconst_1
106: invokevirtual #112
109: ldc           #110
111: invokevirtual #111
114: invokevirtual #114
117: iload         5
119: iconst_1
120: if_icmpne     127
123: iconst_1
124: goto          128
127: iconst_0
128: invokestatic  #115
131: return
Exception table:
from    to  target type
49    65    68   Class java/nio/charset/IllegalCharsetNameException
Source File: /data/islam/DBT-workbench/resources/subjects/fixed/jsoup/39/src/test/java/org/jsoup/helper/RegressionTest0.java
Bytecode File: /data/islam/DBT-workbench/resources/subjects/fixed/jsoup/39/target/test-classes/org/jsoup/helper/RegressionTest0.class
Class name: RegressionTest0
Method name: test59
Start line: 1083
End line: 1199
Method source code: 
    public void test59() throws Throwable {
        if (debug)
            System.out.format("%n%s%n", "RegressionTest0.test59");
        java.io.InputStream inputStream0 = null;
        org.jsoup.nodes.Document document4 = org.jsoup.nodes.Document.createShell("hi!");
        java.util.List<org.jsoup.nodes.TextNode> textNodeList5 = document4.textNodes();
        org.jsoup.nodes.Element element6 = document4.nextElementSibling();
        java.lang.String str7 = document4.title();
        java.util.List<org.jsoup.nodes.Node> nodeList8 = document4.childNodes();
        org.jsoup.nodes.Document document10 = org.jsoup.nodes.Document.createShell("hi!");
        java.util.List<org.jsoup.nodes.TextNode> textNodeList11 = document10.textNodes();
        org.jsoup.nodes.Document document13 = org.jsoup.nodes.Document.createShell("hi!");
        java.util.List<org.jsoup.nodes.TextNode> textNodeList14 = document13.textNodes();
        org.jsoup.nodes.Element element15 = document13.nextElementSibling();
        org.jsoup.nodes.Document document17 = org.jsoup.nodes.Document.createShell("hi!");
        java.util.List<org.jsoup.nodes.TextNode> textNodeList18 = document17.textNodes();
        org.jsoup.nodes.Document document20 = org.jsoup.nodes.Document.createShell("hi!");
        java.util.List<org.jsoup.nodes.TextNode> textNodeList21 = document20.textNodes();
        org.jsoup.nodes.Element element22 = document20.nextElementSibling();
        org.jsoup.nodes.Element[] elementArray23 = new org.jsoup.nodes.Element[] { document10, document13, document17, document20 };
        java.util.ArrayList<org.jsoup.nodes.Element> elementList24 = new java.util.ArrayList<org.jsoup.nodes.Element>();
        boolean boolean25 = java.util.Collections.addAll((java.util.Collection<org.jsoup.nodes.Element>) elementList24, elementArray23);
        org.jsoup.select.Elements elements26 = new org.jsoup.select.Elements((java.util.Collection<org.jsoup.nodes.Element>) elementList24);
        org.jsoup.nodes.Document document29 = org.jsoup.nodes.Document.createShell("hi!");
        org.jsoup.nodes.Element element30 = elements26.set(0, (org.jsoup.nodes.Element) document29);
        java.util.List<org.jsoup.nodes.TextNode> textNodeList31 = element30.textNodes();
        org.jsoup.nodes.Element element32 = document4.appendChild((org.jsoup.nodes.Node) element30);
        java.util.Set<java.lang.String> strSet33 = document4.classNames();
        java.util.LinkedList<java.util.Set<java.lang.String>> strSetList34 = new java.util.LinkedList<java.util.Set<java.lang.String>>();
        boolean boolean35 = strSetList34.add(strSet33);
        org.jsoup.nodes.Document document37 = org.jsoup.nodes.Document.createShell("hi!");
        java.util.List<org.jsoup.nodes.TextNode> textNodeList38 = document37.textNodes();
        org.jsoup.nodes.Document document40 = org.jsoup.nodes.Document.createShell("hi!");
        java.util.List<org.jsoup.nodes.TextNode> textNodeList41 = document40.textNodes();
        org.jsoup.nodes.Element element42 = document40.nextElementSibling();
        org.jsoup.nodes.Document document44 = org.jsoup.nodes.Document.createShell("hi!");
        java.util.List<org.jsoup.nodes.TextNode> textNodeList45 = document44.textNodes();
        org.jsoup.nodes.Document document47 = org.jsoup.nodes.Document.createShell("hi!");
        java.util.List<org.jsoup.nodes.TextNode> textNodeList48 = document47.textNodes();
        org.jsoup.nodes.Element element49 = document47.nextElementSibling();
        org.jsoup.nodes.Element[] elementArray50 = new org.jsoup.nodes.Element[] { document37, document40, document44, document47 };
        java.util.ArrayList<org.jsoup.nodes.Element> elementList51 = new java.util.ArrayList<org.jsoup.nodes.Element>();
        boolean boolean52 = java.util.Collections.addAll((java.util.Collection<org.jsoup.nodes.Element>) elementList51, elementArray50);
        org.jsoup.select.Elements elements53 = new org.jsoup.select.Elements((java.util.Collection<org.jsoup.nodes.Element>) elementList51);
        org.jsoup.nodes.Document document56 = org.jsoup.nodes.Document.createShell("hi!");
        org.jsoup.nodes.Element element57 = elements53.set(0, (org.jsoup.nodes.Element) document56);
        java.lang.String[] strArray60 = new java.lang.String[] { "UTF-8", "UTF-8" };
        java.util.LinkedHashSet<java.lang.String> strSet61 = new java.util.LinkedHashSet<java.lang.String>();
        boolean boolean62 = java.util.Collections.addAll((java.util.Collection<java.lang.String>) strSet61, strArray60);
        org.jsoup.nodes.Element element63 = element57.classNames((java.util.Set<java.lang.String>) strSet61);
        org.jsoup.select.Elements elements65 = element57.getElementsContainingText("UTF-8");
        org.jsoup.select.Elements elements67 = element57.getElementsContainingText(".");
        java.util.Set<java.lang.String> strSet68 = element57.classNames();
        boolean boolean69 = strSetList34.offer(strSet68);
        org.jsoup.select.Evaluator.AttributeWithValueNot attributeWithValueNot72 = new org.jsoup.select.Evaluator.AttributeWithValueNot("[<html>\n <head></head>\n <body></body>\n</html>, <html>\n <head></head>\n <body></body>\n</html>, <html>\n <head></head>\n <body></body>\n</html>]", "<html>\n <head></head>\n <body></body>\n</html>");
        boolean boolean73 = strSetList34.contains((java.lang.Object) "[<html>\n <head></head>\n <body></body>\n</html>, <html>\n <head></head>\n <body></body>\n</html>, <html>\n <head></head>\n <body></body>\n</html>]");
        org.jsoup.parser.Parser parser74 = org.jsoup.parser.Parser.xmlParser();
        org.jsoup.parser.Parser parser76 = parser74.setTrackErrors((int) (short) 100);
        java.util.List<org.jsoup.parser.ParseError> parseErrorList77 = parser76.getErrors();
        boolean boolean78 = strSetList34.remove((java.lang.Object) parser76);
        // The following exception was thrown during execution in test generation
        try {
            org.jsoup.nodes.Document document79 = org.jsoup.helper.DataUtil.load(inputStream0, "<html>\n <head>\n  <title>:contains(:only-child</title>\n </head>\n <body></body>\n</html>", ":matchesOwn(null", parser76);
            org.junit.Assert.fail("Expected exception of type java.lang.NullPointerException; message: null");
        } catch (java.lang.NullPointerException e) {
        // Expected exception.
        }
        org.junit.Assert.assertNotNull(document4);
        org.junit.Assert.assertNotNull(textNodeList5);
        org.junit.Assert.assertNull(element6);
        org.junit.Assert.assertEquals("'" + str7 + "' != '" + "" + "'", str7, "");
        org.junit.Assert.assertNotNull(nodeList8);
        org.junit.Assert.assertNotNull(document10);
        org.junit.Assert.assertNotNull(textNodeList11);
        org.junit.Assert.assertNotNull(document13);
        org.junit.Assert.assertNotNull(textNodeList14);
        org.junit.Assert.assertNull(element15);
        org.junit.Assert.assertNotNull(document17);
        org.junit.Assert.assertNotNull(textNodeList18);
        org.junit.Assert.assertNotNull(document20);
        org.junit.Assert.assertNotNull(textNodeList21);
        org.junit.Assert.assertNull(element22);
        org.junit.Assert.assertNotNull(elementArray23);
        org.junit.Assert.assertTrue("'" + boolean25 + "' != '" + true + "'", boolean25 == true);
        org.junit.Assert.assertNotNull(document29);
        org.junit.Assert.assertNotNull(element30);
        org.junit.Assert.assertNotNull(textNodeList31);
        org.junit.Assert.assertNotNull(element32);
        org.junit.Assert.assertNotNull(strSet33);
        org.junit.Assert.assertTrue("'" + boolean35 + "' != '" + true + "'", boolean35 == true);
        org.junit.Assert.assertNotNull(document37);
        org.junit.Assert.assertNotNull(textNodeList38);
        org.junit.Assert.assertNotNull(document40);
        org.junit.Assert.assertNotNull(textNodeList41);
        org.junit.Assert.assertNull(element42);
        org.junit.Assert.assertNotNull(document44);
        org.junit.Assert.assertNotNull(textNodeList45);
        org.junit.Assert.assertNotNull(document47);
        org.junit.Assert.assertNotNull(textNodeList48);
        org.junit.Assert.assertNull(element49);
        org.junit.Assert.assertNotNull(elementArray50);
        org.junit.Assert.assertTrue("'" + boolean52 + "' != '" + true + "'", boolean52 == true);
        org.junit.Assert.assertNotNull(document56);
        org.junit.Assert.assertNotNull(element57);
        org.junit.Assert.assertNotNull(strArray60);
        org.junit.Assert.assertTrue("'" + boolean62 + "' != '" + true + "'", boolean62 == true);
        org.junit.Assert.assertNotNull(element63);
        org.junit.Assert.assertNotNull(elements65);
        org.junit.Assert.assertNotNull(elements67);
        org.junit.Assert.assertNotNull(strSet68);
        org.junit.Assert.assertTrue("'" + boolean69 + "' != '" + true + "'", boolean69 == true);
        org.junit.Assert.assertTrue("'" + boolean73 + "' != '" + false + "'", boolean73 == false);
        org.junit.Assert.assertNotNull(parser74);
        org.junit.Assert.assertNotNull(parser76);
        org.junit.Assert.assertNull(parseErrorList77);
        org.junit.Assert.assertTrue("'" + boolean78 + "' != '" + false + "'", boolean78 == false);
    }
Method byte code: 
0: getstatic     #2
3: ifeq          24
6: getstatic     #3
9: ldc           #4
11: iconst_1
12: anewarray     #5
15: dup
16: iconst_0
17: ldc           #186
19: aastore
20: invokevirtual #7
23: pop
24: aconst_null
25: astore_1
26: ldc           #14
28: invokestatic  #124
31: astore_2
32: aload_2
33: invokevirtual #125
36: astore_3
37: aload_2
38: invokevirtual #126
41: astore        4
43: aload_2
44: invokevirtual #127
47: astore        5
49: aload_2
50: invokevirtual #128
53: astore        6
55: ldc           #14
57: invokestatic  #124
60: astore        7
62: aload         7
64: invokevirtual #125
67: astore        8
69: ldc           #14
71: invokestatic  #124
74: astore        9
76: aload         9
78: invokevirtual #125
81: astore        10
83: aload         9
85: invokevirtual #126
88: astore        11
90: ldc           #14
92: invokestatic  #124
95: astore        12
97: aload         12
99: invokevirtual #125
102: astore        13
104: ldc           #14
106: invokestatic  #124
109: astore        14
111: aload         14
113: invokevirtual #125
116: astore        15
118: aload         14
120: invokevirtual #126
123: astore        16
125: iconst_4
126: anewarray     #129
129: dup
130: iconst_0
131: aload         7
133: aastore
134: dup
135: iconst_1
136: aload         9
138: aastore
139: dup
140: iconst_2
141: aload         12
143: aastore
144: dup
145: iconst_3
146: aload         14
148: aastore
149: astore        17
151: new           #130
154: dup
155: invokespecial #131
158: astore        18
160: aload         18
162: aload         17
164: invokestatic  #132
167: istore        19
169: new           #133
172: dup
173: aload         18
175: invokespecial #134
178: astore        20
180: ldc           #14
182: invokestatic  #124
185: astore        21
187: aload         20
189: iconst_0
190: aload         21
192: invokevirtual #135
195: astore        22
197: aload         22
199: invokevirtual #136
202: astore        23
204: aload_2
205: aload         22
207: invokevirtual #137
210: astore        24
212: aload_2
213: invokevirtual #138
216: astore        25
218: new           #139
221: dup
222: invokespecial #140
225: astore        26
227: aload         26
229: aload         25
231: invokevirtual #141
234: istore        27
236: ldc           #14
238: invokestatic  #124
241: astore        28
243: aload         28
245: invokevirtual #125
248: astore        29
250: ldc           #14
252: invokestatic  #124
255: astore        30
257: aload         30
259: invokevirtual #125
262: astore        31
264: aload         30
266: invokevirtual #126
269: astore        32
271: ldc           #14
273: invokestatic  #124
276: astore        33
278: aload         33
280: invokevirtual #125
283: astore        34
285: ldc           #14
287: invokestatic  #124
290: astore        35
292: aload         35
294: invokevirtual #125
297: astore        36
299: aload         35
301: invokevirtual #126
304: astore        37
306: iconst_4
307: anewarray     #129
310: dup
311: iconst_0
312: aload         28
314: aastore
315: dup
316: iconst_1
317: aload         30
319: aastore
320: dup
321: iconst_2
322: aload         33
324: aastore
325: dup
326: iconst_3
327: aload         35
329: aastore
330: astore        38
332: new           #130
335: dup
336: invokespecial #131
339: astore        39
341: aload         39
343: aload         38
345: invokestatic  #132
348: istore        40
350: new           #133
353: dup
354: aload         39
356: invokespecial #134
359: astore        41
361: ldc           #14
363: invokestatic  #124
366: astore        42
368: aload         41
370: iconst_0
371: aload         42
373: invokevirtual #135
376: astore        43
378: iconst_2
379: anewarray     #142
382: dup
383: iconst_0
384: ldc           #34
386: aastore
387: dup
388: iconst_1
389: ldc           #34
391: aastore
392: astore        44
394: new           #143
397: dup
398: invokespecial #144
401: astore        45
403: aload         45
405: aload         44
407: invokestatic  #132
410: istore        46
412: aload         43
414: aload         45
416: invokevirtual #145
419: astore        47
421: aload         43
423: ldc           #34
425: invokevirtual #146
428: astore        48
430: aload         43
432: ldc           #22
434: invokevirtual #146
437: astore        49
439: aload         43
441: invokevirtual #147
444: astore        50
446: aload         26
448: aload         50
450: invokevirtual #148
453: istore        51
455: new           #149
458: dup
459: ldc           #25
461: ldc           #50
463: invokespecial #150
466: astore        52
468: aload         26
470: ldc           #25
472: invokevirtual #151
475: istore        53
477: invokestatic  #41
480: astore        54
482: aload         54
484: bipush        100
486: invokevirtual #42
489: astore        55
491: aload         55
493: invokevirtual #94
496: astore        56
498: aload         26
500: aload         55
502: invokevirtual #152
505: istore        57
507: aload_1
508: ldc           #91
510: ldc           #177
512: aload         55
514: invokestatic  #9
517: astore        58
519: ldc           #10
521: invokestatic  #11
524: goto          529
527: astore        58
529: aload_2
530: invokestatic  #46
533: aload_3
534: invokestatic  #46
537: aload         4
539: invokestatic  #16
542: new           #108
545: dup
546: invokespecial #109
549: ldc           #110
551: invokevirtual #111
554: aload         5
556: invokevirtual #111
559: ldc           #155
561: invokevirtual #111
564: invokevirtual #114
567: aload         5
569: ldc           #8
571: invokestatic  #156
574: aload         6
576: invokestatic  #46
579: aload         7
581: invokestatic  #46
584: aload         8
586: invokestatic  #46
589: aload         9
591: invokestatic  #46
594: aload         10
596: invokestatic  #46
599: aload         11
601: invokestatic  #16
604: aload         12
606: invokestatic  #46
609: aload         13
611: invokestatic  #46
614: aload         14
616: invokestatic  #46
619: aload         15
621: invokestatic  #46
624: aload         16
626: invokestatic  #16
629: aload         17
631: invokestatic  #46
634: new           #108
637: dup
638: invokespecial #109
641: ldc           #110
643: invokevirtual #111
646: iload         19
648: invokevirtual #112
651: ldc           #113
653: invokevirtual #111
656: iconst_1
657: invokevirtual #112
660: ldc           #110
662: invokevirtual #111
665: invokevirtual #114
668: iload         19
670: iconst_1
671: if_icmpne     678
674: iconst_1
675: goto          679
678: iconst_0
679: invokestatic  #115
682: aload         21
684: invokestatic  #46
687: aload         22
689: invokestatic  #46
692: aload         23
694: invokestatic  #46
697: aload         24
699: invokestatic  #46
702: aload         25
704: invokestatic  #46
707: new           #108
710: dup
711: invokespecial #109
714: ldc           #110
716: invokevirtual #111
719: iload         27
721: invokevirtual #112
724: ldc           #113
726: invokevirtual #111
729: iconst_1
730: invokevirtual #112
733: ldc           #110
735: invokevirtual #111
738: invokevirtual #114
741: iload         27
743: iconst_1
744: if_icmpne     751
747: iconst_1
748: goto          752
751: iconst_0
752: invokestatic  #115
755: aload         28
757: invokestatic  #46
760: aload         29
762: invokestatic  #46
765: aload         30
767: invokestatic  #46
770: aload         31
772: invokestatic  #46
775: aload         32
777: invokestatic  #16
780: aload         33
782: invokestatic  #46
785: aload         34
787: invokestatic  #46
790: aload         35
792: invokestatic  #46
795: aload         36
797: invokestatic  #46
800: aload         37
802: invokestatic  #16
805: aload         38
807: invokestatic  #46
810: new           #108
813: dup
814: invokespecial #109
817: ldc           #110
819: invokevirtual #111
822: iload         40
824: invokevirtual #112
827: ldc           #113
829: invokevirtual #111
832: iconst_1
833: invokevirtual #112
836: ldc           #110
838: invokevirtual #111
841: invokevirtual #114
844: iload         40
846: iconst_1
847: if_icmpne     854
850: iconst_1
851: goto          855
854: iconst_0
855: invokestatic  #115
858: aload         42
860: invokestatic  #46
863: aload         43
865: invokestatic  #46
868: aload         44
870: invokestatic  #46
873: new           #108
876: dup
877: invokespecial #109
880: ldc           #110
882: invokevirtual #111
885: iload         46
887: invokevirtual #112
890: ldc           #113
892: invokevirtual #111
895: iconst_1
896: invokevirtual #112
899: ldc           #110
901: invokevirtual #111
904: invokevirtual #114
907: iload         46
909: iconst_1
910: if_icmpne     917
913: iconst_1
914: goto          918
917: iconst_0
918: invokestatic  #115
921: aload         47
923: invokestatic  #46
926: aload         48
928: invokestatic  #46
931: aload         49
933: invokestatic  #46
936: aload         50
938: invokestatic  #46
941: new           #108
944: dup
945: invokespecial #109
948: ldc           #110
950: invokevirtual #111
953: iload         51
955: invokevirtual #112
958: ldc           #113
960: invokevirtual #111
963: iconst_1
964: invokevirtual #112
967: ldc           #110
969: invokevirtual #111
972: invokevirtual #114
975: iload         51
977: iconst_1
978: if_icmpne     985
981: iconst_1
982: goto          986
985: iconst_0
986: invokestatic  #115
989: new           #108
992: dup
993: invokespecial #109
996: ldc           #110
998: invokevirtual #111
1001: iload         53
1003: invokevirtual #112
1006: ldc           #113
1008: invokevirtual #111
1011: iconst_0
1012: invokevirtual #112
1015: ldc           #110
1017: invokevirtual #111
1020: invokevirtual #114
1023: iload         53
1025: ifne          1032
1028: iconst_1
1029: goto          1033
1032: iconst_0
1033: invokestatic  #115
1036: aload         54
1038: invokestatic  #46
1041: aload         55
1043: invokestatic  #46
1046: aload         56
1048: invokestatic  #16
1051: new           #108
1054: dup
1055: invokespecial #109
1058: ldc           #110
1060: invokevirtual #111
1063: iload         57
1065: invokevirtual #112
1068: ldc           #113
1070: invokevirtual #111
1073: iconst_0
1074: invokevirtual #112
1077: ldc           #110
1079: invokevirtual #111
1082: invokevirtual #114
1085: iload         57
1087: ifne          1094
1090: iconst_1
1091: goto          1095
1094: iconst_0
1095: invokestatic  #115
1098: return
Exception table:
from    to  target type
507   524   527   Class java/lang/NullPointerException
Source File: /data/islam/DBT-workbench/resources/subjects/fixed/jsoup/39/src/test/java/org/jsoup/helper/RegressionTest0.java
Bytecode File: /data/islam/DBT-workbench/resources/subjects/fixed/jsoup/39/target/test-classes/org/jsoup/helper/RegressionTest0.class
Class name: RegressionTest0
Method name: test60
Start line: 1202
End line: 1213
Method source code: 
    public void test60() throws Throwable {
        if (debug)
            System.out.format("%n%s%n", "RegressionTest0.test60");
        java.io.InputStream inputStream0 = null;
        // The following exception was thrown during execution in test generation
        try {
            java.nio.ByteBuffer byteBuffer2 = org.jsoup.helper.DataUtil.readToByteBuffer(inputStream0, 4);
            org.junit.Assert.fail("Expected exception of type java.lang.NullPointerException; message: null");
        } catch (java.lang.NullPointerException e) {
        // Expected exception.
        }
    }
Method byte code: 
0: getstatic     #2
3: ifeq          24
6: getstatic     #3
9: ldc           #4
11: iconst_1
12: anewarray     #5
15: dup
16: iconst_0
17: ldc           #187
19: aastore
20: invokevirtual #7
23: pop
24: aconst_null
25: astore_1
26: aload_1
27: iconst_4
28: invokestatic  #20
31: astore_2
32: ldc           #10
34: invokestatic  #11
37: goto          41
40: astore_2
41: return
Exception table:
from    to  target type
26    37    40   Class java/lang/NullPointerException
Source File: /data/islam/DBT-workbench/resources/subjects/fixed/jsoup/39/src/test/java/org/jsoup/helper/RegressionTest0.java
Bytecode File: /data/islam/DBT-workbench/resources/subjects/fixed/jsoup/39/target/test-classes/org/jsoup/helper/RegressionTest0.class
Class name: RegressionTest0
Method name: test61
Start line: 1216
End line: 1228
Method source code: 
    public void test61() throws Throwable {
        if (debug)
            System.out.format("%n%s%n", "RegressionTest0.test61");
        java.nio.ByteBuffer byteBuffer0 = null;
        org.jsoup.parser.Parser parser3 = null;
        // The following exception was thrown during execution in test generation
        try {
            org.jsoup.nodes.Document document4 = org.jsoup.helper.DataUtil.parseByteData(byteBuffer0, ":matches(null", "#doctype", parser3);
            org.junit.Assert.fail("Expected exception of type java.nio.charset.IllegalCharsetNameException; message: :matches(null");
        } catch (java.nio.charset.IllegalCharsetNameException e) {
        // Expected exception.
        }
    }
Method byte code: 
0: getstatic     #2
3: ifeq          24
6: getstatic     #3
9: ldc           #4
11: iconst_1
12: anewarray     #5
15: dup
16: iconst_0
17: ldc           #188
19: aastore
20: invokevirtual #7
23: pop
24: aconst_null
25: astore_1
26: aconst_null
27: astore_2
28: aload_1
29: ldc           #55
31: ldc           #82
33: aload_2
34: invokestatic  #27
37: astore_3
38: ldc           #189
40: invokestatic  #11
43: goto          47
46: astore_3
47: return
Exception table:
from    to  target type
28    43    46   Class java/nio/charset/IllegalCharsetNameException
Source File: /data/islam/DBT-workbench/resources/subjects/fixed/jsoup/39/src/test/java/org/jsoup/helper/RegressionTest0.java
Bytecode File: /data/islam/DBT-workbench/resources/subjects/fixed/jsoup/39/target/test-classes/org/jsoup/helper/RegressionTest0.class
Class name: RegressionTest0
Method name: test62
Start line: 1231
End line: 1244
Method source code: 
    public void test62() throws Throwable {
        if (debug)
            System.out.format("%n%s%n", "RegressionTest0.test62");
        java.io.InputStream inputStream0 = null;
        org.jsoup.parser.Parser parser3 = org.jsoup.parser.Parser.htmlParser();
        // The following exception was thrown during execution in test generation
        try {
            org.jsoup.nodes.Document document4 = org.jsoup.helper.DataUtil.load(inputStream0, "hi!", "<html>\n <head></head>\n <body></body>\n</html>\n<html>\n <head></head>\n <body></body>\n</html>\n\n", parser3);
            org.junit.Assert.fail("Expected exception of type java.lang.NullPointerException; message: null");
        } catch (java.lang.NullPointerException e) {
        // Expected exception.
        }
        org.junit.Assert.assertNotNull(parser3);
    }
Method byte code: 
0: getstatic     #2
3: ifeq          24
6: getstatic     #3
9: ldc           #4
11: iconst_1
12: anewarray     #5
15: dup
16: iconst_0
17: ldc           #190
19: aastore
20: invokevirtual #7
23: pop
24: aconst_null
25: astore_1
26: invokestatic  #191
29: astore_2
30: aload_1
31: ldc           #14
33: ldc           #192
35: aload_2
36: invokestatic  #9
39: astore_3
40: ldc           #10
42: invokestatic  #11
45: goto          49
48: astore_3
49: aload_2
50: invokestatic  #46
53: return
Exception table:
from    to  target type
30    45    48   Class java/lang/NullPointerException
Source File: /data/islam/DBT-workbench/resources/subjects/fixed/jsoup/39/src/test/java/org/jsoup/helper/RegressionTest0.java
Bytecode File: /data/islam/DBT-workbench/resources/subjects/fixed/jsoup/39/target/test-classes/org/jsoup/helper/RegressionTest0.class
Class name: RegressionTest0
Method name: test63
Start line: 1247
End line: 1252
Method source code: 
    public void test63() throws Throwable {
        if (debug)
            System.out.format("%n%s%n", "RegressionTest0.test63");
        java.lang.String str1 = org.jsoup.helper.DataUtil.getCharsetFromContentType("[:nth-last-child(32n+100)*=#document]");
        org.junit.Assert.assertNull(str1);
    }
Method byte code: 
0: getstatic     #2
3: ifeq          24
6: getstatic     #3
9: ldc           #4
11: iconst_1
12: anewarray     #5
15: dup
16: iconst_0
17: ldc           #193
19: aastore
20: invokevirtual #7
23: pop
24: ldc           #194
26: invokestatic  #15
29: astore_1
30: aload_1
31: invokestatic  #16
34: return
Source File: /data/islam/DBT-workbench/resources/subjects/fixed/jsoup/39/src/test/java/org/jsoup/helper/RegressionTest0.java
Bytecode File: /data/islam/DBT-workbench/resources/subjects/fixed/jsoup/39/target/test-classes/org/jsoup/helper/RegressionTest0.class
Class name: RegressionTest0
Method name: test64
Start line: 1255
End line: 1266
Method source code: 
    public void test64() throws Throwable {
        if (debug)
            System.out.format("%n%s%n", "RegressionTest0.test64");
        java.io.File file0 = null;
        // The following exception was thrown during execution in test generation
        try {
            org.jsoup.nodes.Document document3 = org.jsoup.helper.DataUtil.load(file0, ":lt(100)", ":nth-last-of-type(-1n+1)");
            org.junit.Assert.fail("Expected exception of type java.lang.NullPointerException; message: null");
        } catch (java.lang.NullPointerException e) {
        // Expected exception.
        }
    }
Method byte code: 
0: getstatic     #2
3: ifeq          24
6: getstatic     #3
9: ldc           #4
11: iconst_1
12: anewarray     #5
15: dup
16: iconst_0
17: ldc           #195
19: aastore
20: invokevirtual #7
23: pop
24: aconst_null
25: astore_1
26: aload_1
27: ldc           #196
29: ldc           #170
31: invokestatic  #35
34: astore_2
35: ldc           #10
37: invokestatic  #11
40: goto          44
43: astore_2
44: return
Exception table:
from    to  target type
26    40    43   Class java/lang/NullPointerException
Source File: /data/islam/DBT-workbench/resources/subjects/fixed/jsoup/39/src/test/java/org/jsoup/helper/RegressionTest0.java
Bytecode File: /data/islam/DBT-workbench/resources/subjects/fixed/jsoup/39/target/test-classes/org/jsoup/helper/RegressionTest0.class
Class name: RegressionTest0
Method name: test65
Start line: 1269
End line: 1290
Method source code: 
    public void test65() throws Throwable {
        if (debug)
            System.out.format("%n%s%n", "RegressionTest0.test65");
        java.io.InputStream inputStream0 = null;
        org.jsoup.parser.Parser parser3 = org.jsoup.parser.Parser.xmlParser();
        org.jsoup.parser.Parser parser5 = parser3.setTrackErrors((int) (short) 100);
        org.jsoup.nodes.Document document8 = parser3.parseInput("UTF-8", "<html> <head></head> <body></body> </html> <html> <head></head> <body></body> </html> <html> <head></head> <body></body> </html> <html> <head></head> <body></body> </html>");
        org.jsoup.nodes.Document document11 = parser3.parseInput(":empty", ":matches(null");
        boolean boolean12 = parser3.isTrackErrors();
        // The following exception was thrown during execution in test generation
        try {
            org.jsoup.nodes.Document document13 = org.jsoup.helper.DataUtil.load(inputStream0, ":nth-last-child(32n+100)", "", parser3);
            org.junit.Assert.fail("Expected exception of type java.lang.NullPointerException; message: null");
        } catch (java.lang.NullPointerException e) {
        // Expected exception.
        }
        org.junit.Assert.assertNotNull(parser3);
        org.junit.Assert.assertNotNull(parser5);
        org.junit.Assert.assertNotNull(document8);
        org.junit.Assert.assertNotNull(document11);
        org.junit.Assert.assertTrue("'" + boolean12 + "' != '" + true + "'", boolean12 == true);
    }
Method byte code: 
0: getstatic     #2
3: ifeq          24
6: getstatic     #3
9: ldc           #4
11: iconst_1
12: anewarray     #5
15: dup
16: iconst_0
17: ldc           #197
19: aastore
20: invokevirtual #7
23: pop
24: aconst_null
25: astore_1
26: invokestatic  #41
29: astore_2
30: aload_2
31: bipush        100
33: invokevirtual #42
36: astore_3
37: aload_2
38: ldc           #34
40: ldc           #64
42: invokevirtual #58
45: astore        4
47: aload_2
48: ldc           #65
50: ldc           #55
52: invokevirtual #58
55: astore        5
57: aload_2
58: invokevirtual #105
61: istore        6
63: aload_1
64: ldc           #198
66: ldc           #8
68: aload_2
69: invokestatic  #9
72: astore        7
74: ldc           #10
76: invokestatic  #11
79: goto          84
82: astore        7
84: aload_2
85: invokestatic  #46
88: aload_3
89: invokestatic  #46
92: aload         4
94: invokestatic  #46
97: aload         5
99: invokestatic  #46
102: new           #108
105: dup
106: invokespecial #109
109: ldc           #110
111: invokevirtual #111
114: iload         6
116: invokevirtual #112
119: ldc           #113
121: invokevirtual #111
124: iconst_1
125: invokevirtual #112
128: ldc           #110
130: invokevirtual #111
133: invokevirtual #114
136: iload         6
138: iconst_1
139: if_icmpne     146
142: iconst_1
143: goto          147
146: iconst_0
147: invokestatic  #115
150: return
Exception table:
from    to  target type
63    79    82   Class java/lang/NullPointerException
Source File: /data/islam/DBT-workbench/resources/subjects/fixed/jsoup/39/src/test/java/org/jsoup/helper/RegressionTest0.java
Bytecode File: /data/islam/DBT-workbench/resources/subjects/fixed/jsoup/39/target/test-classes/org/jsoup/helper/RegressionTest0.class
Class name: RegressionTest0
Method name: test66
Start line: 1293
End line: 1298
Method source code: 
    public void test66() throws Throwable {
        if (debug)
            System.out.format("%n%s%n", "RegressionTest0.test66");
        java.lang.String str1 = org.jsoup.helper.DataUtil.getCharsetFromContentType("<html>\n <head></head>\n <body></body>\n</html>\n<html>\n <head></head>\n <body></body>\n</html>\n\n");
        org.junit.Assert.assertNull(str1);
    }
Method byte code: 
0: getstatic     #2
3: ifeq          24
6: getstatic     #3
9: ldc           #4
11: iconst_1
12: anewarray     #5
15: dup
16: iconst_0
17: ldc           #199
19: aastore
20: invokevirtual #7
23: pop
24: ldc           #192
26: invokestatic  #15
29: astore_1
30: aload_1
31: invokestatic  #16
34: return
Source File: /data/islam/DBT-workbench/resources/subjects/fixed/jsoup/39/src/test/java/org/jsoup/helper/RegressionTest0.java
Bytecode File: /data/islam/DBT-workbench/resources/subjects/fixed/jsoup/39/target/test-classes/org/jsoup/helper/RegressionTest0.class
Class name: RegressionTest0
Method name: test67
Start line: 1301
End line: 1306
Method source code: 
    public void test67() throws Throwable {
        if (debug)
            System.out.format("%n%s%n", "RegressionTest0.test67");
        java.lang.String str1 = org.jsoup.helper.DataUtil.getCharsetFromContentType(":eq(35)");
        org.junit.Assert.assertNull(str1);
    }
Method byte code: 
0: getstatic     #2
3: ifeq          24
6: getstatic     #3
9: ldc           #4
11: iconst_1
12: anewarray     #5
15: dup
16: iconst_0
17: ldc           #200
19: aastore
20: invokevirtual #7
23: pop
24: ldc           #201
26: invokestatic  #15
29: astore_1
30: aload_1
31: invokestatic  #16
34: return
Source File: /data/islam/DBT-workbench/resources/subjects/fixed/jsoup/39/src/test/java/org/jsoup/helper/RegressionTest0.java
Bytecode File: /data/islam/DBT-workbench/resources/subjects/fixed/jsoup/39/target/test-classes/org/jsoup/helper/RegressionTest0.class
Class name: RegressionTest0
Method name: test68
Start line: 1309
End line: 1326
Method source code: 
    public void test68() throws Throwable {
        if (debug)
            System.out.format("%n%s%n", "RegressionTest0.test68");
        java.io.InputStream inputStream0 = null;
        org.jsoup.parser.Parser parser3 = org.jsoup.parser.Parser.xmlParser();
        org.jsoup.parser.Parser parser5 = parser3.setTrackErrors((int) (short) 100);
        java.util.List<org.jsoup.parser.ParseError> parseErrorList6 = parser5.getErrors();
        // The following exception was thrown during execution in test generation
        try {
            org.jsoup.nodes.Document document7 = org.jsoup.helper.DataUtil.load(inputStream0, "##.", "", parser5);
            org.junit.Assert.fail("Expected exception of type java.lang.NullPointerException; message: null");
        } catch (java.lang.NullPointerException e) {
        // Expected exception.
        }
        org.junit.Assert.assertNotNull(parser3);
        org.junit.Assert.assertNotNull(parser5);
        org.junit.Assert.assertNull(parseErrorList6);
    }
Method byte code: 
0: getstatic     #2
3: ifeq          24
6: getstatic     #3
9: ldc           #4
11: iconst_1
12: anewarray     #5
15: dup
16: iconst_0
17: ldc           #202
19: aastore
20: invokevirtual #7
23: pop
24: aconst_null
25: astore_1
26: invokestatic  #41
29: astore_2
30: aload_2
31: bipush        100
33: invokevirtual #42
36: astore_3
37: aload_3
38: invokevirtual #94
41: astore        4
43: aload_1
44: ldc           #203
46: ldc           #8
48: aload_3
49: invokestatic  #9
52: astore        5
54: ldc           #10
56: invokestatic  #11
59: goto          64
62: astore        5
64: aload_2
65: invokestatic  #46
68: aload_3
69: invokestatic  #46
72: aload         4
74: invokestatic  #16
77: return
Exception table:
from    to  target type
43    59    62   Class java/lang/NullPointerException
Source File: /data/islam/DBT-workbench/resources/subjects/fixed/jsoup/39/src/test/java/org/jsoup/helper/RegressionTest0.java
Bytecode File: /data/islam/DBT-workbench/resources/subjects/fixed/jsoup/39/target/test-classes/org/jsoup/helper/RegressionTest0.class
Class name: RegressionTest0
Method name: test69
Start line: 1329
End line: 1334
Method source code: 
    public void test69() throws Throwable {
        if (debug)
            System.out.format("%n%s%n", "RegressionTest0.test69");
        java.lang.String str1 = org.jsoup.helper.DataUtil.getCharsetFromContentType("[#root*=:matches(null]");
        org.junit.Assert.assertNull(str1);
    }
Method byte code: 
0: getstatic     #2
3: ifeq          24
6: getstatic     #3
9: ldc           #4
11: iconst_1
12: anewarray     #5
15: dup
16: iconst_0
17: ldc           #204
19: aastore
20: invokevirtual #7
23: pop
24: ldc           #162
26: invokestatic  #15
29: astore_1
30: aload_1
31: invokestatic  #16
34: return
Source File: /data/islam/DBT-workbench/resources/subjects/fixed/jsoup/39/src/test/java/org/jsoup/helper/RegressionTest0.java
Bytecode File: /data/islam/DBT-workbench/resources/subjects/fixed/jsoup/39/target/test-classes/org/jsoup/helper/RegressionTest0.class
Class name: RegressionTest0
Method name: test70
Start line: 1337
End line: 1348
Method source code: 
    public void test70() throws Throwable {
        if (debug)
            System.out.format("%n%s%n", "RegressionTest0.test70");
        java.io.InputStream inputStream0 = null;
        // The following exception was thrown during execution in test generation
        try {
            org.jsoup.nodes.Document document3 = org.jsoup.helper.DataUtil.load(inputStream0, "#.", "<html>\n <head></head>\n <body></body>\n</html>\n<html>\n <head></head>\n <body></body>\n</html>\n\n");
            org.junit.Assert.fail("Expected exception of type java.lang.NullPointerException; message: null");
        } catch (java.lang.NullPointerException e) {
        // Expected exception.
        }
    }
Method byte code: 
0: getstatic     #2
3: ifeq          24
6: getstatic     #3
9: ldc           #4
11: iconst_1
12: anewarray     #5
15: dup
16: iconst_0
17: ldc           #205
19: aastore
20: invokevirtual #7
23: pop
24: aconst_null
25: astore_1
26: aload_1
27: ldc           #57
29: ldc           #192
31: invokestatic  #23
34: astore_2
35: ldc           #10
37: invokestatic  #11
40: goto          44
43: astore_2
44: return
Exception table:
from    to  target type
26    40    43   Class java/lang/NullPointerException
Source File: /data/islam/DBT-workbench/resources/subjects/fixed/jsoup/39/src/test/java/org/jsoup/helper/RegressionTest0.java
Bytecode File: /data/islam/DBT-workbench/resources/subjects/fixed/jsoup/39/target/test-classes/org/jsoup/helper/RegressionTest0.class
Class name: RegressionTest0
Method name: test71
Start line: 1351
End line: 1370
Method source code: 
    public void test71() throws Throwable {
        if (debug)
            System.out.format("%n%s%n", "RegressionTest0.test71");
        java.io.InputStream inputStream0 = null;
        org.jsoup.parser.Parser parser3 = org.jsoup.parser.Parser.xmlParser();
        org.jsoup.parser.Parser parser5 = parser3.setTrackErrors((int) (short) 100);
        org.jsoup.nodes.Document document8 = parser3.parseInput("UTF-8", "<html> <head></head> <body></body> </html> <html> <head></head> <body></body> </html> <html> <head></head> <body></body> </html> <html> <head></head> <body></body> </html>");
        boolean boolean9 = parser3.isTrackErrors();
        // The following exception was thrown during execution in test generation
        try {
            org.jsoup.nodes.Document document10 = org.jsoup.helper.DataUtil.load(inputStream0, "\n<!--*-->", "<head></head> <body></body>", parser3);
            org.junit.Assert.fail("Expected exception of type java.lang.NullPointerException; message: null");
        } catch (java.lang.NullPointerException e) {
        // Expected exception.
        }
        org.junit.Assert.assertNotNull(parser3);
        org.junit.Assert.assertNotNull(parser5);
        org.junit.Assert.assertNotNull(document8);
        org.junit.Assert.assertTrue("'" + boolean9 + "' != '" + true + "'", boolean9 == true);
    }
Method byte code: 
0: getstatic     #2
3: ifeq          24
6: getstatic     #3
9: ldc           #4
11: iconst_1
12: anewarray     #5
15: dup
16: iconst_0
17: ldc           #206
19: aastore
20: invokevirtual #7
23: pop
24: aconst_null
25: astore_1
26: invokestatic  #41
29: astore_2
30: aload_2
31: bipush        100
33: invokevirtual #42
36: astore_3
37: aload_2
38: ldc           #34
40: ldc           #64
42: invokevirtual #58
45: astore        4
47: aload_2
48: invokevirtual #105
51: istore        5
53: aload_1
54: ldc           #207
56: ldc           #208
58: aload_2
59: invokestatic  #9
62: astore        6
64: ldc           #10
66: invokestatic  #11
69: goto          74
72: astore        6
74: aload_2
75: invokestatic  #46
78: aload_3
79: invokestatic  #46
82: aload         4
84: invokestatic  #46
87: new           #108
90: dup
91: invokespecial #109
94: ldc           #110
96: invokevirtual #111
99: iload         5
101: invokevirtual #112
104: ldc           #113
106: invokevirtual #111
109: iconst_1
110: invokevirtual #112
113: ldc           #110
115: invokevirtual #111
118: invokevirtual #114
121: iload         5
123: iconst_1
124: if_icmpne     131
127: iconst_1
128: goto          132
131: iconst_0
132: invokestatic  #115
135: return
Exception table:
from    to  target type
53    69    72   Class java/lang/NullPointerException
Source File: /data/islam/DBT-workbench/resources/subjects/fixed/jsoup/39/src/test/java/org/jsoup/helper/RegressionTest0.java
Bytecode File: /data/islam/DBT-workbench/resources/subjects/fixed/jsoup/39/target/test-classes/org/jsoup/helper/RegressionTest0.class
Class name: RegressionTest0
Method name: test72
Start line: 1373
End line: 1384
Method source code: 
    public void test72() throws Throwable {
        if (debug)
            System.out.format("%n%s%n", "RegressionTest0.test72");
        java.io.InputStream inputStream0 = null;
        // The following exception was thrown during execution in test generation
        try {
            org.jsoup.nodes.Document document3 = org.jsoup.helper.DataUtil.load(inputStream0, "<html></html>", ":eq(35)");
            org.junit.Assert.fail("Expected exception of type java.lang.NullPointerException; message: null");
        } catch (java.lang.NullPointerException e) {
        // Expected exception.
        }
    }
Method byte code: 
0: getstatic     #2
3: ifeq          24
6: getstatic     #3
9: ldc           #4
11: iconst_1
12: anewarray     #5
15: dup
16: iconst_0
17: ldc           #209
19: aastore
20: invokevirtual #7
23: pop
24: aconst_null
25: astore_1
26: aload_1
27: ldc           #159
29: ldc           #201
31: invokestatic  #23
34: astore_2
35: ldc           #10
37: invokestatic  #11
40: goto          44
43: astore_2
44: return
Exception table:
from    to  target type
26    40    43   Class java/lang/NullPointerException
Source File: /data/islam/DBT-workbench/resources/subjects/fixed/jsoup/39/src/test/java/org/jsoup/helper/RegressionTest0.java
Bytecode File: /data/islam/DBT-workbench/resources/subjects/fixed/jsoup/39/target/test-classes/org/jsoup/helper/RegressionTest0.class
Class name: RegressionTest0
Method name: test73
Start line: 1387
End line: 1398
Method source code: 
    public void test73() throws Throwable {
        if (debug)
            System.out.format("%n%s%n", "RegressionTest0.test73");
        java.io.File file0 = null;
        // The following exception was thrown during execution in test generation
        try {
            org.jsoup.nodes.Document document3 = org.jsoup.helper.DataUtil.load(file0, "[<html>\n <head></head>\n <body></body>\n</html>, <html>\n <head></head>\n <body></body>\n</html>, <html>\n <head></head>\n <body></body>\n</html>]", "<html class=\" \n<!---->\">\n <head class=\" \n<!---->\"></head>\n <body class=\" \n<!---->\"></body>\n</html>:nth-last-of-type(32n+10)<html class=\" \n<!---->\">\n <head class=\" \n<!---->\"></head>\n <body class=\" \n<!---->\"></body>\n</html>:nth-last-of-type(32n+10)<head class=\" \n<!---->\"></head>:nth-last-of-type(32n+10)<body class=\" \n<!---->\"></body>");
            org.junit.Assert.fail("Expected exception of type java.lang.NullPointerException; message: null");
        } catch (java.lang.NullPointerException e) {
        // Expected exception.
        }
    }
Method byte code: 
0: getstatic     #2
3: ifeq          24
6: getstatic     #3
9: ldc           #4
11: iconst_1
12: anewarray     #5
15: dup
16: iconst_0
17: ldc           #210
19: aastore
20: invokevirtual #7
23: pop
24: aconst_null
25: astore_1
26: aload_1
27: ldc           #25
29: ldc           #211
31: invokestatic  #35
34: astore_2
35: ldc           #10
37: invokestatic  #11
40: goto          44
43: astore_2
44: return
Exception table:
from    to  target type
26    40    43   Class java/lang/NullPointerException
Source File: /data/islam/DBT-workbench/resources/subjects/fixed/jsoup/39/src/test/java/org/jsoup/helper/RegressionTest0.java
Bytecode File: /data/islam/DBT-workbench/resources/subjects/fixed/jsoup/39/target/test-classes/org/jsoup/helper/RegressionTest0.class
Class name: RegressionTest0
Method name: test74
Start line: 1401
End line: 1406
Method source code: 
    public void test74() throws Throwable {
        if (debug)
            System.out.format("%n%s%n", "RegressionTest0.test74");
        java.lang.String str1 = org.jsoup.helper.DataUtil.getCharsetFromContentType(":lt(100)");
        org.junit.Assert.assertNull(str1);
    }
Method byte code: 
0: getstatic     #2
3: ifeq          24
6: getstatic     #3
9: ldc           #4
11: iconst_1
12: anewarray     #5
15: dup
16: iconst_0
17: ldc           #212
19: aastore
20: invokevirtual #7
23: pop
24: ldc           #196
26: invokestatic  #15
29: astore_1
30: aload_1
31: invokestatic  #16
34: return
Source File: /data/islam/DBT-workbench/resources/subjects/fixed/jsoup/39/src/test/java/org/jsoup/helper/RegressionTest0.java
Bytecode File: /data/islam/DBT-workbench/resources/subjects/fixed/jsoup/39/target/test-classes/org/jsoup/helper/RegressionTest0.class
Class name: RegressionTest0
Method name: test75
Start line: 1409
End line: 1420
Method source code: 
    public void test75() throws Throwable {
        if (debug)
            System.out.format("%n%s%n", "RegressionTest0.test75");
        java.io.InputStream inputStream0 = null;
        // The following exception was thrown during execution in test generation
        try {
            java.nio.ByteBuffer byteBuffer2 = org.jsoup.helper.DataUtil.readToByteBuffer(inputStream0, (int) (byte) 100);
            org.junit.Assert.fail("Expected exception of type java.lang.NullPointerException; message: null");
        } catch (java.lang.NullPointerException e) {
        // Expected exception.
        }
    }
Method byte code: 
0: getstatic     #2
3: ifeq          24
6: getstatic     #3
9: ldc           #4
11: iconst_1
12: anewarray     #5
15: dup
16: iconst_0
17: ldc           #213
19: aastore
20: invokevirtual #7
23: pop
24: aconst_null
25: astore_1
26: aload_1
27: bipush        100
29: invokestatic  #20
32: astore_2
33: ldc           #10
35: invokestatic  #11
38: goto          42
41: astore_2
42: return
Exception table:
from    to  target type
26    38    41   Class java/lang/NullPointerException
Source File: /data/islam/DBT-workbench/resources/subjects/fixed/jsoup/39/src/test/java/org/jsoup/helper/RegressionTest0.java
Bytecode File: /data/islam/DBT-workbench/resources/subjects/fixed/jsoup/39/target/test-classes/org/jsoup/helper/RegressionTest0.class
Class name: RegressionTest0
Method name: test76
Start line: 1423
End line: 1442
Method source code: 
    public void test76() throws Throwable {
        if (debug)
            System.out.format("%n%s%n", "RegressionTest0.test76");
        java.io.InputStream inputStream0 = null;
        org.jsoup.parser.Parser parser3 = org.jsoup.parser.Parser.xmlParser();
        org.jsoup.nodes.Document document6 = parser3.parseInput("[#document=*]", "");
        org.jsoup.parser.Parser parser8 = parser3.setTrackErrors(0);
        java.util.List<org.jsoup.parser.ParseError> parseErrorList9 = parser8.getErrors();
        // The following exception was thrown during execution in test generation
        try {
            org.jsoup.nodes.Document document10 = org.jsoup.helper.DataUtil.load(inputStream0, "", "[<html>\n <head></head>\n <body></body>\n</html>, <html>\n <head></head>\n <body></body>\n</html>, <html>\n <head></head>\n <body></body>\n</html>]", parser8);
            org.junit.Assert.fail("Expected exception of type java.lang.NullPointerException; message: null");
        } catch (java.lang.NullPointerException e) {
        // Expected exception.
        }
        org.junit.Assert.assertNotNull(parser3);
        org.junit.Assert.assertNotNull(document6);
        org.junit.Assert.assertNotNull(parser8);
        org.junit.Assert.assertNotNull(parseErrorList9);
    }
Method byte code: 
0: getstatic     #2
3: ifeq          24
6: getstatic     #3
9: ldc           #4
11: iconst_1
12: anewarray     #5
15: dup
16: iconst_0
17: ldc           #214
19: aastore
20: invokevirtual #7
23: pop
24: aconst_null
25: astore_1
26: invokestatic  #41
29: astore_2
30: aload_2
31: ldc           #85
33: ldc           #8
35: invokevirtual #58
38: astore_3
39: aload_2
40: iconst_0
41: invokevirtual #42
44: astore        4
46: aload         4
48: invokevirtual #94
51: astore        5
53: aload_1
54: ldc           #8
56: ldc           #25
58: aload         4
60: invokestatic  #9
63: astore        6
65: ldc           #10
67: invokestatic  #11
70: goto          75
73: astore        6
75: aload_2
76: invokestatic  #46
79: aload_3
80: invokestatic  #46
83: aload         4
85: invokestatic  #46
88: aload         5
90: invokestatic  #46
93: return
Exception table:
from    to  target type
53    70    73   Class java/lang/NullPointerException
Source File: /data/islam/DBT-workbench/resources/subjects/fixed/jsoup/39/src/test/java/org/jsoup/helper/RegressionTest0.java
Bytecode File: /data/islam/DBT-workbench/resources/subjects/fixed/jsoup/39/target/test-classes/org/jsoup/helper/RegressionTest0.class
Class name: RegressionTest0
Method name: test77
Start line: 1445
End line: 1457
Method source code: 
    public void test77() throws Throwable {
        if (debug)
            System.out.format("%n%s%n", "RegressionTest0.test77");
        java.nio.ByteBuffer byteBuffer0 = null;
        org.jsoup.parser.Parser parser3 = null;
        // The following exception was thrown during execution in test generation
        try {
            org.jsoup.nodes.Document document4 = org.jsoup.helper.DataUtil.parseByteData(byteBuffer0, "", "[[:only-of-type*=[:nth-last-child(32n+100)^=*]]^=org.jsoup.select.selector$selectorparseexception: hi!]", parser3);
            org.junit.Assert.fail("Expected exception of type java.lang.IllegalArgumentException; message: Must set charset arg to character set of file to parse. Set to null to attempt to detect from HTML");
        } catch (java.lang.IllegalArgumentException e) {
        // Expected exception.
        }
    }
Method byte code: 
0: getstatic     #2
3: ifeq          24
6: getstatic     #3
9: ldc           #4
11: iconst_1
12: anewarray     #5
15: dup
16: iconst_0
17: ldc           #215
19: aastore
20: invokevirtual #7
23: pop
24: aconst_null
25: astore_1
26: aconst_null
27: astore_2
28: aload_1
29: ldc           #8
31: ldc           #182
33: aload_2
34: invokestatic  #27
37: astore_3
38: ldc           #216
40: invokestatic  #11
43: goto          47
46: astore_3
47: return
Exception table:
from    to  target type
28    43    46   Class java/lang/IllegalArgumentException
Source File: /data/islam/DBT-workbench/resources/subjects/fixed/jsoup/39/src/test/java/org/jsoup/helper/RegressionTest0.java
Bytecode File: /data/islam/DBT-workbench/resources/subjects/fixed/jsoup/39/target/test-classes/org/jsoup/helper/RegressionTest0.class
Class name: RegressionTest0
Method name: test78
Start line: 1460
End line: 1471
Method source code: 
    public void test78() throws Throwable {
        if (debug)
            System.out.format("%n%s%n", "RegressionTest0.test78");
        java.io.File file0 = null;
        // The following exception was thrown during execution in test generation
        try {
            org.jsoup.nodes.Document document3 = org.jsoup.helper.DataUtil.load(file0, "", "*");
            org.junit.Assert.fail("Expected exception of type java.lang.NullPointerException; message: null");
        } catch (java.lang.NullPointerException e) {
        // Expected exception.
        }
    }
Method byte code: 
0: getstatic     #2
3: ifeq          24
6: getstatic     #3
9: ldc           #4
11: iconst_1
12: anewarray     #5
15: dup
16: iconst_0
17: ldc           #217
19: aastore
20: invokevirtual #7
23: pop
24: aconst_null
25: astore_1
26: aload_1
27: ldc           #8
29: ldc           #54
31: invokestatic  #35
34: astore_2
35: ldc           #10
37: invokestatic  #11
40: goto          44
43: astore_2
44: return
Exception table:
from    to  target type
26    40    43   Class java/lang/NullPointerException
Source File: /data/islam/DBT-workbench/resources/subjects/fixed/jsoup/39/src/test/java/org/jsoup/helper/RegressionTest0.java
Bytecode File: /data/islam/DBT-workbench/resources/subjects/fixed/jsoup/39/target/test-classes/org/jsoup/helper/RegressionTest0.class
Class name: RegressionTest0
Method name: test79
Start line: 1474
End line: 1491
Method source code: 
    public void test79() throws Throwable {
        if (debug)
            System.out.format("%n%s%n", "RegressionTest0.test79");
        java.nio.ByteBuffer byteBuffer0 = null;
        org.jsoup.parser.Parser parser3 = org.jsoup.parser.Parser.xmlParser();
        org.jsoup.parser.Parser parser5 = parser3.setTrackErrors((int) (short) 100);
        org.jsoup.nodes.Document document8 = parser5.parseInput(":gt(0)", "#.");
        // The following exception was thrown during execution in test generation
        try {
            org.jsoup.nodes.Document document9 = org.jsoup.helper.DataUtil.parseByteData(byteBuffer0, "#document", ":matchesOwn(null", parser5);
            org.junit.Assert.fail("Expected exception of type java.nio.charset.IllegalCharsetNameException; message: #document");
        } catch (java.nio.charset.IllegalCharsetNameException e) {
        // Expected exception.
        }
        org.junit.Assert.assertNotNull(parser3);
        org.junit.Assert.assertNotNull(parser5);
        org.junit.Assert.assertNotNull(document8);
    }
Method byte code: 
0: getstatic     #2
3: ifeq          24
6: getstatic     #3
9: ldc           #4
11: iconst_1
12: anewarray     #5
15: dup
16: iconst_0
17: ldc           #218
19: aastore
20: invokevirtual #7
23: pop
24: aconst_null
25: astore_1
26: invokestatic  #41
29: astore_2
30: aload_2
31: bipush        100
33: invokevirtual #42
36: astore_3
37: aload_3
38: ldc           #18
40: ldc           #57
42: invokevirtual #58
45: astore        4
47: aload_1
48: ldc           #26
50: ldc           #177
52: aload_3
53: invokestatic  #27
56: astore        5
58: ldc           #219
60: invokestatic  #11
63: goto          68
66: astore        5
68: aload_2
69: invokestatic  #46
72: aload_3
73: invokestatic  #46
76: aload         4
78: invokestatic  #46
81: return
Exception table:
from    to  target type
47    63    66   Class java/nio/charset/IllegalCharsetNameException
Source File: /data/islam/DBT-workbench/resources/subjects/fixed/jsoup/39/src/test/java/org/jsoup/helper/RegressionTest0.java
Bytecode File: /data/islam/DBT-workbench/resources/subjects/fixed/jsoup/39/target/test-classes/org/jsoup/helper/RegressionTest0.class
Class name: RegressionTest0
Method name: test80
Start line: 1494
End line: 1511
Method source code: 
    public void test80() throws Throwable {
        if (debug)
            System.out.format("%n%s%n", "RegressionTest0.test80");
        java.nio.ByteBuffer byteBuffer0 = null;
        org.jsoup.parser.Parser parser3 = org.jsoup.parser.Parser.xmlParser();
        org.jsoup.parser.Parser parser5 = parser3.setTrackErrors((int) (short) 100);
        java.util.List<org.jsoup.parser.ParseError> parseErrorList6 = parser5.getErrors();
        // The following exception was thrown during execution in test generation
        try {
            org.jsoup.nodes.Document document7 = org.jsoup.helper.DataUtil.parseByteData(byteBuffer0, "[^#text]", "[<html> <head></head> <body></body> </html>, <html> <head></head> <body></body> </html>, <html> <head></head> <body></body> </html>, <html> <head></head> <body></body> </html>]", parser5);
            org.junit.Assert.fail("Expected exception of type java.nio.charset.IllegalCharsetNameException; message: [^#text]");
        } catch (java.nio.charset.IllegalCharsetNameException e) {
        // Expected exception.
        }
        org.junit.Assert.assertNotNull(parser3);
        org.junit.Assert.assertNotNull(parser5);
        org.junit.Assert.assertNull(parseErrorList6);
    }
Method byte code: 
0: getstatic     #2
3: ifeq          24
6: getstatic     #3
9: ldc           #4
11: iconst_1
12: anewarray     #5
15: dup
16: iconst_0
17: ldc           #220
19: aastore
20: invokevirtual #7
23: pop
24: aconst_null
25: astore_1
26: invokestatic  #41
29: astore_2
30: aload_2
31: bipush        100
33: invokevirtual #42
36: astore_3
37: aload_3
38: invokevirtual #94
41: astore        4
43: aload_1
44: ldc           #221
46: ldc           #222
48: aload_3
49: invokestatic  #27
52: astore        5
54: ldc           #223
56: invokestatic  #11
59: goto          64
62: astore        5
64: aload_2
65: invokestatic  #46
68: aload_3
69: invokestatic  #46
72: aload         4
74: invokestatic  #16
77: return
Exception table:
from    to  target type
43    59    62   Class java/nio/charset/IllegalCharsetNameException
Source File: /data/islam/DBT-workbench/resources/subjects/fixed/jsoup/39/src/test/java/org/jsoup/helper/RegressionTest0.java
Bytecode File: /data/islam/DBT-workbench/resources/subjects/fixed/jsoup/39/target/test-classes/org/jsoup/helper/RegressionTest0.class
Class name: RegressionTest0
Method name: test81
Start line: 1514
End line: 1525
Method source code: 
    public void test81() throws Throwable {
        if (debug)
            System.out.format("%n%s%n", "RegressionTest0.test81");
        java.io.InputStream inputStream0 = null;
        // The following exception was thrown during execution in test generation
        try {
            org.jsoup.nodes.Document document3 = org.jsoup.helper.DataUtil.load(inputStream0, "<html>\n <head></head>\n <body>\n  hi!\n </body>\n</html>", "##.");
            org.junit.Assert.fail("Expected exception of type java.lang.NullPointerException; message: null");
        } catch (java.lang.NullPointerException e) {
        // Expected exception.
        }
    }
Method byte code: 
0: getstatic     #2
3: ifeq          24
6: getstatic     #3
9: ldc           #4
11: iconst_1
12: anewarray     #5
15: dup
16: iconst_0
17: ldc           #224
19: aastore
20: invokevirtual #7
23: pop
24: aconst_null
25: astore_1
26: aload_1
27: ldc           #225
29: ldc           #203
31: invokestatic  #23
34: astore_2
35: ldc           #10
37: invokestatic  #11
40: goto          44
43: astore_2
44: return
Exception table:
from    to  target type
26    40    43   Class java/lang/NullPointerException
Source File: /data/islam/DBT-workbench/resources/subjects/fixed/jsoup/39/src/test/java/org/jsoup/helper/RegressionTest0.java
Bytecode File: /data/islam/DBT-workbench/resources/subjects/fixed/jsoup/39/target/test-classes/org/jsoup/helper/RegressionTest0.class
Class name: RegressionTest0
Method name: test82
Start line: 1528
End line: 1539
Method source code: 
    public void test82() throws Throwable {
        if (debug)
            System.out.format("%n%s%n", "RegressionTest0.test82");
        java.io.File file0 = null;
        // The following exception was thrown during execution in test generation
        try {
            org.jsoup.nodes.Document document3 = org.jsoup.helper.DataUtil.load(file0, ":only-child", ":eq(-1)");
            org.junit.Assert.fail("Expected exception of type java.lang.NullPointerException; message: null");
        } catch (java.lang.NullPointerException e) {
        // Expected exception.
        }
    }
Method byte code: 
0: getstatic     #2
3: ifeq          24
6: getstatic     #3
9: ldc           #4
11: iconst_1
12: anewarray     #5
15: dup
16: iconst_0
17: ldc           #226
19: aastore
20: invokevirtual #7
23: pop
24: aconst_null
25: astore_1
26: aload_1
27: ldc           #44
29: ldc           #227
31: invokestatic  #35
34: astore_2
35: ldc           #10
37: invokestatic  #11
40: goto          44
43: astore_2
44: return
Exception table:
from    to  target type
26    40    43   Class java/lang/NullPointerException
Source File: /data/islam/DBT-workbench/resources/subjects/fixed/jsoup/39/src/test/java/org/jsoup/helper/RegressionTest0.java
Bytecode File: /data/islam/DBT-workbench/resources/subjects/fixed/jsoup/39/target/test-classes/org/jsoup/helper/RegressionTest0.class
Class name: RegressionTest0
Method name: test83
Start line: 1542
End line: 1567
Method source code: 
    public void test83() throws Throwable {
        if (debug)
            System.out.format("%n%s%n", "RegressionTest0.test83");
        java.io.InputStream inputStream0 = null;
        org.jsoup.parser.Parser parser3 = org.jsoup.parser.Parser.xmlParser();
        org.jsoup.parser.Parser parser5 = parser3.setTrackErrors((int) (short) 100);
        boolean boolean6 = parser5.isTrackErrors();
        org.jsoup.parser.Parser parser8 = parser5.setTrackErrors((int) 'a');
        boolean boolean9 = parser8.isTrackErrors();
        boolean boolean10 = parser8.isTrackErrors();
        org.jsoup.nodes.Document document13 = parser8.parseInput(":eq(40)", ".#.");
        // The following exception was thrown during execution in test generation
        try {
            org.jsoup.nodes.Document document14 = org.jsoup.helper.DataUtil.load(inputStream0, "html", ".", parser8);
            org.junit.Assert.fail("Expected exception of type java.lang.NullPointerException; message: null");
        } catch (java.lang.NullPointerException e) {
        // Expected exception.
        }
        org.junit.Assert.assertNotNull(parser3);
        org.junit.Assert.assertNotNull(parser5);
        org.junit.Assert.assertTrue("'" + boolean6 + "' != '" + true + "'", boolean6 == true);
        org.junit.Assert.assertNotNull(parser8);
        org.junit.Assert.assertTrue("'" + boolean9 + "' != '" + true + "'", boolean9 == true);
        org.junit.Assert.assertTrue("'" + boolean10 + "' != '" + true + "'", boolean10 == true);
        org.junit.Assert.assertNotNull(document13);
    }
Method byte code: 
0: getstatic     #2
3: ifeq          24
6: getstatic     #3
9: ldc           #4
11: iconst_1
12: anewarray     #5
15: dup
16: iconst_0
17: ldc           #228
19: aastore
20: invokevirtual #7
23: pop
24: aconst_null
25: astore_1
26: invokestatic  #41
29: astore_2
30: aload_2
31: bipush        100
33: invokevirtual #42
36: astore_3
37: aload_3
38: invokevirtual #105
41: istore        4
43: aload_3
44: bipush        97
46: invokevirtual #42
49: astore        5
51: aload         5
53: invokevirtual #105
56: istore        6
58: aload         5
60: invokevirtual #105
63: istore        7
65: aload         5
67: ldc           #229
69: ldc           #230
71: invokevirtual #58
74: astore        8
76: aload_1
77: ldc           #231
79: ldc           #22
81: aload         5
83: invokestatic  #9
86: astore        9
88: ldc           #10
90: invokestatic  #11
93: goto          98
96: astore        9
98: aload_2
99: invokestatic  #46
102: aload_3
103: invokestatic  #46
106: new           #108
109: dup
110: invokespecial #109
113: ldc           #110
115: invokevirtual #111
118: iload         4
120: invokevirtual #112
123: ldc           #113
125: invokevirtual #111
128: iconst_1
129: invokevirtual #112
132: ldc           #110
134: invokevirtual #111
137: invokevirtual #114
140: iload         4
142: iconst_1
143: if_icmpne     150
146: iconst_1
147: goto          151
150: iconst_0
151: invokestatic  #115
154: aload         5
156: invokestatic  #46
159: new           #108
162: dup
163: invokespecial #109
166: ldc           #110
168: invokevirtual #111
171: iload         6
173: invokevirtual #112
176: ldc           #113
178: invokevirtual #111
181: iconst_1
182: invokevirtual #112
185: ldc           #110
187: invokevirtual #111
190: invokevirtual #114
193: iload         6
195: iconst_1
196: if_icmpne     203
199: iconst_1
200: goto          204
203: iconst_0
204: invokestatic  #115
207: new           #108
210: dup
211: invokespecial #109
214: ldc           #110
216: invokevirtual #111
219: iload         7
221: invokevirtual #112
224: ldc           #113
226: invokevirtual #111
229: iconst_1
230: invokevirtual #112
233: ldc           #110
235: invokevirtual #111
238: invokevirtual #114
241: iload         7
243: iconst_1
244: if_icmpne     251
247: iconst_1
248: goto          252
251: iconst_0
252: invokestatic  #115
255: aload         8
257: invokestatic  #46
260: return
Exception table:
from    to  target type
76    93    96   Class java/lang/NullPointerException
Source File: /data/islam/DBT-workbench/resources/subjects/fixed/jsoup/39/src/test/java/org/jsoup/helper/RegressionTest0.java
Bytecode File: /data/islam/DBT-workbench/resources/subjects/fixed/jsoup/39/target/test-classes/org/jsoup/helper/RegressionTest0.class
Class name: RegressionTest0
Method name: test84
Start line: 1570
End line: 1575
Method source code: 
    public void test84() throws Throwable {
        if (debug)
            System.out.format("%n%s%n", "RegressionTest0.test84");
        java.lang.String str1 = org.jsoup.helper.DataUtil.getCharsetFromContentType("a");
        org.junit.Assert.assertNull(str1);
    }
Method byte code: 
0: getstatic     #2
3: ifeq          24
6: getstatic     #3
9: ldc           #4
11: iconst_1
12: anewarray     #5
15: dup
16: iconst_0
17: ldc           #232
19: aastore
20: invokevirtual #7
23: pop
24: ldc           #233
26: invokestatic  #15
29: astore_1
30: aload_1
31: invokestatic  #16
34: return
Source File: /data/islam/DBT-workbench/resources/subjects/fixed/jsoup/39/src/test/java/org/jsoup/helper/RegressionTest0.java
Bytecode File: /data/islam/DBT-workbench/resources/subjects/fixed/jsoup/39/target/test-classes/org/jsoup/helper/RegressionTest0.class
Class name: RegressionTest0
Method name: test85
Start line: 1578
End line: 1597
Method source code: 
    public void test85() throws Throwable {
        if (debug)
            System.out.format("%n%s%n", "RegressionTest0.test85");
        java.io.InputStream inputStream0 = null;
        org.jsoup.parser.Parser parser3 = org.jsoup.parser.Parser.xmlParser();
        org.jsoup.parser.Parser parser5 = parser3.setTrackErrors((int) (short) 100);
        org.jsoup.nodes.Document document8 = parser3.parseInput("UTF-8", "<html> <head></head> <body></body> </html> <html> <head></head> <body></body> </html> <html> <head></head> <body></body> </html> <html> <head></head> <body></body> </html>");
        org.jsoup.nodes.Document document11 = parser3.parseInput(":empty", ":matches(null");
        // The following exception was thrown during execution in test generation
        try {
            org.jsoup.nodes.Document document12 = org.jsoup.helper.DataUtil.load(inputStream0, "[^<hi!></hi!>]", ":empty", parser3);
            org.junit.Assert.fail("Expected exception of type java.lang.NullPointerException; message: null");
        } catch (java.lang.NullPointerException e) {
        // Expected exception.
        }
        org.junit.Assert.assertNotNull(parser3);
        org.junit.Assert.assertNotNull(parser5);
        org.junit.Assert.assertNotNull(document8);
        org.junit.Assert.assertNotNull(document11);
    }
Method byte code: 
0: getstatic     #2
3: ifeq          24
6: getstatic     #3
9: ldc           #4
11: iconst_1
12: anewarray     #5
15: dup
16: iconst_0
17: ldc           #234
19: aastore
20: invokevirtual #7
23: pop
24: aconst_null
25: astore_1
26: invokestatic  #41
29: astore_2
30: aload_2
31: bipush        100
33: invokevirtual #42
36: astore_3
37: aload_2
38: ldc           #34
40: ldc           #64
42: invokevirtual #58
45: astore        4
47: aload_2
48: ldc           #65
50: ldc           #55
52: invokevirtual #58
55: astore        5
57: aload_1
58: ldc           #235
60: ldc           #65
62: aload_2
63: invokestatic  #9
66: astore        6
68: ldc           #10
70: invokestatic  #11
73: goto          78
76: astore        6
78: aload_2
79: invokestatic  #46
82: aload_3
83: invokestatic  #46
86: aload         4
88: invokestatic  #46
91: aload         5
93: invokestatic  #46
96: return
Exception table:
from    to  target type
57    73    76   Class java/lang/NullPointerException
Source File: /data/islam/DBT-workbench/resources/subjects/fixed/jsoup/39/src/test/java/org/jsoup/helper/RegressionTest0.java
Bytecode File: /data/islam/DBT-workbench/resources/subjects/fixed/jsoup/39/target/test-classes/org/jsoup/helper/RegressionTest0.class
Class name: RegressionTest0
Method name: test86
Start line: 1600
End line: 1617
Method source code: 
    public void test86() throws Throwable {
        if (debug)
            System.out.format("%n%s%n", "RegressionTest0.test86");
        java.nio.ByteBuffer byteBuffer0 = null;
        org.jsoup.parser.Parser parser3 = org.jsoup.parser.Parser.xmlParser();
        org.jsoup.parser.Parser parser5 = parser3.setTrackErrors((int) '#');
        org.jsoup.nodes.Document document8 = parser5.parseInput(" text=\":gt(0)\"", "#text");
        // The following exception was thrown during execution in test generation
        try {
            org.jsoup.nodes.Document document9 = org.jsoup.helper.DataUtil.parseByteData(byteBuffer0, "", "<body class=\" #:only-of-type\">\n [   ,    ,    ]\n</body>", parser5);
            org.junit.Assert.fail("Expected exception of type java.lang.IllegalArgumentException; message: Must set charset arg to character set of file to parse. Set to null to attempt to detect from HTML");
        } catch (java.lang.IllegalArgumentException e) {
        // Expected exception.
        }
        org.junit.Assert.assertNotNull(parser3);
        org.junit.Assert.assertNotNull(parser5);
        org.junit.Assert.assertNotNull(document8);
    }
Method byte code: 
0: getstatic     #2
3: ifeq          24
6: getstatic     #3
9: ldc           #4
11: iconst_1
12: anewarray     #5
15: dup
16: iconst_0
17: ldc           #236
19: aastore
20: invokevirtual #7
23: pop
24: aconst_null
25: astore_1
26: invokestatic  #41
29: astore_2
30: aload_2
31: bipush        35
33: invokevirtual #42
36: astore_3
37: aload_3
38: ldc           #84
40: ldc           #59
42: invokevirtual #58
45: astore        4
47: aload_1
48: ldc           #8
50: ldc           #237
52: aload_3
53: invokestatic  #27
56: astore        5
58: ldc           #216
60: invokestatic  #11
63: goto          68
66: astore        5
68: aload_2
69: invokestatic  #46
72: aload_3
73: invokestatic  #46
76: aload         4
78: invokestatic  #46
81: return
Exception table:
from    to  target type
47    63    66   Class java/lang/IllegalArgumentException
Source File: /data/islam/DBT-workbench/resources/subjects/fixed/jsoup/39/src/test/java/org/jsoup/helper/DataUtilTest.java
Bytecode File: /data/islam/DBT-workbench/resources/subjects/fixed/jsoup/39/target/test-classes/org/jsoup/helper/DataUtilTest.class
Class name: DataUtilTest
Method name: testCharset
Start line: 13
End line: 20
Method source code: 
    public void testCharset() {
        assertEquals("utf-8", DataUtil.getCharsetFromContentType("text/html;charset=utf-8 "));
        assertEquals("UTF-8", DataUtil.getCharsetFromContentType("text/html; charset=UTF-8"));
        assertEquals("ISO-8859-1", DataUtil.getCharsetFromContentType("text/html; charset=ISO-8859-1"));
        assertEquals(null, DataUtil.getCharsetFromContentType("text/html"));
        assertEquals(null, DataUtil.getCharsetFromContentType(null));
        assertEquals(null, DataUtil.getCharsetFromContentType("text/html;charset=Unknown"));
    }
Method byte code: 
0: ldc           #2
2: ldc           #3
4: invokestatic  #4
7: invokestatic  #5
10: ldc           #6
12: ldc           #7
14: invokestatic  #4
17: invokestatic  #5
20: ldc           #8
22: ldc           #9
24: invokestatic  #4
27: invokestatic  #5
30: aconst_null
31: ldc           #10
33: invokestatic  #4
36: invokestatic  #5
39: aconst_null
40: aconst_null
41: invokestatic  #4
44: invokestatic  #5
47: aconst_null
48: ldc           #11
50: invokestatic  #4
53: invokestatic  #5
56: return
Source File: /data/islam/DBT-workbench/resources/subjects/fixed/jsoup/39/src/test/java/org/jsoup/helper/DataUtilTest.java
Bytecode File: /data/islam/DBT-workbench/resources/subjects/fixed/jsoup/39/target/test-classes/org/jsoup/helper/DataUtilTest.class
Class name: DataUtilTest
Method name: testQuotedCharset
Start line: 22
End line: 28
Method source code: 
    @Test public void testQuotedCharset() {
        assertEquals("utf-8", DataUtil.getCharsetFromContentType("text/html; charset=\"utf-8\""));
        assertEquals("UTF-8", DataUtil.getCharsetFromContentType("text/html;charset=\"UTF-8\""));
        assertEquals("ISO-8859-1", DataUtil.getCharsetFromContentType("text/html; charset=\"ISO-8859-1\""));
        assertEquals(null, DataUtil.getCharsetFromContentType("text/html; charset=\"Unsupported\""));
        assertEquals("UTF-8", DataUtil.getCharsetFromContentType("text/html; charset='UTF-8'"));
    }
Method byte code: 
0: ldc           #2
2: ldc           #12
4: invokestatic  #4
7: invokestatic  #5
10: ldc           #6
12: ldc           #13
14: invokestatic  #4
17: invokestatic  #5
20: ldc           #8
22: ldc           #14
24: invokestatic  #4
27: invokestatic  #5
30: aconst_null
31: ldc           #15
33: invokestatic  #4
36: invokestatic  #5
39: ldc           #6
41: ldc           #16
43: invokestatic  #4
46: invokestatic  #5
49: return
Source File: /data/islam/DBT-workbench/resources/subjects/fixed/jsoup/39/src/test/java/org/jsoup/helper/DataUtilTest.java
Bytecode File: /data/islam/DBT-workbench/resources/subjects/fixed/jsoup/39/target/test-classes/org/jsoup/helper/DataUtilTest.class
Class name: DataUtilTest
Method name: discardsSpuriousByteOrderMark
Start line: 30
End line: 35
Method source code: 
    @Test public void discardsSpuriousByteOrderMark() {
        String html = "\uFEFF<html><head><title>One</title></head><body>Two</body></html>";
        ByteBuffer buffer = Charset.forName("UTF-8").encode(html);
        Document doc = DataUtil.parseByteData(buffer, "UTF-8", "http://foo.com/", Parser.htmlParser());
        assertEquals("One", doc.head().text());
    }
Method byte code: 
0: ldc           #17
2: astore_1
3: ldc           #6
5: invokestatic  #18
8: aload_1
9: invokevirtual #19
12: astore_2
13: aload_2
14: ldc           #6
16: ldc           #20
18: invokestatic  #21
21: invokestatic  #22
24: astore_3
25: ldc           #23
27: aload_3
28: invokevirtual #24
31: invokevirtual #25
34: invokestatic  #5
37: return
Source File: /data/islam/DBT-workbench/resources/subjects/fixed/jsoup/39/src/test/java/org/jsoup/helper/DataUtilTest.java
Bytecode File: /data/islam/DBT-workbench/resources/subjects/fixed/jsoup/39/target/test-classes/org/jsoup/helper/DataUtilTest.class
Class name: DataUtilTest
Method name: discardsSpuriousByteOrderMarkWhenNoCharsetSet
Start line: 37
End line: 43
Method source code: 
    @Test public void discardsSpuriousByteOrderMarkWhenNoCharsetSet() {
        String html = "\uFEFF<html><head><title>One</title></head><body>Two</body></html>";
        ByteBuffer buffer = Charset.forName("UTF-8").encode(html);
        Document doc = DataUtil.parseByteData(buffer, null, "http://foo.com/", Parser.htmlParser());
        assertEquals("One", doc.head().text());
        assertEquals("UTF-8", doc.outputSettings().charset().displayName());
    }
Method byte code: 
0: ldc           #17
2: astore_1
3: ldc           #6
5: invokestatic  #18
8: aload_1
9: invokevirtual #19
12: astore_2
13: aload_2
14: aconst_null
15: ldc           #20
17: invokestatic  #21
20: invokestatic  #22
23: astore_3
24: ldc           #23
26: aload_3
27: invokevirtual #24
30: invokevirtual #25
33: invokestatic  #5
36: ldc           #6
38: aload_3
39: invokevirtual #26
42: invokevirtual #27
45: invokevirtual #28
48: invokestatic  #5
51: return
Source File: /data/islam/DBT-workbench/resources/subjects/fixed/jsoup/39/src/test/java/org/jsoup/helper/DataUtilTest.java
Bytecode File: /data/islam/DBT-workbench/resources/subjects/fixed/jsoup/39/target/test-classes/org/jsoup/helper/DataUtilTest.class
Class name: DataUtilTest
Method name: shouldNotThrowExceptionOnEmptyCharset
Start line: 46
End line: 49
Method source code: 
    public void shouldNotThrowExceptionOnEmptyCharset() {
        assertEquals(null, DataUtil.getCharsetFromContentType("text/html; charset="));
        assertEquals(null, DataUtil.getCharsetFromContentType("text/html; charset=;"));
    }
Method byte code: 
0: aconst_null
1: ldc           #29
3: invokestatic  #4
6: invokestatic  #5
9: aconst_null
10: ldc           #30
12: invokestatic  #4
15: invokestatic  #5
18: return
Source File: /data/islam/DBT-workbench/resources/subjects/fixed/jsoup/39/src/test/java/org/jsoup/helper/DataUtilTest.java
Bytecode File: /data/islam/DBT-workbench/resources/subjects/fixed/jsoup/39/target/test-classes/org/jsoup/helper/DataUtilTest.class
Class name: DataUtilTest
Method name: shouldSelectFirstCharsetOnWeirdMultileCharsetsInMetaTags
Start line: 52
End line: 54
Method source code: 
    public void shouldSelectFirstCharsetOnWeirdMultileCharsetsInMetaTags() {
        assertEquals("ISO-8859-1", DataUtil.getCharsetFromContentType("text/html; charset=ISO-8859-1, charset=1251"));
    }
Method byte code: 
0: ldc           #8
2: ldc           #31
4: invokestatic  #4
7: invokestatic  #5
10: return
Source File: /data/islam/DBT-workbench/resources/subjects/fixed/jsoup/39/src/test/java/org/jsoup/helper/DataUtilTest.java
Bytecode File: /data/islam/DBT-workbench/resources/subjects/fixed/jsoup/39/target/test-classes/org/jsoup/helper/DataUtilTest.class
Class name: DataUtilTest
Method name: shouldCorrectCharsetForDuplicateCharsetString
Start line: 57
End line: 59
Method source code: 
    public void shouldCorrectCharsetForDuplicateCharsetString() {
        assertEquals("iso-8859-1", DataUtil.getCharsetFromContentType("text/html; charset=charset=iso-8859-1"));
    }
Method byte code: 
0: ldc           #32
2: ldc           #33
4: invokestatic  #4
7: invokestatic  #5
10: return
Source File: /data/islam/DBT-workbench/resources/subjects/fixed/jsoup/39/src/test/java/org/jsoup/helper/DataUtilTest.java
Bytecode File: /data/islam/DBT-workbench/resources/subjects/fixed/jsoup/39/target/test-classes/org/jsoup/helper/DataUtilTest.class
Class name: DataUtilTest
Method name: shouldReturnNullForIllegalCharsetNames
Start line: 62
End line: 64
Method source code: 
    public void shouldReturnNullForIllegalCharsetNames() {
        assertEquals(null, DataUtil.getCharsetFromContentType("text/html; charset=$HJKDF§$/("));
    }
Method byte code: 
0: aconst_null
1: ldc           #34
3: invokestatic  #4
6: invokestatic  #5
9: return
}
Source File: /data/islam/DBT-workbench/resources/subjects/fixed/jsoup/39/src/test/java/org/jsoup/helper/DataUtil_ESTest.java
Bytecode File: /data/islam/DBT-workbench/resources/subjects/fixed/jsoup/39/target/test-classes/org/jsoup/helper/DataUtil_ESTest.class
Class name: DataUtil_ESTest
Method name: test00
Start line: 29
End line: 41
Method source code: 
  public void test00()  throws Throwable  {
      // Undeclared exception!
      try { 
        DataUtil.load((InputStream) null, "open", "open");
        fail("Expecting exception: NullPointerException");
      
      } catch(NullPointerException e) {
         //
         // no message in exception (getMessage() returned null)
         //
         verifyException("org.jsoup.helper.DataUtil", e);
      }
  }
Method byte code: 
0: aconst_null
1: checkcast     #2
4: ldc           #3
6: ldc           #3
8: invokestatic  #4
11: pop
12: ldc           #5
14: invokestatic  #6
17: goto          27
20: astore_1
21: ldc           #8
23: aload_1
24: invokestatic  #9
27: return
Exception table:
from    to  target type
0    17    20   Class java/lang/NullPointerException
Source File: /data/islam/DBT-workbench/resources/subjects/fixed/jsoup/39/src/test/java/org/jsoup/helper/DataUtil_ESTest.java
Bytecode File: /data/islam/DBT-workbench/resources/subjects/fixed/jsoup/39/target/test-classes/org/jsoup/helper/DataUtil_ESTest.class
Class name: DataUtil_ESTest
Method name: test01
Start line: 44
End line: 48
Method source code: 
  public void test01()  throws Throwable  {
      Parser parser0 = Parser.xmlParser();
      // Undeclared exception!
      try { 
        DataUtil.load((InputStream) null, "E/mK.By}a", "E/mK.By}a", parser0);
Method byte code: 
0: invokestatic  #10
3: astore_1
4: aconst_null
5: checkcast     #2
8: ldc           #11
10: ldc           #11
12: aload_1
13: invokestatic  #12
16: pop
17: ldc           #5
19: invokestatic  #6
22: goto          32
25: astore_2
26: ldc           #8
28: aload_2
29: invokestatic  #9
32: return
Exception table:
from    to  target type
4    22    25   Class java/lang/NullPointerException
Source File: /data/islam/DBT-workbench/resources/subjects/fixed/jsoup/39/src/test/java/org/jsoup/helper/DataUtil_ESTest.java
Bytecode File: /data/islam/DBT-workbench/resources/subjects/fixed/jsoup/39/target/test-classes/org/jsoup/helper/DataUtil_ESTest.class
Class name: DataUtil_ESTest
Method name: test02
Start line: 60
End line: 72
Method source code: 
  public void test02()  throws Throwable  {
      MockFile mockFile0 = new MockFile("v");
      try { 
        DataUtil.load((File) mockFile0, "~", "~");
        fail("Expecting exception: FileNotFoundException");
      
      } catch(FileNotFoundException e) {
         //
         // no message in exception (getMessage() returned null)
         //
         verifyException("org.evosuite.runtime.mock.java.io.MockFileInputStream", e);
      }
  }
Method byte code: 
0: new           #13
3: dup
4: ldc           #14
6: invokespecial #15
9: astore_1
10: aload_1
11: ldc           #16
13: ldc           #16
15: invokestatic  #17
18: pop
19: ldc           #18
21: invokestatic  #6
24: goto          34
27: astore_2
28: ldc           #20
30: aload_2
31: invokestatic  #9
34: return
Exception table:
from    to  target type
10    24    27   Class java/io/FileNotFoundException
Source File: /data/islam/DBT-workbench/resources/subjects/fixed/jsoup/39/src/test/java/org/jsoup/helper/DataUtil_ESTest.java
Bytecode File: /data/islam/DBT-workbench/resources/subjects/fixed/jsoup/39/target/test-classes/org/jsoup/helper/DataUtil_ESTest.class
Class name: DataUtil_ESTest
Method name: test03
Start line: 75
End line: 88
Method source code: 
  public void test03()  throws Throwable  {
      File file0 = MockFile.createTempFile(", currentElement=", ", currentElement=");
      // Undeclared exception!
      try { 
        DataUtil.load(file0, ", currentElement=", ", currentElement=");
        fail("Expecting exception: IllegalCharsetNameException");
      
      } catch(IllegalCharsetNameException e) {
         //
         // , currentElement=
         //
         verifyException("java.nio.charset.Charset", e);
      }
  }
Method byte code: 
0: ldc           #21
2: ldc           #21
4: invokestatic  #22
7: astore_1
8: aload_1
9: ldc           #21
11: ldc           #21
13: invokestatic  #17
16: pop
17: ldc           #23
19: invokestatic  #6
22: goto          32
25: astore_2
26: ldc           #25
28: aload_2
29: invokestatic  #9
32: return
Exception table:
from    to  target type
8    22    25   Class java/nio/charset/IllegalCharsetNameException
Source File: /data/islam/DBT-workbench/resources/subjects/fixed/jsoup/39/src/test/java/org/jsoup/helper/DataUtil_ESTest.java
Bytecode File: /data/islam/DBT-workbench/resources/subjects/fixed/jsoup/39/target/test-classes/org/jsoup/helper/DataUtil_ESTest.class
Class name: DataUtil_ESTest
Method name: test04
Start line: 91
End line: 0
Method source code: 
  public void test04()  throws Throwable  {
      File file0 = MockFile.createTempFile("char{set=", "char{set=");
      EvoSuiteFile evoSuiteFile0 = new EvoSuiteFile("/tmp/char{set=0char{set=");
      FileSystemHandling.appendLineToFile(evoSuiteFile0, "char{set=");
      Document document0 = DataUtil.load(file0, (String) null, "char{set=");
      assertEquals("char{set=", document0.location());
  }
Method byte code: 
0: ldc           #26
2: ldc           #26
4: invokestatic  #22
7: astore_1
8: new           #27
11: dup
12: ldc           #28
14: invokespecial #29
17: astore_2
18: aload_2
19: ldc           #26
21: invokestatic  #30
24: pop
25: aload_1
26: aconst_null
27: checkcast     #31
30: ldc           #26
32: invokestatic  #17
35: astore_3
36: ldc           #26
38: aload_3
39: invokevirtual #32
42: invokestatic  #33
45: return
Source File: /data/islam/DBT-workbench/resources/subjects/fixed/jsoup/39/src/test/java/org/jsoup/helper/DataUtil_ESTest.java
Bytecode File: /data/islam/DBT-workbench/resources/subjects/fixed/jsoup/39/target/test-classes/org/jsoup/helper/DataUtil_ESTest.class
Class name: DataUtil_ESTest
Method name: test05
Start line: 100
End line: 0
Method source code: 
  public void test05()  throws Throwable  {
      File file0 = MockFile.createTempFile("HkS7}&M>r", "HkS7}&M>r");
      Document document0 = DataUtil.load(file0, "UTF-8", "HkS7}&M>r");
      assertEquals("HkS7}&M>r", document0.baseUri());
  }
Method byte code: 
0: ldc           #34
2: ldc           #34
4: invokestatic  #22
7: astore_1
8: aload_1
9: ldc           #35
11: ldc           #34
13: invokestatic  #17
16: astore_2
17: ldc           #34
19: aload_2
20: invokevirtual #36
23: invokestatic  #33
26: return
Source File: /data/islam/DBT-workbench/resources/subjects/fixed/jsoup/39/src/test/java/org/jsoup/helper/DataUtil_ESTest.java
Bytecode File: /data/islam/DBT-workbench/resources/subjects/fixed/jsoup/39/target/test-classes/org/jsoup/helper/DataUtil_ESTest.class
Class name: DataUtil_ESTest
Method name: test06
Start line: 107
End line: 120
Method source code: 
  public void test06()  throws Throwable  {
      PipedInputStream pipedInputStream0 = new PipedInputStream();
      // Undeclared exception!
      try { 
        DataUtil.readToByteBuffer(pipedInputStream0, (-694));
        fail("Expecting exception: IllegalArgumentException");
      
      } catch(IllegalArgumentException e) {
         //
         // maxSize must be 0 (unlimited) or larger
         //
         verifyException("org.jsoup.helper.Validate", e);
      }
  }
Method byte code: 
0: new           #37
3: dup
4: invokespecial #38
7: astore_1
8: aload_1
9: sipush        -694
12: invokestatic  #39
15: pop
16: ldc           #40
18: invokestatic  #6
21: goto          31
24: astore_2
25: ldc           #42
27: aload_2
28: invokestatic  #9
31: return
Exception table:
from    to  target type
8    21    24   Class java/lang/IllegalArgumentException
Source File: /data/islam/DBT-workbench/resources/subjects/fixed/jsoup/39/src/test/java/org/jsoup/helper/DataUtil_ESTest.java
Bytecode File: /data/islam/DBT-workbench/resources/subjects/fixed/jsoup/39/target/test-classes/org/jsoup/helper/DataUtil_ESTest.class
Class name: DataUtil_ESTest
Method name: test07
Start line: 123
End line: 129
Method source code: 
  public void test07()  throws Throwable  {
      byte[] byteArray0 = new byte[20];
      ByteArrayInputStream byteArrayInputStream0 = new ByteArrayInputStream(byteArray0);
      ByteBuffer byteBuffer0 = DataUtil.readToByteBuffer(byteArrayInputStream0, 17);
      assertEquals(0, byteArrayInputStream0.available());
      assertEquals("java.nio.HeapByteBuffer[pos=0 lim=17 cap=17]", byteBuffer0.toString());
  }
Method byte code: 
0: bipush        20
2: newarray       byte
4: astore_1
5: new           #43
8: dup
9: aload_1
10: invokespecial #44
13: astore_2
14: aload_2
15: bipush        17
17: invokestatic  #39
20: astore_3
21: lconst_0
22: aload_2
23: invokevirtual #45
26: i2l
27: invokestatic  #46
30: ldc           #47
32: aload_3
33: invokevirtual #48
36: invokestatic  #33
39: return
Source File: /data/islam/DBT-workbench/resources/subjects/fixed/jsoup/39/src/test/java/org/jsoup/helper/DataUtil_ESTest.java
Bytecode File: /data/islam/DBT-workbench/resources/subjects/fixed/jsoup/39/target/test-classes/org/jsoup/helper/DataUtil_ESTest.class
Class name: DataUtil_ESTest
Method name: test08
Start line: 132
End line: 137
Method source code: 
  public void test08()  throws Throwable  {
      byte[] byteArray0 = new byte[1];
      ByteArrayInputStream byteArrayInputStream0 = new ByteArrayInputStream(byteArray0);
      ByteBuffer byteBuffer0 = DataUtil.readToByteBuffer(byteArrayInputStream0, 509);
      assertEquals(1, byteBuffer0.limit());
  }
Method byte code: 
0: iconst_1
1: newarray       byte
3: astore_1
4: new           #43
7: dup
8: aload_1
9: invokespecial #44
12: astore_2
13: aload_2
14: sipush        509
17: invokestatic  #39
20: astore_3
21: lconst_1
22: aload_3
23: invokevirtual #49
26: i2l
27: invokestatic  #46
30: return
Source File: /data/islam/DBT-workbench/resources/subjects/fixed/jsoup/39/src/test/java/org/jsoup/helper/DataUtil_ESTest.java
Bytecode File: /data/islam/DBT-workbench/resources/subjects/fixed/jsoup/39/target/test-classes/org/jsoup/helper/DataUtil_ESTest.class
Class name: DataUtil_ESTest
Method name: test09
Start line: 140
End line: 141
Method source code: 
  public void test09()  throws Throwable  {
      String string0 = DataUtil.getCharsetFromContentType("kS7}&%M>r");
Method byte code: 
0: ldc           #50
2: invokestatic  #51
5: astore_1
6: aload_1
7: invokestatic  #52
10: return
Source File: /data/islam/DBT-workbench/resources/subjects/fixed/jsoup/39/src/test/java/org/jsoup/helper/DataUtil_ESTest.java
Bytecode File: /data/islam/DBT-workbench/resources/subjects/fixed/jsoup/39/target/test-classes/org/jsoup/helper/DataUtil_ESTest.class
Class name: DataUtil_ESTest
Method name: test10
Start line: 146
End line: 149
Method source code: 
  public void test10()  throws Throwable  {
      String string0 = DataUtil.getCharsetFromContentType((String) null);
      assertNull(string0);
  }
Method byte code: 
0: aconst_null
1: checkcast     #31
4: invokestatic  #51
7: astore_1
8: aload_1
9: invokestatic  #52
12: return
Source File: /data/islam/DBT-workbench/resources/subjects/fixed/jsoup/39/src/test/java/org/jsoup/helper/DataUtil_ESTest.java
Bytecode File: /data/islam/DBT-workbench/resources/subjects/fixed/jsoup/39/target/test-classes/org/jsoup/helper/DataUtil_ESTest.class
Class name: DataUtil_ESTest
Method name: test11
Start line: 152
End line: 155
Method source code: 
  public void test11()  throws Throwable  {
      String string0 = DataUtil.getCharsetFromContentType("charset=");
      assertNull(string0);
  }
Method byte code: 
0: ldc           #53
2: invokestatic  #51
5: astore_1
6: aload_1
7: invokestatic  #52
10: return
}
